Workbook
Name TaxTV: 10%
Name \p: '[1]FA-LISTING'!#REF!
Name BuiltIn_AutoFilter___3: "$"
Name 文件管制作業辦法: "圖片 1"

Sheet DB小板汇总
A1: 6.71 | E1: 币种:USD
A2: 机型 | B2: 日期 | C2: 原汇率 | D2: 料号 | E2: SKU | F2: PCB | G2: PCB | H2: PCB | I2: Others | J2: Others | K2: SMT | L2: TTL | N2: 备注
A3: XN21S | B3: 46081 | C3: 6.837 | D3: A.F.D.2400329-PVT | E3: A.F.D.2400329 RJ45 DB | F3: =6.038/C3/1.13 -> 0.78153618 | G3: 0.93784341 | H3: 1.0316278 | I3: 3.41 | J3: =I3*1.05 -> 3.5805 | K3: 0.4 | L3: =SUBTOTAL(109,H3,J3,K3) -> 5.0121278 | M3: 3.1 | N3: 含RTL8111H；含GL850G；PS8719ETQFN24GTR2-A0
A4: DA1021C | B4: 46081 | C4: 6.837 | D4: A.F.D.2500004-PVT | E4: A.F.D.2500004 RJ45 DB | F4: 0.41662386 | G4: 0.49994863 | H4: 0.54994349 | I4: 2.6155851 | J4: =I4*1.05 -> 2.7463644 | K4: 0.4 | L4: =SUBTOTAL(109,H4,J4,K4) -> 3.6963079 | M4: 2.3778047 | N4: 含RTL8111H；含GL850G；RTS5170
A5: XN21 | B5: 46285 | C5: 6.7 | D5: A.F.D.2300285 | E5: A.F.D.2300285 RJ45 DB | F5: =4/C5/1.13*1.1 -> 0.58116497 | G5: 0.68865107 | H5: =4.33/C5/1.13 -> 0.57191917 | I5: 2.8349495 | J5: 2.8 | K5: 0.4 | L5: =SUBTOTAL(109,H5,J5,K5) -> 3.7719192 | M5: 2.5772269 | N5: 含有8111H
B6: 20240105 | C6: 6.837 | D6: A.P.10001018 | E6: A.P.10001018 RJ45 DB | F6: 0.72182853 | G6: 0.86619424 | H6: 0.95281366 | I6: 3.3077268 | J6: =I6*1.05 -> 3.4731131 | K6: 0.4 | L6: =SUBTOTAL(109,H6,J6,K6) -> 4.8259268 | M6: 3.0070243 | N6: 8111H
B7: 20241105 | C7: 6.837 | D7: A.F.D.2400048-MP | E7: A.F.D.2400048 USB DB | F7: 0.17745375 | G7: 0.21294449 | H7: 0.23423894 | I7: 1.7055684 | J7: =I7*1.05 -> 1.7908468 | K7: 0.2 | L7: =SUBTOTAL(109,H7,J7,K7) -> 2.2250857 | M7: 1.5505167 | N7: 含有IT66318FN
B8: 20240411 | C8: 6.837 | D8: A.F.D.2400049-MP | E8: A.F.D.2400049 USB DB | F8: 0.16021508 | G8: 0.1922581 | H8: 0.21148391 | I8: 0.65508274 | J8: =I8*1.05 -> 0.68783688 | K8: 0.2 | L8: =SUBTOTAL(109,H8,J8,K8) -> 1.0993208 | M8: 0.59552977
B9: 20240411 | C9: 6.837 | D9: A.F.D.2400058-MP | E9: A.F.D.2400058 TYPEC_DB | F9: 0.33350371 | G9: 0.40020445 | H9: 0.4402249 | I9: 2.691534 | J9: =I9*1.05 -> 2.8261107 | K9: 0.3 | L9: =SUBTOTAL(109,H9,J9,K9) -> 3.5663356 | M9: 2.4468491 | N9: 含有ALC269Q
B10: 20240411 | C10: 6.837 | D10: A.F.D.2400080-MP | E10: A.F.D.2400080 TYPEC_DB | F10: 0.33350371 | G10: 0.40020445 | H10: 0.4402249 | I10: 3.227697 | J10: =I10*1.05 -> 3.3890818 | K10: 0.3 | L10: =SUBTOTAL(109,H10,J10,K10) -> 4.1293067 | M10: 2.93427 | N10: 含有ALC269Q
B11: 20241105 | C11: 6.837 | D11: A.F.D.2300338-MP | E11: A.F.D.2300338 140M_SS_TYPEC_DB | F11: 0.34485622 | G11: 0.41382747 | H11: 0.45521021 | I11: 3.4072901 | J11: =I11*1.05 -> 3.5776546 | K11: 0.4 | L11: =SUBTOTAL(109,H11,J11,K11) -> 4.4328649 | M11: 3.0975365
C12: 6.837 | E12: A.F.D.2300246 140M_SS_TYPEC_DB | F12: 0.4242062 | G12: 0.50904743 | H12: 0.55995218 | I12: 3.5449491 | J12: =I12*1.05 -> 3.7221965 | K12: 0.4 | L12: =SUBTOTAL(109,H12,J12,K12) -> 4.6821487 | M12: 3.222681
A13: AXN88 | C13: 6.837 | E13: A.F.D.2300339 140M-SS_DB | F13: 0.15785612 | G13: 0.18942735 | H13: 0.20837008 | I13: 1.6917892 | J13: =I13*1.05 -> 1.7763787 | K13: 0.2 | L13: =SUBTOTAL(109,H13,J13,K13) -> 2.1847488 | M13: 1.5379902
A14: XN25 | B14: 46122 | C14: 6.837 | D14: A.F.D.2400234-PVT | E14: A.F.D.2400234 TYPEC DB | F14: =0.454147943452342*1.2 -> 0.54497753 | G14: 0.65397304 | H14: 0.71937034 | I14: 1.5036129 | J14: =I14*1.05 -> 1.5787936 | K14: =2.3/C14 -> 0.33640486 | L14: =SUBTOTAL(109,H14,J14,K14) -> 2.6345688 | M14: 1.3669209 | N14: 含有SN6140,
B15: 20250114 | C15: 6.78 | D15: A.F.D.2400198-MP | E15: A.F.D.2400198 RJ45 DB | F15: =5.5/C15/1.13*1.2 -> 0.86146135 | G15: 1.0337536 | H15: 1.137129 | I15: 4.0013867 | J15: =I15*1.05 -> 4.201456 | K15: =2.8/C15 -> 0.41297935 | L15: =SUBTOTAL(109,H15,J15,K15) -> 5.7515643 | M15: 3.6376242 | N15: 含有RTL8111H；ALC269Q；OZ711LV2
C16: 6.837 | E16: A.F.D.2400171 RJ45 DB | F16: 0.53613905 | G16: 0.64336686 | H16: 0.70770355 | I16: 4.0899782 | J16: =I16*1.05 -> 4.2944771 | K16: 0.4 | L16: =SUBTOTAL(109,H16,J16,K16) -> 5.4021806 | M16: 3.718162 | N16: 含有8111H;ALC269Q
A17: DN50Z | B17: 20240625 | C17: 6.837 | D17: A.F.D.2300323-MP | E17: A.F.D.2300323 USB DB | F17: 0.38716667 | G17: 0.4646 | H17: 0.51106 | I17: 3.0333373 | J17: =I17*1.05 -> 3.1850041 | K17: 0.2 | L17: =SUBTOTAL(109,H17,J17,K17) -> 3.8960641 | M17: 2.7575793
B18: 20241030 | C18: 6.837 | D18: A.F.D.2300239-MP | E18: A.F.D.2300239 RJ45 DB | F18: 0.59640776 | G18: 0.71568931 | H18: 0.78725825 | I18: 7.7942757 | J18: =I18*1.05 -> 8.1839895 | K18: 0.4 | L18: =SUBTOTAL(109,H18,J18,K18) -> 9.3712477 | M18: 7.0857052 | N18: 含INTEL网卡ic-I226LM_SRKTT；ALC269Q；FG24102SEG（后期换料）
A19: XN50(6L+通孔+沉金） | B19: 20241030 | C19: 6.7739 | D19: A.F.D.2300240-MP | E19: A.F.D.2300240 RJ45 DB | F19: =6.26/C19/1.13 -> 0.81781884 | G19: 0.9813826 | H19: 1.0795209 | I19: 6.98775 | J19: =I19*1.05 -> 7.3371375 | K19: 0.4 | L19: =SUBTOTAL(109,H19,J19,K19) -> 8.8166584 | M19: =6.05*1.05 -> 6.3525 | N19: 含INTEL网卡ic-I226V_SRKTV；ALC269Q；FG24102SEG（后期换料）
A20: DN50Z | B20: 2025 0226 | C20: 6.837 | D20: A.F.D.2300324-MP | E20: A.F.D.2300324 USB DB | F20: 0.38877095 | G20: 0.46652513 | H20: 0.51317765 | I20: 3.3545245 | J20: =I20*1.05 -> 3.5222507 | K20: 0.2 | L20: =SUBTOTAL(109,H20,J20,K20) -> 4.2354283 | M20: 3.0495677 | N20: ALC269Q
C21: 6.837 | E21: A.P.10001155 140HC_YD_DB | F21: 0.43281173 | G21: 0.51937407 | H21: 0.57131148 | I21: 3.2229098 | J21: =I21*1.05 -> 3.3840553 | K21: 0.4 | L21: =SUBTOTAL(109,H21,J21,K21) -> 4.3553668 | M21: 2.929918
C22: 6.837 | E22: A.P.10001028 RJ45 DB | F22: 0.77676975 | G22: 0.9321237 | H22: 1.0253361 | I22: 4.6184285 | J22: =I22*1.05 -> 4.8493499 | K22: 0.8 | L22: =SUBTOTAL(109,H22,J22,K22) -> 6.674686 | M22: 4.1985714 | N22: I219V，ALC269
C23: 6.837 | E23: A.P.10001065 4G USB DB | F23: 0.56121296 | G23: 0.67345555 | H23: 0.7408011 | I23: 4.0989964 | J23: =I23*1.05 -> 4.3039463 | K23: 0.4 | L23: =SUBTOTAL(109,H23,J23,K23) -> 5.4447474 | M23: 3.7263604
C24: 6.837 | E24: A.P.10001028 RJ45 DB | F24: 0.77676975 | G24: 0.9321237 | H24: 1.0253361 | I24: 4.6184285 | J24: =I24*1.05 -> 4.8493499 | K24: 0.4 | L24: =SUBTOTAL(109,H24,J24,K24) -> 6.274686 | M24: 4.1985714 | N24: I219V，ALC269
B25: 20241115 | C25: 6.837 | D25: A.F.D.2300380-PVT | E25: A.F.D.2300380 USB DB | F25: 0.45234837 | G25: 0.54281804 | H25: 0.59709984 | I25: 2.5466575 | J25: =I25*1.05 -> 2.6739904 | K25: 0.2 | L25: =SUBTOTAL(109,H25,J25,K25) -> 3.4710903 | M25: 2.3151432 | N25: ALC269Q-VC3-GR;PS8719ETQFN24GTR2;RTS5170-GR
B26: 20250715 | C26: 6.837 | D26: A.P.10001066 | E26: A.P.10001066 AUDIO DB | F26: 7.0396087 | G26: 8.4475304 | H26: 9.2922835 | I26: 1.7971733 | J26: =I26*1.05 -> 1.887032 | K26: 0.2 | L26: =SUBTOTAL(109,H26,J26,K26) -> 11.379315 | M26: 1.6337939 | N26: 含在主板BOM里面的 需合计
B27: 20250218 | C27: 6.837 | D27: A.F.D.2300201-MP | E27: A.F.D.2300201 AUDIO DB | F27: 0.34837229 | G27: 0.41804675 | H27: 0.45985142 | I27: 1.8192269 | J27: =I27*1.05 -> 1.9101883 | K27: 0.2 | L27: =SUBTOTAL(109,H27,J27,K27) -> 2.5700397 | M27: 1.6538427 | N27: SN6140；RTS5170；PS8719ETQFN24GTR2-A0
B28: 20250807 | C28: 6.837 | D28: A.F.D.2500222-PVT | E28: A.F.D.2500222 RJ45 DB | F28: 0.4936802 | G28: 0.59241624 | H28: 0.65165787 | I28: 3.2774332 | J28: =I28*1.05 -> 3.4413048 | K28: 0.4 | L28: =SUBTOTAL(109,H28,J28,K28) -> 4.4929627 | M28: 2.9794847 | N28: 含8111H、ALC269Q
B29: 20240829 | C29: 6.837 | D29: A.F.D.2400221-EVT | E29: A.F.D.2400221 RJ45 DB | F29: 0.49957625 | G29: 0.5994915 | H29: 0.65944065 | I29: 3.0888772 | J29: =I29*1.05 -> 3.2433211 | K29: 0.4 | L29: =SUBTOTAL(109,H29,J29,K29) -> 4.3027617 | M29: 2.8080702 | N29: 含8111H
A30: DA1059E | B30: 20250516 | C30: 6.837 | E30: A.F.D.2300379 RJ45 DB | F30: 0.44991566 | G30: 0.53989879 | H30: 0.59388867 | I30: 3.683971 | J30: =I30*1.05 -> 3.8681696 | K30: 0.4 | L30: =SUBTOTAL(109,H30,J30,K30) -> 4.8620583 | M30: 3.3490646 | N30: 含8111H、ALC269Q
A31: MTNTU146L | B31: 46081 | C31: 6.837 | D31: A.F.D.2600043 | E31: MTNTU146L USB DB | F31: =2.64/C31/1.13 -> 0.34171174 | G31: 0.41005409 | H31: 0.4510595 | I31: 3.4658618 | J31: =I31*1.05 -> 3.6391548 | K31: =3.14/C31 -> 0.45926576 | L31: =SUBTOTAL(109,H31,J31,K31) -> 4.5494801 | M31: 3.1507834 | N31: ALC269Q-VC3-GR,,RTL8111H-CG
B32: 20240802 | C32: 6.837 | D32: A.P.10000661-MP | E32: A.P.10000661 USB DB | F32: 0.60677268 | G32: 0.72812721 | H32: 0.80093993 | I32: 0.71857295 | J32: =I32*1.05 -> 0.7545016 | K32: 0.2 | L32: =SUBTOTAL(109,H32,J32,K32) -> 1.7554415 | M32: 0.65324814
C33: 6.837 | E33: A.F.D.2300010 | F33: 0.25779335 | G33: 0.30935202 | H33: 0.34028723 | I33: 1.0896289 | J33: =I33*1.05 -> 1.1441104 | K33: 0.2 | L33: =SUBTOTAL(109,H33,J33,K33) -> 1.6843976 | M33: 0.99057176
C34: 6.837 | E34: A.F.D.2300185 DP13_133M_5G_DB | F34: 0.36967638 | G34: 0.44361166 | H34: 0.48797282 | I34: 1.5691934 | J34: =I34*1.05 -> 1.6476531 | K34: 0.2 | L34: =SUBTOTAL(109,H34,J34,K34) -> 2.3356259 | M34: 1.4265394
C35: 6.837 | E35: A.F.D.2300065 133M_DB | F35: 1.6346313 | G35: 1.9615576 | H35: 2.1577133 | I35: 2.2584353 | J35: =I35*1.05 -> 2.3713571 | K35: 0.2 | L35: =SUBTOTAL(109,H35,J35,K35) -> 4.7290704 | M35: 2.053123
C36: 6.837 | E36: A.P.10001140 133H-LHCX-IO_DB | F36: 0.17002527 | G36: 0.20403033 | H36: 0.22443336 | I36: 0.96689736 | J36: =I36*1.05 -> 1.0152422 | K36: 0.2 | L36: =SUBTOTAL(109,H36,J36,K36) -> 1.4396756 | M36: 0.8789976
C37: 6.837 | E37: A.P.10001141 133H-LHCX-LCD_DB | F37: 0.085012636 | G37: 0.10201516 | H37: 0.11221668 | I37: 4.0632777 | J37: =I37*1.05 -> 4.2664416 | K37: 0.2 | L37: =SUBTOTAL(109,H37,J37,K37) -> 4.5786583 | M37: 3.6938888
B38: 20250425 | C38: 6.837 | D38: A.F.D.2500084-MP | E38: A.F.D.2500084 Hall DB | F38: 0.20437267 | G38: 0.24524721 | H38: 0.26977193 | I38: 1.0900664 | J38: =I38*1.05 -> 1.1445698 | K38: 0.2 | L38: =SUBTOTAL(109,H38,J38,K38) -> 1.6143417 | M38: 0.9909695 | N38: ALC269Q
B39: 20240814 | C39: 6.837 | E39: A.F.D.2300276 USB DB | F39: 0.19147823 | G39: 0.22977388 | H39: 0.25275127 | I39: 1.2057698 | J39: =I39*1.05 -> 1.2660583 | K39: 0.2 | L39: =SUBTOTAL(109,H39,J39,K39) -> 1.7188095 | M39: 1.0961543 | N39: 含有ALC269Q
C40: 6.837 | E40: A.F.D.2400033 IO_DB | F40: 0.33097367 | G40: 0.39716841 | H40: 0.43688525 | I40: 1.2015752 | J40: =I40*1.05 -> 1.2616539 | K40: 0.2 | L40: =SUBTOTAL(109,H40,J40,K40) -> 1.8985392 | M40: 1.092341
A41: DNNTU | B41: 46079 | C41: 6.75 | D41: A.F.D.2500126-PVT | E41: A.F.D.2500126 USB DB | F41: =3.13/C41/1.13 -> 0.41035726 | G41: 0.48616262 | H41: =5/C41/1.13 -> 0.65552278 | I41: 1.9703717 | J41: =I41*1.05 -> 2.0688903 | K41: =2.6/C41/1.13 -> 0.34087185 | L41: =SUBTOTAL(109,H41,J41,K41) -> 3.065285 | M41: 1.791247 | N41: ALC269Q;RTS5170
A42: MTNTU146(4L+通孔+OSP) | B42: 46285 | C42: 6.7 | D42: A.F.D.2500127-PVT | E42: A.F.D.2500127 RJ45 DB | F42: =6.3/6.78/1.13 -> 0.82230402 | G42: 0.98676482 | H42: =4.27/C42/1.13 -> 0.56399419 | I42: 3.4703184 | J42: 3.35 | K42: =3.06/C42/1.13 -> 0.40417382 | L42: =SUBTOTAL(109,H42,J42,K42) -> 4.318168 | M42: 3.1548349 | N42: ALC269Q;RTS5170
A43: MTNTU146 | B43: 46151 | C43: 6.75 | D43: A.F.D.2500130-PVT | E43: A.F.D.2500130 RJ45 DB | F43: =3.2/C43/1.13*1.3 -> 0.54539495 | G43: 0.64760454 | H43: =4.2/C43/1.13 -> 0.55063913 | I43: 3.41 | J43: =I43*1.05 -> 3.5805 | K43: 0.4 | L43: =SUBTOTAL(109,H43,J43,K43) -> 4.5311391 | M43: 3.1 | N43: ALC269Q;RTL8111H;SY6280AAC;RTS5170
A44: MTNTU146 | B44: 20250430 | C44: 6.837 | D44: A.F.D.2500073-EVT | E44: A.F.D.2500073 RJ45 DB | F44: 0.36736928 | G44: 0.44084314 | H44: 0.48492745 | I44: 3.2506484 | J44: =I44*1.05 -> 3.4131808 | K44: 0.4 | L44: =SUBTOTAL(109,H44,J44,K44) -> 4.2981083 | M44: 2.9551349 | N44: ALC269Q;RTL8111H;SY6280AAC
A45: MTNTU146 | B45: 20250506 | C45: 6.837 | D45: A.F.D.2500071-EVT | E45: A.F.D.2500071 USB DB | F45: 0.36332554 | G45: 0.43599065 | H45: 0.47958971 | I45: 1.6693476 | J45: =I45*1.05 -> 1.7528149 | K45: 0.2 | L45: =SUBTOTAL(109,H45,J45,K45) -> 2.4324046 | M45: 1.5175887 | N45: ALC269Q;RTS5170
A46: MTNTU146 | B46: 20250605 | C46: 6.837 | D46: A.F.D.2500072-EVT | E46: A.F.D.2500072 RJ45 DB | F46: 0.41117114 | G46: 0.49340537 | H46: 0.5427459 | I46: 3.3160301 | J46: =I46*1.05 -> 3.4818316 | K46: 0.4 | L46: =SUBTOTAL(109,H46,J46,K46) -> 4.4245775 | M46: 3.0145728 | N46: ALC269Q;RTL8111H
A47: MTNTU146 | C47: 6.837 | E47: A.F.D.2600009 RJ45 DB | F47: 0.43068422 | G47: 0.51682106 | H47: 0.56850317 | I47: 3.4658618 | J47: =I47*1.05 -> 3.6391548 | K47: 0.4 | L47: =SUBTOTAL(109,H47,J47,K47) -> 4.607658 | M47: 3.1507834 | N47: ALC269Q;RTL8111H
A48: XN21 | B48: 46081 | C48: 6.837 | E48: A.F.D.2300079 156H_SCD_DB | F48: 1.0210992 | G48: 1.225319 | H48: 1.3478509 | I48: 1.6708497 | J48: =I48*1.05 -> 1.7543921 | K48: 0.2 | L48: =SUBTOTAL(109,H48,J48,K48) -> 3.302243 | M48: 1.5189542
A49: XN21 | B49: 46081 | C49: 6.837 | E49: A.F.D.2300189 156H-SCD_DB | F49: 0.2895499 | G49: 0.34745988 | H49: 0.38220586 | I49: 1.5985864 | J49: =I49*1.05 -> 1.6785158 | K49: 0.2 | L49: =SUBTOTAL(109,H49,J49,K49) -> 2.2607216 | M49: 1.4532604
A50: XN21 | C50: 6.837 | E50: A.F.D.2300172 RJ45 DB | F50: 0.42746837 | G50: 0.51296205 | H50: 0.56425825 | I50: 3.013989 | J50: =I50*1.05 -> 3.1646884 | K50: 0.4 | L50: =SUBTOTAL(109,H50,J50,K50) -> 4.1289467 | M50: 2.73999 | N50: 8111H
A51: XN21 | C51: 6.837 | E51: A.F.D.2300289 RJ45 DB | F51: 0.48507819 | G51: 0.58209383 | H51: 0.64030321 | I51: 5.0820776 | J51: =I51*1.05 -> 5.3361814 | K51: 0.4 | L51: =SUBTOTAL(109,H51,J51,K51) -> 6.3764846 | M51: 4.6200705 | N51: 8111H；USBHUB
A52: XN21 | C52: 6.837 | E52: A.F.D.2300251 USB DB | F52: =0.328256083931726 -> 0.32825608 | G52: 0.3939073 | H52: =0.66 -> 0.66 | I52: 1.6034042 | J52: =I52*1.05 -> 1.6835744 | K52: 0.2 | L52: =SUBTOTAL(109,H52,J52,K52) -> 2.5435744 | M52: 1.4576401
A53: XN21 | B53: 20240301 | C53: 6.837 | D53: A.F.D.2300197-MP | E53: A.F.D.2300197 LED DB | F53: 0.24232948 | G53: 0.29079538 | H53: 0.31987492 | I53: 0.044838362 | J53: =I53*1.05 -> 0.04708028 | K53: 0.2 | L53: =SUBTOTAL(109,H53,J53,K53) -> 0.5669552 | M53: 0.040762147
A54: XN21 | B54: 20240301 | C54: 6.837 | D54: A.F.D.2300243-PVT | E54: A.F.D.2300243 RJ45 DB | F54: 0.63587256 | G54: 0.76304707 | H54: 0.83935178 | I54: 5.0870711 | J54: =I54*1.05 -> 5.3414247 | K54: 0.4 | L54: =SUBTOTAL(109,H54,J54,K54) -> 6.5807765 | M54: 4.6246101 | N54: 8111H；GL3510
A55: XN21 | B55: 20241010 | C55: 6.837 | D55: A.F.D.2400261-MP | E55: A.F.D.2400261 RJ45 DB | F55: 0.49783336 | G55: 0.59740004 | H55: 0.65714004 | I55: 5.0271595 | J55: =I55*1.05 -> 5.2785175 | K55: 0.4 | L55: =SUBTOTAL(109,H55,J55,K55) -> 6.3356575 | M55: 4.570145 | N55: 含8111H,GL850G,GL3510
A56: XN21 | B56: 20241011 | C56: 6.837 | D56: A.F.D.2400266-MP | E56: A.F.D.2400266 RJ45 DB | F56: 0.59640776 | G56: 0.71568931 | H56: 0.78725825 | I56: 3.2590216 | J56: =I56*1.05 -> 3.4219727 | K56: 0.4 | L56: =SUBTOTAL(109,H56,J56,K56) -> 4.609231 | M56: 2.962747 | N56: 含8111H、GL3510,含109010782连接器
A57: XN21 | B57: 20241011 | C57: 6.837 | D57: A.F.D.2400263-PVT | E57: A.F.D.2400263 RJ45 DB | F57: 0.4506192 | G57: 0.54074304 | H57: 0.59481734 | I57: 2.8645638 | J57: =I57*1.05 -> 3.007792 | K57: 0.4 | L57: =SUBTOTAL(109,H57,J57,K57) -> 4.0026093 | M57: 2.6041489 | N57: 含8111H
A58: XN21 | B58: 20241025 | C58: 6.837 | D58: A.F.D.2400270-EVT | E58: A.F.D.2400270 RJ45 DB | F58: 0.61628802 | G58: 0.73954562 | H58: 0.81350019 | I58: 3.1260485 | J58: =I58*1.05 -> 3.2823509 | K58: 0.4 | L58: =SUBTOTAL(109,H58,J58,K58) -> 4.4958511 | M58: 2.8418623 | N58: 含8111H
A59: XN21 | C59: 6.837 | E59: A.F.D.2300243 RJ45 DB | F59: 0.62630403 | G59: 0.75156483 | H59: 0.82672131 | I59: 5.0589658 | J59: =I59*1.05 -> 5.311914 | K59: 0.4 | L59: =SUBTOTAL(109,H59,J59,K59) -> 6.5386354 | M59: 4.5990598 | N59: 8111H；GL3510
A60: XN21 | B60: 20241213 | C60: 6.837 | D60: A.F.D.2400322-EVT | E60: A.F.D.2400322 RJ45 DB | F60: 0.67494341 | G60: 0.8099321 | H60: 0.89092531 | I60: 3.4508239 | J60: =I60*1.05 -> 3.6233651 | K60: 0.4 | L60: =SUBTOTAL(109,H60,J60,K60) -> 4.9142905 | M60: 3.1371127 | N60: RTL8111H;GL850G
A61: XN21 | B61: 20251126 | C61: 6.837 | D61: A.F.D.2400364-PVT | E61: A.F.D.2400364 RJ45 DB | F61: 0.43890767 | G61: 0.5266892 | H61: 0.57935812 | I61: 1.263303 | J61: =I61*1.05 -> 1.3264682 | K61: 0.4 | L61: =SUBTOTAL(109,H61,J61,K61) -> 2.3058263 | M61: 1.1484573 | N61: GL850G;RTS5170
A62: XN21 | B62: 20250103 | C62: 6.837 | D62: A.F.D.2400366-MP | E62: A.F.D.2400366 LED DB | F62: 0.024972924 | G62: 0.029967509 | H62: 0.03296426 | I62: 0.042255255 | J62: =I62*1.05 -> 0.044368018 | K62: 0.2 | L62: =SUBTOTAL(109,H62,J62,K62) -> 0.27733228 | M62: 0.038413868 | N62: WF32
A63: XN21 | B63: 20250507 | C63: 6.837 | D63: A.F.D.2500101-PVT | E63: A.F.D.2500101 RJ45 DB | F63: 0.68284946 | G63: 0.81941936 | H63: 0.90136129 | I63: 3.0663227 | J63: =I63*1.05 -> 3.2196388 | K63: 0.4 | L63: =SUBTOTAL(109,H63,J63,K63) -> 4.5210001 | M63: 2.7875661 | N63: RTL8111H;GL850G;RTS5170
A64: XN21 | B64: 46081 | C64: 6.75 | D64: A.F.D.2500028-MP | E64: A.F.D.2500028 RJ45 DB | F64: =4.8/C64/1.13 -> 0.62930187 | G64: 0.74555289 | H64: =5.97/C64/1.13 -> 0.7826942 | I64: 4.0049098 | J64: 3.9 | K64: 0.4 | L64: =SUBTOTAL(109,H64,J64,K64) -> 5.0826942 | M64: 3.6408271 | N64: RTL8111H;GL3510
A65: XN21 | B65: 20250108 | C65: 6.837 | D65: A.F.D.2400362-MP | E65: A.F.D.2400362 RJ45 DB | F65: 0.61058799 | G65: 0.73270559 | H65: 0.80597615 | I65: 3.0296299 | J65: =I65*1.05 -> 3.1811114 | K65: 0.4 | L65: =SUBTOTAL(109,H65,J65,K65) -> 4.3870876 | M65: 2.754209 | N65: RTL8111H-CG;GL3510-OSY52
A66: XN21 | B66: 20241202 | C66: 6.837 | D66: A.F.D.2400062-PVT | E66: A.F.D.2400062 RJ45 DB | F66: 0.57757979 | G66: 0.69309574 | H66: 0.76240532 | I66: 3.7519082 | J66: =I66*1.05 -> 3.9395036 | K66: 0.4 | L66: =SUBTOTAL(109,H66,J66,K66) -> 5.1019089 | M66: 3.4108256 | N66: 8111H；GL3510
A67: XN21 | B67: 46081 | C67: 6.837 | D67: A.F.D.2400034-PVT | E67: A.F.D.2400034 LED DB | F67: 0.037839261 | G67: 0.045407114 | H67: =1/6.7/1.13 -> 0.13208295 | I67: 0.045865698 | J67: =I67*1.05 -> 0.048158983 | K67: 0.2 | L67: =SUBTOTAL(109,H67,J67,K67) -> 0.38024193 | M67: 0.041696089
A68: XN21 | B68: 20240605 | C68: 6.837 | D68: A.F.D.2400115-MP | E68: A.F.D.2400115 RJ45 DB | F68: 0.43083469 | G68: 0.51700162 | H68: 0.56870179 | I68: 6.6359809 | J68: =I68*1.05 -> 6.9677799 | K68: 0.4 | L68: =SUBTOTAL(109,H68,J68,K68) -> 7.9364817 | M68: 6.0327099 | N68: 含有英特尔雷电IC*1pcs;GL3510
A69: XN21 | B69: 20250618 | C69: 6.837 | D69: A.F.D.2500138-PVT | E69: A.F.D.2500138 RJ45 DB | F69: 0.69601139 | G69: 0.83521367 | H69: 0.91873504 | I69: 3.071059 | J69: =I69*1.05 -> 3.224612 | K69: 0.4 | L69: =SUBTOTAL(109,H69,J69,K69) -> 4.543347 | M69: 2.7918718 | N69: GL850G;RTS5170;RTL8111H
A70: XN21 | B70: 20241023 | C70: 6.837 | D70: A.F.D.2400289-MP | E70: A.F.D.2400289 RJ45 DB | F70: 0.64809643 | G70: 0.77771572 | H70: 0.85548729 | I70: 3.2590096 | J70: =I70*1.05 -> 3.4219601 | K70: 0.4 | L70: =SUBTOTAL(109,H70,J70,K70) -> 4.6774474 | M70: 2.962736 | N70: 含有8111H
A71: XN21 | B71: 46056 | C71: 6.72 | D71: A.F.D.2400154-MP | E71: A.F.D.2400154 RJ45 DB | F71: =5.7/C71/1.13 -> 0.75063211 | G71: 0.88534406 | H71: 0.97387847 | I71: 4.5279807 | J71: 4.3 | K71: =3/C71 -> 0.44642857 | L71: =SUBTOTAL(109,H71,J71,K71) -> 5.720307 | M71: 4.1163461 | N71: 含有8111H；GL3510;RTS5170
A72: XN21 | B72: 46248 | C72: 6.75 | D72: A.F.D.2400113-EVT | E72: A.F.D.2400113 RJ45 DB | F72: =3.18/C72/1.13+2000/312/6.7851/1.13 -> 1.2529788 | G72: 1.4983234 | H72: =5/C72/1.13 -> 0.65552278 | I72: 2.5714458 | J72: =I72*1.05 -> 2.7000181 | K72: 0.4 | L72: =SUBTOTAL(109,H72,J72,K72) -> 3.7555409 | M72: 2.337678 | N72: 含有8111H, 含PCB312套工程费2000元
A73: XN25 | C73: 6.837 | E73: A.P.10000577-583 DB | F73: 1.6778227 | G73: 2.0133872 | H73: 2.2147259 | I73: 3.5166518 | J73: =I73*1.05 -> 3.6924844 | K73: 0.4 | L73: =SUBTOTAL(109,H73,J73,K73) -> 6.3072103 | M73: 3.1969562
A74: XN25 | C74: 6.837 | E74: A.P.10000586 156M_DB_POWER | F74: 1.9471028 | G74: 2.3365234 | H74: 2.5701757 | I74: 10.356378 | J74: =I74*1.05 -> 10.874197 | K74: 0.4 | L74: =SUBTOTAL(109,H74,J74,K74) -> 13.844373 | M74: 9.4148893 | N74: 不含两个DC-DC电源模块的成本
A75: XN25 | B75: 46265 | C75: 6.73 | D75: A.F.D.2400334-PVT | E75: A.F.D.2400334 AUDIO DB | F75: 0.37150179 | G75: 0.44580215 | H75: =4.4/C75/1.13 -> 0.57857434 | I75: 1.6405838 | J75: =I75*1.05 -> 1.722613 | K75: 0.4 | L75: =SUBTOTAL(109,H75,J75,K75) -> 2.7011873 | M75: 1.4914398 | N75: 含ALC269Q
A76: XN25 | B76: 46059 | C76: 6.837 | D76: A.F.D.2400308-PVT | E76: A.F.D.2400308 AUDIO DB | F76: =3.47/C76/1.13 -> 0.44914384 | G76: 0.53897261 | H76: 0.59286987 | I76: 1.6323091 | J76: =I76*1.05 -> 1.7139245 | K76: =2.05/C76 -> 0.29983911 | L76: =SUBTOTAL(109,H76,J76,K76) -> 2.6066335 | M76: 1.4839173 | N76: ALC269Q-VC3-GR
A77: XN25 | B77: 46080 | C77: 6.837 | D77: A.F.D.2400297-PVT | E77: A.F.D.2400297 USB DB | F77: =3.47/C77/1.13 -> 0.44914384 | G77: 0.53897261 | H77: 0.59286987 | I77: 1.6034642 | J77: =I77*1.05 -> 1.6836374 | K77: 0.2 | L77: =SUBTOTAL(109,H77,J77,K77) -> 2.4765073 | M77: 1.4576947 | N77: 含有ALC269Q;SY6863B3ABC
A78: XN25 | B78: 20250123 | C78: 6.837 | D78: A.F.D.2500020-PVT | E78: A.F.D.2500020 Audio DB | F78: 0.34212906 | G78: 0.41055487 | H78: 0.45161036 | I78: 1.4062958 | J78: =I78*1.05 -> 1.4766106 | K78: 0.2 | L78: =SUBTOTAL(109,H78,J78,K78) -> 2.128221 | M78: 1.2784507 | N78: ALC269Q
A79: XN25 | B79: 20240409 | C79: 6.837 | D79: A.F.D.2400022-EVT | E79: A.F.D.2400022 TYPEC_DB | F79: 0.20892047 | G79: 0.25070456 | H79: 0.27577501 | I79: 3.0238534 | J79: =I79*1.05 -> 3.175046 | K79: 0.4 | L79: =SUBTOTAL(109,H79,J79,K79) -> 3.850821 | M79: 2.7489576 | N79: 含有ALC269Q；GL3510
A80: XN25 | B80: 20250224 | C80: 6.837 | D80: A.F.D.2400255-PVT | E80: A.F.D.2400255 USB DB | F80: 0.34925652 | G80: 0.41910783 | H80: 0.46101861 | I80: 1.2529918 | J80: =I80*1.05 -> 1.3156414 | K80: 0.2 | L80: =SUBTOTAL(109,H80,J80,K80) -> 1.97666 | M80: 1.1390835 | N80: SN6140
A81: XN25 | B81: 20240416 | C81: 6.837 | D81: A.F.D.2400069-MP | E81: A.F.D.2400069 USB DB | F81: 0.17255463 | G81: 0.20706555 | H81: 0.22777211 | I81: 1.4267475 | J81: =I81*1.05 -> 1.4980849 | K81: 0.2 | L81: =SUBTOTAL(109,H81,J81,K81) -> 1.925857 | M81: 1.2970432 | N81: 含有IT66318FN
A82: XN25 | B82: 20240925 | C82: 6.837 | D82: A.F.D.2400208-PVT | E82: A.F.D.2400208 Audio DB | F82: 0.45989665 | G82: 0.55187598 | H82: 0.60706358 | I82: 1.5264851 | J82: =I82*1.05 -> 1.6028094 | K82: 0.2 | L82: =SUBTOTAL(109,H82,J82,K82) -> 2.409873 | M82: 1.3877138
A83: XN25 | B83: 20240925 | C83: 6.837 | D83: A.F.D.2400236-EVT | E83: A.F.D.2400236 Audio DB | F83: 0.38832772 | G83: 0.46599326 | H83: 0.51259259 | I83: 1.3859595 | J83: =I83*1.05 -> 1.4552575 | K83: 0.2 | L83: =SUBTOTAL(109,H83,J83,K83) -> 2.1678501 | M83: 1.2599632
A84: XN25 | B84: 20250401 | C84: 6.837 | D84: A.F.D.2500057-PVT | E84: A.F.D.2500057 AUDIO DB | F84: 0.42828537 | G84: 0.51394244 | H84: 0.56533669 | I84: 1.5481737 | J84: =I84*1.05 -> 1.6255824 | K84: 0.2 | L84: =SUBTOTAL(109,H84,J84,K84) -> 2.3909191 | M84: 1.4074307 | N84: ALC269Q
A85: XN25 | B85: 46078 | C85: 6.837 | D85: A.F.D.2500109-PVT | E85: A.F.D.2500109 DC DB | F85: =1/C85/1.13 -> 0.12943627 | G85: 0.15532352 | H85: 0.17085587 | I85: 0.76025355 | J85: =I85*1.05 -> 0.79826622 | K85: 0.15 | L85: =SUBTOTAL(109,H85,J85,K85) -> 1.1191221 | M85: 0.69113959 | N85: MP3367GR-Z
A86: XN25 | B86: 20250428 | C86: 6.837 | D86: A.F.D.2500076-MP | E86: A.F.D.2500076 AUDIO DB | F86: 0.35106962 | G86: 0.42128355 | H86: 0.4634119 | I86: 3.0593563 | J86: =I86*1.05 -> 3.2123241 | K86: 0.2 | L86: =SUBTOTAL(109,H86,J86,K86) -> 3.875736 | M86: 2.781233 | N86: ALC269Q
A87: XN25 | B87: 20250618 | C87: 6.837 | D87: A.F.D.2500139-EVT | E87: A.F.D.2500139 Audio DB | F87: 0.36930143 | G87: 0.44316171 | H87: 0.48747788 | I87: 3.2177261 | J87: =I87*1.05 -> 3.3786124 | K87: 0.2 | L87: =SUBTOTAL(109,H87,J87,K87) -> 4.0660903 | M87: 2.9252055 | N87: ALC269Q;GL3510
A88: XN25 | B88: 46106 | C88: 6.837 | D88: A.F.D.2500140-EVT | E88: A.F.D.2500140 Audio DB | F88: =2.89/C88/1.13*1.05 -> 0.39277435 | G88: 0.47132922 | H88: 0.51846214 | I88: 1.6050781 | J88: =I88*1.05 -> 1.685332 | K88: =2.01/C88 -> 0.29398859 | L88: =SUBTOTAL(109,H88,J88,K88) -> 2.4977827 | M88: 1.4591619 | N88: ALC269Q
A89: XN25 | B89: 20250106 | C89: 6.837 | D89: A.F.D.2400360-EVT | E89: A.F.D.2400360 USB DB | F89: 0.427037 | G89: 0.5124444 | H89: 0.56368884 | I89: 1.5335152 | J89: =I89*1.05 -> 1.6101909 | K89: 0.2 | L89: =SUBTOTAL(109,H89,J89,K89) -> 2.3738798 | M89: 1.3941047 | N89: ALC269Q
A90: XN25 | B90: 46042 | C90: 6.837 | D90: A.F.D.2500572 | E90: A.F.D.2500572 USB DB | F90: 0.52328565 | G90: 0.62794278 | H90: 0.69073706 | I90: 1.6546695 | J90: =I90*1.05 -> 1.737403 | K90: 0.22 | L90: =SUBTOTAL(109,H90,J90,K90) -> 2.64814 | M90: 1.504245 | N90: ALC269Q，PCB无卤
A91: XN25 | B91: 20250826 | C91: 6.837 | D91: A.F.D.2500153-PVT | E91: A.F.D.2500153 AUDIO DB | F91: 0.44605924 | G91: 0.53527109 | H91: =5.5/6.72/1.13 -> 0.72429414 | I91: 1.637646 | J91: =I91*1.05 -> 1.7195283 | K91: =2.75/6.72 -> 0.40922619 | L91: =SUBTOTAL(109,H91,J91,K91) -> 2.8530487 | M91: 1.4887691 | N91: ALC269Q
A92: XN25 | B92: 20240919 | C92: 6.837 | D92: A.F.D.2400241-PVT | E92: A.F.D.2400241 Audio DB | F92: 0.461287 | G92: 0.5535444 | H92: 0.60889884 | I92: 1.7408849 | J92: =I92*1.05 -> 1.8279291 | K92: 0.2 | L92: =SUBTOTAL(109,H92,J92,K92) -> 2.6368279 | M92: 1.5826226 | N92: 含ALC269Q
A93: XN50 | C93: 6.837 | D93: A.F.D.2300011 | E93: A.F.D.2300011 RJ45 DB | F93: 0.80505485 | G93: 0.96606582 | H93: 1.0626724 | I93: 4.002849 | J93: =I93*1.05 -> 4.2029915 | K93: 0.4 | L93: =SUBTOTAL(109,H93,J93,K93) -> 5.6656639 | M93: 3.6389537 | N93: 8111H
A94: XN50 | C94: 6.837 | D94: A.P.10001030 | E94: A.P.10001030 RJ45 DB | F94: 0.78065973 | G94: 0.93679167 | H94: 1.0304708 | I94: 6.5751931 | J94: =I94*1.05 -> 6.9039528 | K94: 0.4 | L94: =SUBTOTAL(109,H94,J94,K94) -> 8.3344236 | M94: 5.9774483
A95: XN50 | B95: 20250617 | C95: 6.837 | D95: A.F.D.2500137-MP | E95: A.F.D.2500137 RJ45 DB | F95: 0.64170756 | G95: 0.77004908 | H95: 0.84705399 | I95: 3.8172814 | J95: =I95*1.05 -> 4.0081454 | K95: 0.4 | L95: =SUBTOTAL(109,H95,J95,K95) -> 5.2551994 | M95: 3.4702558 | N95: ALC269Q;8111H;BH760FJ2LN-B1-0-TR
A96: XN50 | B96: 20250716 | C96: 6.837 | D96: A.F.D.2300295 | E96: A.F.D.2300295 RJ45 DB | F96: 0.596967 | G96: 0.7163604 | H96: 0.78799644 | I96: 3.8725336 | J96: =I96*1.05 -> 4.0661603 | K96: 0.4 | L96: =SUBTOTAL(109,H96,J96,K96) -> 5.2541568 | M96: 3.5204851 | N96: 8111H;BH760FJ2LN-B1-0-TR
A97: XN79 | B97: 20240627 | C97: 6.837 | D97: A.F.D.2400128-EVT | E97: A.F.D.2400128 USB DB | F97: 0.40905661 | G97: 0.49086794 | H97: 0.53995473 | I97: 1.9483382 | J97: =I97*1.05 -> 2.0457551 | K97: 0.2 | L97: =SUBTOTAL(109,H97,J97,K97) -> 2.7857098 | M97: 1.7712165 | N97: 含SN6140
A98: XN79 | B98: 20250326 | C98: 6.837 | D98: A.F.D.2400139-PVT | E98: A.F.D.2400139 USB DB | F98: 0.36327777 | G98: 0.43593332 | H98: =4.66/6.73/1.13 -> 0.61276282 | I98: 1.5694606 | J98: =I98*1.05 -> 1.6479336 | K98: 0.4 | L98: =SUBTOTAL(109,H98,J98,K98) -> 2.6606964 | M98: 1.4267824 | N98: 含SN6140
A99: XN79 | B99: 20241129 | C99: 6.837 | D99: A.F.D.2400156-EVT/ARA1079 | E99: A.F.D.2400156 USB DB | F99: 0.41426412 | G99: 0.49711695 | H99: 0.54682864 | I99: 4.1808291 | J99: =I99*1.05 -> 4.3898706 | K99: 0.2 | L99: =SUBTOTAL(109,H99,J99,K99) -> 5.1366992 | M99: 3.8007537 | N99: GL3510-OSY50;PS8719ETQFN24GTR2-A0
A100: XN79 | B100: 20241018 | C100: 6.837 | D100: A.F.D.2400282-EVT | E100: A.F.D.2400282 USB DB | F100: 0.48746909 | G100: 0.58496291 | H100: 0.6434592 | I100: 5.2189298 | J100: =I100*1.05 -> 5.4798763 | K100: 0.2 | L100: =SUBTOTAL(109,H100,J100,K100) -> 6.3233355 | M100: 4.7444817 | N100: 含intel 网卡ic-WGI219LM；ALC269Q
...

Sheet DB小板汇总 (2)
B1: 12月份汇率：7.01币种:USA | M1: R02
A2: 厂区 | C2: 日期 | D2: 原汇率 | E2: 更新汇率 | F2: 料号 | G2: SKU | H2: PCB | I2: Others | J2: SMT | K2: TTL | L2: 备注
C3: 20250113 | D3: 7.3 | E3: 7.17 | F3: A.F.D.2400329-PVT | G3: A.F.D.2400329 RJ45 DB | H3: 0.69307483 | I3: 2.9511529 | J3: 0.4 | K3: =SUM(H3:J3)+1 -> 5.0442278 | L3: 含RTL8111H；含GL850G；PS8719ETQFN24GTR2-A0
C4: 20250114 | D4: 7.3 | E4: 7.17 | F4: A.F.D.2500004-PVT | G4: A.F.D.2500004 RJ45 DB | H4: 0.41400792 | I4: 2.3394799 | J4: 0.4 | K4: =SUM(H4:J4)+1 -> 4.1534878 | L4: 含RTL8111H；含GL850G；RTS5170
B5: XN21 | C5: 20241113 | D5: 7.2 | E5: 7.17 | F5: A.F.D.2300285-EVT | G5: A.F.D.2300285 RJ45 DB | H5: 0.42621852 | I5: 2.3974685 | J5: 0.4 | K5: =SUM(H5:J5) -> 3.223687 | L5: 含有8111H | M5: .
C6: 20240105 | D6: 7.2 | E6: 7.17 | F6: A.P.10001018 | G6: A.P.10001018 RJ45 DB | H6: 0.71729625 | I6: 2.958558 | J6: 0.4 | K6: =SUM(H6:J6) -> 4.0758542 | L6: 8111H | M6: .
C7: 20241105 | D7: 7.11 | E7: 7.17 | F7: A.F.D.2400048-MP | G7: A.F.D.2400048 USB DB | H7: 0.17305155 | I7: 1.5255259 | J7: 0.2 | K7: =SUM(H7:J7) -> 1.8985775 | L7: 含有IT66318FN
C8: 20240411 | D8: 7.23 | E8: 7.17 | F8: A.F.D.2400049-MP | G8: A.F.D.2400049 USB DB | H8: 0.15624054 | I8: 0.58593119 | J8: 0.2 | K8: =SUM(H8:J8) -> 0.94217173
C9: 20240411 | D9: 7.23 | E9: A.F.M.2401621-MP | F9: A.F.D.2400058-MP | G9: A.F.D.2400058 TYPEC_DB | H9: 0.3252303 | I9: 2.4074114 | J9: 0.3 | K9: =SUM(H9:J9) -> 3.0326418 | L9: 含有ALC269Q
C10: 20240411 | D10: 7.23 | E10: A.F.M.2401623-MP | F10: A.F.D.2400080-MP | G10: A.F.D.2400080 TYPEC_DB | H10: 0.3252303 | I10: 2.8869763 | J10: 0.3 | K10: =SUM(H10:J10) -> 3.5122066 | L10: 含有ALC269Q
C11: 20241105 | D11: 7.11 | E11: 7.17 | F11: A.F.D.2300338-MP | G11: A.F.D.2300338 140M_SS_TYPEC_DB | H11: 0.33630119 | I11: 3.0476113 | J11: 0.4 | K11: =SUM(H11:J11) -> 3.7839125 | M11: .
G12: A.F.D.2300198 140M_2USB_HDMI_DB | H12: 0.1539401 | I12: 1.4743058 | J12: 0.2 | K12: =SUM(H12:J12) -> 1.8282459 | M12: .
G13: A.F.D.2300246 140M_SS_TYPEC_DB | H13: 0.41368268 | I13: 3.1707387 | J13: 0.4 | K13: =SUM(H13:J13) -> 3.9844214 | M13: .
G14: A.F.D.2300339 140M-SS_DB | H14: 0.1539401 | I14: 1.5132013 | J14: 0.2 | K14: =SUM(H14:J14) -> 1.8671414 | M14: .
C15: 20240914 | D15: 7.11 | E15: 7.17 | F15: A.F.D.2400234-PVT | G15: A.F.D.2400234 TYPEC DB | H15: 0.44288165 | I15: 1.3448892 | J15: 0.2 | K15: =SUM(H15:J15) -> 1.9877709 | L15: 含有SN6140
C16: 20250114 | D16: 7.3 | E16: 7.17 | F16: A.F.D.2400198-MP | G16: A.F.D.2400198 RJ45 DB | H16: 0.58215771 | I16: 3.5789941 | J16: 0.4 | K16: =SUM(H16:J16) -> 4.5611518 | L16: 含有RTL8111H；ALC269Q；OZ711LV2
G17: A.F.D.2400171 RJ45 DB | H17: 0.52283876 | I17: 3.6582337 | J17: 0.4 | K17: =SUM(H17:J17) -> 4.5810725 | L17: 含有8111H;ALC269Q
B18: DN50Z | C18: 20240625 | D18: 7.26 | E18: 7.17 | F18: A.F.D.2300323-MP | G18: A.F.D.2300323 USB DB | H18: 0.37756201 | I18: 2.7131335 | J18: 0.2 | K18: =SUM(H18:J18) -> 3.2906955
C19: 20241030 | D19: 7.11 | E19: 7.17 | F19: A.F.D.2300239-MP | G19: A.F.D.2300239 RJ45 DB | H19: 0.58161235 | I19: 6.9714999 | J19: 0.4 | K19: =SUM(H19:J19) -> 7.9531122 | L19: 含INTEL网卡ic-I226LM_SRKTT；ALC269Q；FG24102SEG（后期换料）
C20: 20241030 | D20: 7.11 | E20: 7.17 | F20: A.F.D.2300240-MP | G20: A.F.D.2300240 RJ45 DB | H20: 0.58161235 | I20: 4.9677094 | J20: 0.4 | K20: =SUM(H20:J20) -> 5.9493218 | L20: 含INTEL网卡ic-I226V_SRKTV；ALC269Q；FG24102SEG（后期换料）
B21: DN50Z | C21: 2025 0226 | D21: 7.25 | E21: 7.17 | F21: A.F.D.2300324-MP | G21: A.F.D.2300324 USB DB | H21: 0.37912649 | I21: 3.0004157 | J21: 0.2 | K21: =SUM(H21:J21) -> 3.5795421 | L21: ALC269Q
G22: A.P.10001155 140HC_YD_DB | H22: 0.42207473 | I22: 2.8826944 | J22: 0.4 | K22: =SUM(H22:J22) -> 3.7047692
G23: A.P.10001028 RJ45 DB | H23: 0.7575 | I23: 4.1309 | J23: 0.8 | K23: =SUM(H23:J23) -> 5.6884 | L23: I219V，ALC269
G24: A.P.10001065 4G USB DB | H24: 0.54729064 | I24: 3.6663 | J24: 0.4 | K24: =SUM(H24:J24) -> 4.6135906
G25: A.P.10001028 RJ45 DB | H25: 0.7575 | I25: 4.1309 | J25: 0.4 | K25: =SUM(H25:J25) -> 5.2884 | L25: I219V，ALC269
C26: 46105 | D26: 6.91
C27: 46105 | D27: 6.91
C28: 20240312 | D28: 7.2 | E28: A.F.M.2401762 | F28: A.F.D.2300211-MP | G28: A.F.D.2300211 RJ45 DB | H28: 0.56716292 | I28: 4.015214 | J28: 0.4 | K28: =SUM(H28:J28) -> 4.9823769 | L28: 含有Intel WGI219V;ALC269Q | P28: =42.7/D28/1.13 -> 5.2482793 | Q28: 28.5
C29: 20241115 | D29: 7.2 | E29: 7.17 | F29: A.F.D.2300380-PVT | G29: A.F.D.2300380 USB DB | H29: 0.44112671 | I29: 2.2778284 | J29: 0.2 | K29: =SUM(H29:J29) -> 2.9189551 | L29: ALC269Q-VC3-GR;PS8719ETQFN24GTR2;RTS5170-GR
B30: XN32G | G30: A.F.D.2300283 RJ45 DB | H30: 0.42544642 | I30: 3.0663503 | J30: 0.4 | K30: =SUM(H30:J30) -> 3.8917967
C31: 20250715 | E31: 7.17 | F31: A.P.10001066 | G31: A.P.10001066 AUDIO DB | H31: 6.8649733 | I31: 1.6074609 | J31: 0.2 | K31: =SUM(H31:J31) -> 8.6724342 | L31: 含在主板BOM里面的 需合计
C32: 20250218 | D32: 7.3 | E32: 7.17 | F32: A.F.D.2300201-MP | G32: A.F.D.2300201 AUDIO DB | H32: 0.33973003 | I32: 1.6271865 | J32: 0.2 | K32: =SUM(H32:J32) -> 2.1669165 | L32: SN6140；RTS5170；PS8719ETQFN24GTR2-A0
C33: 20250807 | D33: 7.17 | E33: 7.17 | F33: A.F.D.2500222-PVT | G33: A.F.D.2500222 RJ45 DB | H33: 0.48143321 | I33: 2.9314622 | J33: 0.4 | K33: =SUM(H33:J33) -> 3.8128955 | L33: 含8111H、ALC269Q
C34: 20240829 | D34: 7.12 | E34: 7.17 | F34: A.F.D.2400221-EVT | G34: A.F.D.2400221 RJ45 DB | H34: 0.48718299 | I34: 2.7628105 | J34: 0.4 | K34: =SUM(H34:J34) -> 3.6499935 | L34: 含8111H
B35: DA1059E | C35: 20250516 | D35: 7.19 | G35: A.F.D.2300379 RJ45 DB | H35: 0.43875436 | I35: 3.2950853 | J35: 0.4 | K35: =SUM(H35:J35) -> 4.1338397 | L35: 含8111H、ALC269Q
C36: 20240802 | D36: 7.26 | E36: 7.17 | F36: A.P.10000661-MP | G36: A.P.10000661 USB DB | H36: 0.59172014 | I36: 0.64271927 | J36: 0.2 | K36: =SUM(H36:J36) -> 1.4344394 | Q36: 16 | V36: TYPE-C:ANX7447QN-AC-R,电量计:CW2217,视频桥接：IT6113FN
G37: A.F.D.2300010 | H37: 0.25139813 | I37: 0.97460601 | J37: 0.2 | K37: =SUM(H37:J37) -> 1.4260041
G38: A.F.D.2300185 DP13_133M_5G_DB | H38: 0.36050562 | I38: 1.4035469 | J38: 0.2 | K38: =SUM(H38:J38) -> 1.9640525
G39: A.F.D.2300065 133M_DB | H39: 1.5940801 | I39: 2.0200314 | J39: 0.2 | K39: =SUM(H39:J39) -> 3.8141115
G40: A.P.10001140 133H-LHCX-IO_DB | H40: 0.16580736 | I40: 0.86483017 | J40: 0.2 | K40: =SUM(H40:J40) -> 1.2306375
G41: A.P.10001141 133H-LHCX-LCD_DB | H41: 0.082903681 | I41: 3.6343518 | J41: 0.2 | K41: =SUM(H41:J41) -> 3.9172555
C42: 20250425 | D42: 7.31 | E42: 7.17 | F42: A.F.D.2500084-MP | G42: A.F.D.2500084 Hall DB | H42: 0.19930269 | I42: 0.97499734 | J42: 0.2 | K42: =SUM(H42:J42) -> 1.3743 | L42: ALC269Q
C43: 20240814 | E43: A.F.M.2503122 | G43: A.F.D.2300276 USB DB | H43: 0.18672813 | I43: 1.0784868 | J43: 0.2 | K43: =SUM(H43:J43) -> 1.465215 | L43: 含有ALC269Q
G44: A.F.D.2400033 IO_DB | H44: 0.32276303 | I44: 1.074735 | J44: 0.2 | K44: =SUM(H44:J44) -> 1.597498
B45: DNNTU | C45: 20250619 | D45: 6.91 | E45: A.F.M.2600110 | F45: A.F.D.2500126-PVT | G45: A.F.D.2500126 USB DB | H45: 0.35450506 | I45: 1.6808192 | J45: 0.2 | K45: =SUM(H45:J45) -> 2.2353243
B46: MTNTU146 | C46: 20250619 | D46: 7.19 | E46: 7.07 | F46: A.F.D.2500127-PVT | G46: A.F.D.2500127 RJ45 DB | H46: 0.40834387 | I46: 3.0502084 | J46: 0.4 | K46: =SUM(H46:J46) -> 3.8585522 | L46: ALC269Q;RTL8111H
C47: 20250627 | D47: 7.19 | E47: 7.17 | F47: A.F.D.2500130-PVT | G47: A.F.D.2500130 RJ45 DB | H47: 0.37790934 | I47: 3.0077308 | J47: 0.4 | K47: =SUM(H47:J47) -> 3.7856401 | L47: ALC269Q;RTL8111H;SY6280AAC;RTS5170
C48: 20250430 | D48: 7.31 | E48: 7.24 | F48: A.F.D.2500073-EVT | G48: A.F.D.2500073 RJ45 DB | H48: 0.35825575 | I48: 2.9075049 | J48: 0.4 | K48: =SUM(H48:J48) -> 3.6657607 | L48: ALC269Q;RTL8111H;SY6280AAC
C49: 20250506 | D49: 7.24 | F49: A.F.D.2500071-EVT | G49: A.F.D.2500071 USB DB | H49: 0.35431233 | I49: 1.4931286 | J49: 0.2 | K49: =SUM(H49:J49) -> 2.047441 | L49: ALC269Q;RTS5170 | P49: =31.73/7.13/1.13 -> 3.9382393 | R49: =23.5/6.91 -> 3.4008683
C50: 20250605 | D50: 7.31 | E50: 7.2 | F50: A.F.D.2500072-EVT | G50: A.F.D.2500072 RJ45 DB | H50: 0.40097099 | I50: 2.9659848 | J50: 0.4 | K50: =SUM(H50:J50) -> 3.7669558 | L50: ALC269Q;RTL8111H | R50: =23.5/6.91 -> 3.4008683
B51: XN21 | G51: A.F.D.2300079 156H_SCD_DB | H51: 1.0146878 | I51: 1.4944722 | J51: 0.2 | K51: =SUM(H51:J51) -> 2.70916 | M51: . | P51: =31.73/D51/1.13 -> #DIV/0! | R51: =23.5/6.91 -> 3.4008683
B52: XN21 | G52: A.F.D.2300189 156H-SCD_DB | H52: 0.28773185 | I52: 1.4298372 | J52: 0.2 | K52: =SUM(H52:J52) -> 1.917569 | M52: . | P52: =31.73/D52/1.13 -> #DIV/0! | R52: =23.5/6.91 -> 3.4008683
B53: XN21 | G53: A.F.D.2300172 RJ45 DB | H53: 0.41686393 | I53: 2.6958276 | J53: 0.4 | K53: =SUM(H53:J53) -> 3.5126915 | L53: 8111H | M53: .
B54: XN21 | G54: A.F.D.2300289 RJ45 DB | H54: 0.47304459 | I54: 4.5456055 | J54: 0.4 | K54: =SUM(H54:J54) -> 5.4186501 | L54: 8111H；USBHUB | M54: .
B55: XN21 | G55: A.F.D.2300251 USB DB | H55: 0.32011286 | I55: 1.4341463 | J55: 0.2 | K55: =SUM(H55:J55) -> 1.9542592 | M55: .
B56: XN21 | C56: 20240301 | D56: 7.2 | E56: 7.17 | F56: A.F.D.2300197-MP | G56: A.F.D.2300197 LED DB | H56: 0.23631788 | I56: 0.040105155 | J56: 0.2 | K56: =SUM(H56:J56) -> 0.47642304 | M56: .
B57: XN21 | C57: 20240301 | D57: 7.2 | E57: 7.17 | F57: A.F.D.2300243-PVT | G57: A.F.D.2300243 RJ45 DB | H57: 0.62009812 | I57: 4.550072 | J57: 0.4 | K57: =SUM(H57:J57) -> 5.5701701 | L57: 8111H；GL3510 | M57: .
B58: XN21 | C58: 20250326 | D58: 7.25 | E58: 7.17 | F58: A.F.D.2400068-PVT | G58: A.F.D.2400068 USB DB | H58: 0.42621852 | I58: 1.1562113 | J58: 0.2 | K58: =SUM(H58:J58) -> 1.7824299 | L58: GL850G；RTS5170 | M58: .
B59: XN21 | C59: 20241010 | D59: 7.11 | E59: A.F.M.2501978 | F59: A.F.D.2400261-MP | G59: A.F.D.2400261 RJ45 DB | H59: 0.4822451 | I59: 4.4664926 | J59: 0.4 | K59: =SUM(H59:J59) -> 5.3487377 | L59: 含8111H,GL850G,GL3510
B60: XN21 | C60: 20241011 | D60: 6.9264 | E60: A.F.M.2502465 | F60: A.F.D.2400266-MP | G60: A.F.D.2400266 RJ45 DB | H60: 0.58161235 | I60: 2.9149943 | J60: 0.4 | K60: =SUM(H60:J60) -> 3.8966066 | L60: 含8111H、GL3510,含109010782连接器 | Q60: 21.9
B61: XN21 | C61: 20241011 | D61: 7.11 | E61: 7.17 | F61: A.F.D.2400263-PVT | G61: A.F.D.2400263 RJ45 DB | H61: 0.43944044 | I61: 2.562176 | J61: 0.4 | K61: =SUM(H61:J61) -> 3.4016164 | L61: 含8111H
B62: XN21 | C62: 20241025 | D62: 7.11 | E62: 7.17 | F62: A.F.D.2400270-EVT | G62: A.F.D.2400270 RJ45 DB | H62: 0.60099943 | I62: 2.7960579 | J62: 0.4 | K62: =SUM(H62:J62) -> 3.7970574 | L62: 含8111H
B63: XN21 | G63: A.F.D.2300243 RJ45 DB | H63: 0.61076696 | I63: 4.5249335 | J63: 0.4 | K63: =SUM(H63:J63) -> 5.5357004 | L63: 8111H；GL3510 | M63: .
B64: XN21 | C64: 20241213 | D64: 7.3 | E64: 7.17 | F64: A.F.D.2400322-EVT | G64: A.F.D.2400322 RJ45 DB | H64: 0.65819973 | I64: 3.0865496 | J64: 0.4 | K64: =SUM(H64:J64) -> 4.1447493 | L64: RTL8111H;GL850G
B65: XN21 | C65: 20251126 | D65: 7.3 | E65: 7.1 | F65: A.F.D.2400364-PVT | G65: A.F.D.2400364 RJ45 DB | H65: 0.42801944 | I65: 1.1299468 | J65: 0.4 | K65: =SUM(H65:J65) -> 1.9579663 | L65: GL850G;RTS5170
B66: XN21 | C66: 20250103 | D66: 7.3 | E66: 7.17 | F66: A.F.D.2400366-MP | G66: A.F.D.2400366 LED DB | H66: 0.024353407 | I66: 0.037794724 | J66: 0.2 | K66: =SUM(H66:J66) -> 0.26214813 | L66: WF32
B67: XN21 | C67: 20250507 | D67: 7.24 | F67: A.F.D.2500101-PVT | G67: A.F.D.2500101 RJ45 DB | H67: 0.66590965 | I67: 2.7426369 | J67: 0.4 | K67: =SUM(H67:J67) -> 3.8085465 | L67: RTL8111H;GL850G;RTS5170
B68: XN21 | C68: 20250227 | D68: 7.25 | E68: 7.17 | F68: A.F.D.2500028-MP | G68: A.F.D.2500028 RJ45 DB | H68: 0.60660239 | I68: 3.4443705 | J68: 0.4 | K68: =SUM(H68:J68) -> 4.4509729 | L68: RTL8111H;GL3510
B69: XN21 | C69: 20250108 | D69: 7.3 | E69: 7.17 | F69: A.F.D.2400362-MP | G69: A.F.D.2400362 RJ45 DB | H69: 0.5954408 | I69: 2.7098175 | J69: 0.4 | K69: =SUM(H69:J69) -> 3.7052583 | L69: RTL8111H-CG;GL3510-OSY52
B70: XN21 | C70: 20241202 | D70: 7.2 | E70: 7.17 | F70: A.F.D.2400062-PVT | G70: A.F.D.2400062 RJ45 DB | H70: 0.56325145 | I70: 3.3558509 | J70: 0.4 | K70: =SUM(H70:J70) -> 4.3191024 | L70: 8111H；GL3510
B71: XN21 | C71: 20240511 | D71: 7.22 | E71: 7.17 | F71: A.F.D.2400034-PVT | G71: A.F.D.2400034 LED DB | H71: 0.037601673 | I71: 0.039446196 | J71: 0.2 | K71: =SUM(H71:J71) -> 0.27704787
B72: XN21 | C72: 20240605 | D72: 7.25 | E72: 7.17 | F72: A.F.D.2400115-MP | G72: A.F.D.2400115 RJ45 DB | H72: 0.42014674 | I72: 5.9354764 | J72: 0.4 | K72: =SUM(H72:J72) -> 6.7556231 | L72: 含有英特尔雷电IC*1pcs;GL3510
B73: XN21 | C73: 20250618 | D73: 7.19 | F73: A.F.D.2500138-PVT | G73: A.F.D.2500138 RJ45 DB | H73: 0.67874506 | I73: 2.7468733 | J73: 0.4 | K73: =SUM(H73:J73) -> 3.8256183 | L73: GL850G;RTS5170;RTL8111H
B74: XN21 | C74: 20241023 | D74: 7.11 | E74: 7.17 | F74: A.F.D.2400289-MP | G74: A.F.D.2400289 RJ45 DB | H74: 0.63201875 | I74: 2.9149835 | J74: 0.4 | K74: =SUM(H74:J74) -> 3.9470023 | L74: 含有8111H
B75: XN21 | C75: 20241016 | D75: 7.1 | E75: 7.17 | F75: A.F.D.2400154-MP | G75: A.F.D.2400154 RJ45 DB | H75: 0.48604321 | I75: 4.0290705 | J75: 0.4 | K75: =SUM(H75:J75) -> 4.9151137 | L75: 含有8111H；GL3510;RTS5170
B76: XN21 | C76: 20241111 | D76: 7.2 | E76: 7.17 | F76: A.F.D.2400113-EVT | G76: A.F.D.2400113 RJ45 DB | H76: 0.42656997 | I76: 2.1725659 | J76: 0.4 | K76: =SUM(H76:J76) -> 2.9991359 | L76: 含有8111H
B77: XN25 | G77: A.P.10000577-583 DB | H77: 1.6362 | I77: 3.1454286 | J77: 0.4 | K77: =SUM(H77:J77) -> 5.1816286 | M77: .
B78: XN25 | G78: A.P.10000586 156M_DB_POWER | H78: 1.8988 | I78: 9.2631429 | J78: 0.4 | K78: =SUM(H78:J78) -> 11.561943 | L78: 不含两个DC-DC电源模块的成本 | M78: .
B79: XN25 | C79: 20250818 | D79: 7.25 | E79: 7.07 | F79: A.F.D.2400334-PVT | G79: A.F.D.2400334 AUDIO DB | H79: 0.36228574 | I79: 1.4674012 | J79: 0.4 | K79: =SUM(H79:J79) -> 2.229687 | L79: 含ALC269Q
B80: XN25 | C80: 20241113 | D80: 7.2 | E80: 7.17 | F80: A.F.D.2400308-PVT | G80: A.F.D.2400308 AUDIO DB | H80: 0.43734563 | I80: 1.4084576 | J80: 0.2 | K80: =SUM(H80:J80) -> 2.0458032 | L80: ALC269Q-VC3-GR
B81: XN25 | C81: 20241023 | D81: 7.11 | E81: 7.17 | F81: A.F.D.2400297-PVT | G81: A.F.D.2400297 USB DB | H81: 0.44848775 | I81: 1.4342 | J81: 0.2 | K81: =SUM(H81:J81) -> 2.0826877 | L81: 含有ALC269Q;SY6863B3ABC
B82: XN25 | C82: 20250123 | D82: 7.3 | E82: 7.17 | F82: A.F.D.2500020-PVT | G82: A.F.D.2500020 Audio DB | H82: 0.33364168 | I82: 1.257845 | J82: 0.2 | K82: =SUM(H82:J82) -> 1.7914867 | L82: ALC269Q
B83: XN25 | C83: 20240409 | D83: 7.23 | E83: 7.17 | F83: A.F.D.2400022-EVT | G83: A.F.D.2400022 TYPEC_DB | H83: 0.20373766 | I83: 2.7046507 | J83: 0.4 | K83: =SUM(H83:J83) -> 3.3083884 | L83: 含有ALC269Q；GL3510 | M83: .
B84: XN25 | C84: 20250224 | D84: 7.25 | E84: 7.17 | F84: A.F.D.2400255-PVT | G84: A.F.D.2400255 USB DB | H84: 0.34059232 | I84: 1.1207241 | J84: 0.2 | K84: =SUM(H84:J84) -> 1.6613164 | L84: SN6140
B85: XN25 | C85: 20240416 | D85: 7.24 | E85: 7.17 | F85: A.F.D.2400069-MP | G85: A.F.D.2400069 USB DB | H85: 0.16827397 | I85: 1.2761378 | J85: 0.2 | K85: =SUM(H85:J85) -> 1.6444118 | L85: 含有IT66318FN
B86: XN25 | C86: 20240925 | D86: 7.11 | E86: 7.17 | F86: A.F.D.2400208-PVT | G86: A.F.D.2400208 Audio DB | H86: 0.44848775 | I86: 1.365347 | J86: 0.2 | K86: =SUM(H86:J86) -> 2.0138347
B87: XN25 | C87: 20240925 | D87: 7.11 | E87: 7.17 | F87: A.F.D.2400236-EVT | G87: A.F.D.2400236 Audio DB | H87: 0.37869426 | I87: 1.2396555 | J87: 0.2 | K87: =SUM(H87:J87) -> 1.8183497 | P87: =55.2/D87/1.13 -> 6.8705425 | R87: =22.36/D87 -> 3.1448664
B88: XN25 | C88: 20250401 | D88: 7.25 | E88: 7.17 | F88: A.F.D.2500057-PVT | G88: A.F.D.2500057 AUDIO DB | H88: 0.41766066 | I88: 1.3847461 | J88: 0.2 | K88: =SUM(H88:J88) -> 2.0024068 | L88: ALC269Q | P88: =55.2/D88/1.13 -> 6.73787 | R88: =22.36/D88 -> 3.0841379
B89: XN25 | C89: 20250513 | D89: 7.24 | E89: 7.1 | F89: A.F.D.2500109-PVT | G89: A.F.D.2500109 DC DB | H89: 0.081827247 | I89: 0.62743213 | J89: 0.2 | K89: =SUM(H89:J89) -> 0.90925937 | L89: MP3367GR-Z
B90: XN25 | C90: 20250428 | D90: 7.31 | E90: 7.17 | F90: A.F.D.2500076-MP | G90: A.F.D.2500076 AUDIO DB | H90: 0.34236045 | I90: 2.7364059 | J90: 0.2 | K90: =SUM(H90:J90) -> 3.2787663 | L90: ALC269Q
B91: XN25 | C91: 20250402 | D91: 7.25 | E91: 7.17 | F91: A.F.D.2500082-PVT | G91: A.F.D.2500082 AUDIO DB | H91: 0.31946068 | I91: 1.4639898 | J91: 0.2 | K91: =SUM(H91:J91) -> 1.9834505 | L91: ALC269Q
B92: XN25 | C92: 20250618 | D92: 7.19 | E92: 7.17 | F92: A.F.D.2500139-EVT | G92: A.F.D.2500139 Audio DB | H92: 0.36013996 | I92: 2.8780579 | J92: 0.2 | K92: =SUM(H92:J92) -> 3.4381979 | L92: ALC269Q;GL3510
B93: XN25 | C93: 20250618 | D93: 7.19 | E93: 7.13 | F93: A.F.D.2500140-EVT | G93: A.F.D.2500140 Audio DB | H93: 0.36228574 | I93: 1.413835 | J93: 0.2 | K93: =SUM(H93:J93) -> 1.9761208 | L93: ALC269Q
B94: XN25 | C94: 20250106 | D94: 7.3 | E94: 7.17 | F94: A.F.D.2400360-EVT | G94: A.F.D.2400360 USB DB | H94: 0.41644326 | I94: 1.3716349 | J94: 0.2 | K94: =SUM(H94:J94) -> 1.9880782 | L94: ALC269Q
B95: XN25 | C95: 20250826 | D95: 7.17 | E95: 7.13 | F95: A.F.D.2500153-PVT | G95: A.F.D.2500153 AUDIO DB | H95: 0.43499361 | I95: 1.4647736 | J95: 0.2 | K95: =SUM(H95:J95) -> 2.0997672 | L95: ALC269Q
B96: XN25 | C96: 20240919 | D96: 7.11 | E96: 7.17 | F96: A.F.D.2400241-PVT | G96: A.F.D.2400241 Audio DB | H96: 0.44848775 | I96: 1.5524211 | J96: 0.2 | K96: =SUM(H96:J96) -> 2.2009089 | L96: 含ALC269Q | P96: =25.54/D96/1.13 -> 3.1788706
B97: XN50 | F97: A.F.D.2300011 | G97: A.F.D.2300011 RJ45 DB | H97: 4.5469747 | I97: 3.5803021 | J97: 0.4 | K97: =SUM(H97:J97) -> 8.5272767 | L97: 8111H | M97: .
B98: XN50 | D98: 6.901 | F98: A.P.10001030 | G98: A.P.10001030 RJ45 DB | H98: 0.76129348 | I98: 5.8811055 | J98: 0.4 | K98: =SUM(H98:J98) -> 7.042399 | M98: . | T98: LPDDR5X 8GB*2+256UFS*1
B99: XN50 | C99: 20250617 | D99: 7.19 | E99: A.F.M.2503155 | F99: A.F.D.2500137-MP | G99: A.F.D.2500137 RJ45 DB | H99: 0.62578838 | I99: 3.4143232 | J99: 0.4 | K99: =SUM(H99:J99) -> 4.4401116 | L99: ALC269Q;8111H;BH760FJ2LN-B1-0-TR | R99: =24.03/6.91/1.13 -> 3.0774945 | T99: LPDDR4X 8GB*1+256UFS*1
B100: XN50 | C100: 20250716 | E100: 7.17 | F100: A.F.D.2300295 | G100: A.F.D.2300295 RJ45 DB | H100: 0.58215771 | I100: 3.463743 | J100: 0.4 | K100: =SUM(H100:J100) -> 4.4459007 | L100: 8111H;BH760FJ2LN-B1-0-TR | M100: .
...

Sheet E BOM大核
C1: 9月汇率：6.71 | U1: pcb为普通材质OSP工艺，如用特殊材质请单独核;CPU;DDR;SSD;EMMC;WIFI请按需求选配, | W1: - | X1: 类型 | Y1: 型号 | Z1: 美金单项单价 | AB1: - | AC1: 类型 | AD1: 型号 | AE1: 美金单项单价 | AG1: 类型 | AH1: 型号 | AI1: 美金单项单价
W2: - | X2: TYPC IC | Y2: ANX7447QN | Z2: 0.64 | AB2: - | AC2: 加密IC TPM | AD2: 9672 | AE2: 1.05 | AG2: HDMI2.0 | AH2: IT66318FN | AI2: 0.71
W3: - | Y3: CYPD6228 | Z3: 1.7769148 | AB3: - | AI3: =0.48*1.05 -> 0.504
AG4: HDMI2.1 | AH4: ANX7484Q42 | AI4: 0.94
I5: 币种：USD | W5: - | Y5: CYPD6227 | Z5: 1.8079 | AB5: - | AC5: 电量计 | AD5: CW2217 | AE5: 0.23 | AG5: USB3-10G | AH5: GL9901VAE | AI5: 0.37
Y6: CS32G053HRCW6NR/ANX7484Q42 | Z6: 0.99 | AH6: PS8811QFN36 | AI6: =0.9*1.05 -> 0.945
W7: - | Y7: ASL2330AN | Z7: 0.52 | AB7: - | AC7: 雷电IC | AD7: 8040 | AE7: 2.948 | AG7: OLED | AH7: G2708CKU1U | AI7: 2.36
Y8: IT8856FN/CX | Z8: 0.93 | AD8: 9040 | AE8: 3.054
C9: 机型 | D9: PCB尺寸 | E9: 日期 | F9: 汇率 | G9: 料号 | H9: SKU | I9: TPYE-C | J9: 功率 | K9: WIFI | L9: CPU/存储 | M9: WIFI | N9: PCB | O9: PCB | P9: Others | Q9: SMT | R9: TTL | T9: DDR/SSD | U9: 包含可选功能 | V9: 备注 | Y9: IT5272FN | Z9: 1
A10: 3 | B10: 46246 | C10: DN21C(8L+通孔+OSP) | D10: 214.5*120.0*1.0mm | E10: 20240919 | F10: 6.75 | G10: A.F.M.2401621-MP | H10: SKU135 | I10: 单Tpye c IC及双Type c接口（ANX7447QN） | J10: U-15W | K10: 选配 | L10: 现询 | M10: 选配 | N10: 4.77 | O10: =45.18/F10/1.13*1.05 -> 6.219469 | P10: 18.53 | Q10: =24.03/F10/1.13 -> 3.1504425 | R10: =SUBTOTAL(109,O10:Q10) -> 27.899912 | S10: 16.4 | T10: 条子/SSD PCIE3.0 | U10: TPM TPM(9672)； 电量计：CW2217; ROM:128Mb;
A11: 2 | B11: 46246 | D11: 214.5*120.0*1.0mm | E11: 20240919 | F11: 6.75 | G11: A.F.M.2401623-MP | H11: SKU137 | I11: 单Tpye c IC及双Type c接口（ANX7447QN） | J11: H-28W | K11: 选配 | L11: 现询 | M11: 选配 | N11: 4.77 | O11: =45.18/F11/1.13*1.05 -> 6.219469 | P11: 20.2 | Q11: =24.03/F11/1.13 -> 3.1504425 | R11: =SUBTOTAL(109,O11:Q11) -> 29.569912 | S11: 18 | T11: 条子/SSD PCIE3.0 | U11: TPM TPM(9672)； 电量计：CW2217; ROM:128Mb;
A12: 3 | C12: DN25(10L+通孔+OSP) | D12: 188.1*99.2 | E12: 20250827 | F12: 6.75 | G12: A.F.M.2509998 | H12: SKU99 | I12: 单Tpye c IC及双Type c接口（CYPD6227） | J12: U-15W | K12: 选配 | L12: 现询 | M12: 选配 | N12: 4.9455492 | O12: 5.4401041 | P12: 27.4 | Q12: 3.1167329 | R12: =SUBTOTAL(109,O12:Q12) -> 35.956837 | S12: 24.3 | T12: LPDDR5-315球8G*4 | U12: 雷电IC8040; HDMI2.0 IT66318FN； TPM TPM(9672)；电量计： CW2217
A13: 3 | D13: 188.1*99.2 | E13: 20250827 | F13: 6.75 | G13: A.F.M.2509999 | H13: SKU100 | I13: 单Tpye c IC及双Type c接口（CYPD6227） | J13: H-28W | K13: 选配 | L13: 现询 | M13: 选配 | N13: 4.9455492 | O13: 5.4401041 | P13: 29.2 | Q13: 3.1167329 | R13: =SUBTOTAL(109,O13:Q13) -> 37.756837 | S13: 25.95 | T13: LPDDR5-315球8G*4 | U13: 雷电IC8040; HDMI2.0, IT66318FN； TPM TPM(9672)； 电量计：CW2217
A14: 3 | C14: DN79(8L++通孔+OSP) | D14: 237.8*138.1 | E14: 20250827 | F14: 6.7 | G14: A.F.M.2501814 | H14: SKU27 | I14: 单Tpye c IC及双Type c接口（CYPD6227） | J14: U-15W | K14: 选配 | L14: 现询 | M14: 选配 | N14: 6.1542946 | O14: =56.43/F14/1.13*1.05 -> 7.8261128 | P14: 24.4 | Q14: =24.1707/F14/1.13 -> 3.1925373 | R14: =SUBTOTAL(109,O14:Q14) -> 35.41865 | S14: 21.9 | T14: 条子 | U14: 雷电IC8040； HDMI2.0 IT66318FN; TPM TPM(9672) ; USB3-10G GL9901VAE-OGY11 电量计CW2217： ROM:128Mb;
A15: 3 | D15: 237.8*138.1 | E15: 20250827 | F15: 6.7 | G15: A.F.M.2501815 | H15: SKU28/SKU29 | I15: 单Tpye c IC及双Type c接口（CYPD6227） | J15: P/H-28W/45W | K15: 选配 | L15: 现询 | M15: 选配 | N15: 6.1542946 | O15: =56.43/F15/1.13*1.05 -> 7.8261128 | P15: 26.1 | Q15: =24.1707/F15/1.13 -> 3.1925373 | R15: =SUBTOTAL(109,O15:Q15) -> 37.11865 | S15: 23.5 | T15: 条子 | U15: 雷电IC8040； HDMI2.0 IT66318FN; TPM TPM(9672) ; USB3-10G GL9901VAE-OGY11 电量计CW2217； ROM:128Mb;
A16: 3 | C16: MTN25C(10L++通孔+OSP) | D16: 188.1*99.2阴阳铜 | E16: 20250829 | F16: 6.75 | G16: A.F.M.2509000 | H16: SKU99 | I16: 双Type C IC及双Type C 接口（ANX7447QN） | J16: U-15W | K16: 选配 | L16: 现询 | M16: 选配 | N16: =30.8/6.78/1.13*1.4 -> 5.6282142 | O16: =39.2/F16/1.13*1.05 -> 5.3962635 | P16: 24.5 | Q16: =23.91/F16/1.13 -> 3.1347099 | R16: =SUBTOTAL(109,O16:Q16) -> 33.030973 | S16: 21.95 | T16: LPDDR5x-315球4G*4 | U16: TPM TPM(9672)； 电量计：CW2217;； HDMI2.0 IT66318FN; ROM；256Mb
A17: 3 | D17: 188.1*99.2阴阳铜 | E17: 20250829 | F17: 6.75 | G17: A.F.M.2509001 | H17: SKU100 | I17: 双Type C IC及双Type C 接口（ANX7447QN） | J17: H-28W | K17: 选配 | L17: 现询 | M17: 选配 | N17: =30.8/6.78/1.13*1.4 -> 5.6282142 | O17: =39.2/F17/1.13*1.05 -> 5.3962635 | P17: 26.1 | Q17: =23.91/F17/1.13 -> 3.1347099 | R17: =SUBTOTAL(109,O17:Q17) -> 34.630973 | S17: 23.4 | T17: LPDDR5x-315球4G*4 | U17: TPM TPM(9672)； 电量计：CW2217;； HDMI2.0 IT66318FN ROM；256Mb
A18: 3 | C18: MTN25(10L+通孔+OSP) | D18: 188.1*99.2*1.0mm | E18: 20250904 | F18: 6.75 | G18: A.F.M.2900100 | I18: 单Type C IC及两个Type C 接口（CYPD6228） | J18: U-15W | K18: BE200 | L18: 现询 | M18: 现询 | N18: 4.8056225 | O18: 5.2861848 | P18: 30.4 | Q18: =24.86/F18/1.13 -> 3.2592593 | R18: =SUBTOTAL(109,O18:Q18) -> 38.945444 | S18: 27.4 | T18: LPDDR5-315球8G*4 | U18: OLED:G2708CKU1U; 含加密IC TPM(9672)；雷电IC9040;含CW2217; HDMI2.0 :IT66318FN; 降噪钽电
A19: 3 | D19: 188.1*99.2*1.0 | E19: 20250904 | F19: 6.75 | G19: A.F.M.2900101 | I19: 单Tpye c IC及两个Type c接口（CYPD6228） | J19: H-28W | K19: BE200 | L19: 现询 | M19: 现询 | N19: 4.8056225 | O19: 5.2861848 | P19: 32.25 | Q19: =24.86/F19/1.13 -> 3.2592593 | R19: =SUBTOTAL(109,O19:Q19) -> 40.795444 | S19: 29.3 | T19: LPDDR5-315球8G*4 | U19: OLED:G2708CKU1U; 含加密IC TPM(9672)；雷电IC9040;含CW2217: HDMI2.0: IT66318FN；降噪钽电
A20: 3 | C20: DN25C(10L++通孔+OSP) | D20: 188.1*99.2 | E20: 46080 | F20: 6.72 | G20: 全配 | H20: SKU99 | I20: 双Type C IC及双Type C 接口（ANX7447QN） | J20: U-15W | K20: AX101.D2WG.NV | L20: 现询 | M20: - | N20: 4.0104112 | O20: =39.2/F20/1.13*1.05 -> 5.420354 | P20: 26.3 | Q20: =23.3/F20/1.13 -> 3.0683734 | R20: =SUBTOTAL(109,O20:Q20) -> 34.788727 | S20: 21.5 | T20: LPDDR5-315球8G*4 | U20: HDMI2.0:IT66318FN/; TPM: SLB 9672;: 电量计：CW2217: ROM:128Mb
A21: 3 | D21: 188.1*99.2 | E21: 46080 | F21: 6.72 | G21: A.F.M.2510000 | H21: SKU100 | I21: 双Type C IC及双Type C 接口（ANX7447QN） | J21: H-28W | K21: AX101.D2WG.NV | L21: 现询 | M21: - | N21: 4.0104112 | O21: =39.2/F21/1.13*1.05 -> 5.420354 | P21: 28.3 | Q21: =23.3/F21/1.13 -> 3.0683734 | R21: =SUBTOTAL(109,O21:Q21) -> 36.788727 | S21: 23.2 | T21: LPDDR5-315球8G*4 | U21: HDMI2.0:IT66318FN/; TPM: SLB 9672;: 电量计：CW2217: ROM:128Mb
A22: 3 | C22: DP67(10L++通孔+OSP) | D22: 214*88*0.8 | E22: 20250901 | F22: 6.75 | G22: A.F.M.2501282 | H22: SKU19 | I22: 单Type-c IC及双Type c 接口(CYPD6227) | J22: U-15W | K22: 选配 | L22: 现询 | M22: 选配 | N22: 4.9433628 | O22: 5.4376991 | P22: 18.2 | Q22: =22.95/F22/1.13 -> 3.0088496 | R22: =SUBTOTAL(109,O22:Q22) -> 26.646549 | S22: 15.55 | T22: LPDDR4x-200球4GB*4 | U22: 电量计 ：CW2217; ROM:128Mb
A23: 3 | C23: DP67C（10L++通孔+OSP) | D23: 214*88 | E23: 20250805 | F23: 6.75 | G23: A.F.M.2501922-EVT | H23: SKU1 | I23: Type c(双Type c接口)(CYPD6227) | J23: U-15W | K23: AX211.D2WG | L23: 现询 | M23: - | N23: 4.9433628 | O23: 5.4376991 | P23: 18.1 | Q23: 4.1796878 | R23: =SUBTOTAL(109,O23:Q23) -> 27.717387 | S23: 15.6 | T23: LPDDR5X-315球4G*4+0 | U23: 电量计 ：CW2217; ROM:128Mb
A24: 2 | D24: 214*88 | E24: 20250805 | F24: 6.75 | G24: A.F.M.2503368 | H24: SKU6 | I24: Type c(双Type c接口)(CYPD6227) | J24: U-15W | K24: 选配 | L24: 现询 | M24: 选配 | N24: 4.9433628 | O24: 5.4376991 | P24: 18.3 | Q24: 4.1796878 | R24: =SUBTOTAL(109,O24:Q24) -> 27.917387 | S24: 15.9 | T24: LPDDR5X-315球4G*4+0 | U24: 电量计 ：CW2217; ROM:128Mb
A25: 3 | B25: 46251 | C25: DN21F(8L++通孔+OSP) | D25: 214.5*120 | E25: 46157 | F25: 6.75 | G25: A.F.M.2401749 | H25: SKU6 | I25: 单Type C IC及单Type C 接口（ANX7447QN） | J25: H-28W | K25: 选配 | L25: 现询 | M25: 选配 | N25: 4.8771473 | O25: =40.125/F25/1.13*1.05 -> 5.5235988 | P25: 17.34 | Q25: =22.56/F25/1.13 -> 2.9577188 | R25: =SUBTOTAL(109,O25:Q25) -> 25.821318 | S25: 15.5 | T25: 条子 | U25: HDMI2.0:IT66318FN; TPM: SLB 9672V 电量计 ：CW2217; ROM:128Mb
A26: 3 | B26: 46251 | D26: 214.5*120 | E26: 20250903 | F26: 6.75 | G26: A.F.M.2501634 | H26: SKU19 | I26: 单Type C IC及单Type C 接口（ANX7447QN） | J26: U-15W | K26: 选配 | L26: 现询 | M26: 选配 | N26: 4.8771473 | O26: =40.125/F26/1.13*1.05 -> 5.5235988 | P26: 15.74 | Q26: =22.56/F26/1.13 -> 2.9577188 | R26: =SUBTOTAL(109,O26:Q26) -> 24.221318 | S26: 13.5 | T26: 条子 | U26: HDMI2.0:IT66318FN; 电量计 ：CW2217; ROM:128Mb
A27: 3 | B27: 46252 | C27: MTN50(8L+HDI+沉金) | D27: 230.7*120.8 | E27: 20260106 | F27: 6.75 | G27: A.F.M.2401762 | H27: SKU12 | I27: 单Tpye c IC及双Type c接口（RTS5453H） | J27: U-28W | K27: 选配 | L27: 现询 | M27: 选配 | N27: 7.2228006 | O27: =63.81/F27/1.13*1.05 -> 8.7840708 | P27: 32.1 | Q27: =24.12/F27 -> 3.5733333 | R27: =SUBTOTAL(109,O27:Q27) -> 44.457404 | S27: 29.4 | T27: 条子 | U27: 雷电JHL9040R*2； HDMI2.1 ANX7484Q42； TPM:SLB 9672VU; USB3-10G GL9901VAE
A28: 3 | C28: MTN79(8L++通孔+OSP) | D28: 237.8*138.1 | E28: 46151 | F28: 6.7 | G28: A.F.M.2501824 | H28: SKU24 | I28: 单Type C IC及双Type c接口（CYPD6228） | J28: U-15W | K28: 选配 | L28: 现询 | M28: 选配 | N28: 6.1717855 | O28: =56.43/F28/1.13*1.05 -> 7.8261128 | P28: 25.4 | Q28: 3.6572268 | R28: =SUBTOTAL(109,O28:Q28) -> 36.88334 | S28: 22 | T28: 条子 | U28: 电量计CW2217;HDMI2.0 IT66318FN; TPM:SLB 9672; USB3-10G GL9901VAE
A29: 3 | D29: 237.8*138.1 | E29: 46151 | F29: 6.7 | G29: A.F.M.2501825 | H29: SKU25 | I29: 单Type C IC及双Type c接口（CYPD6228） | J29: H-28W | K29: 选配 | L29: 现询 | M29: 选配 | N29: 6.1717855 | O29: =56.43/F29/1.13*1.05 -> 7.8261128 | P29: 29.4 | Q29: 3.6572268 | R29: =SUBTOTAL(109,O29:Q29) -> 40.88334 | S29: 24.3 | T29: 条子 | U29: 电量计CW2217;HDMI2.0 IT66318FN; TPM:SLB 9672; USB3-10G GL9901VAE
A30: 3 | D30: 237.8*138.1 | E30: 46151 | F30: 6.7 | G30: A.F.M.2501826 | H30: SKU26 | I30: 单Type C IC及双Type c接口（CYPD6228） | J30: H-45W | K30: 选配 | L30: 现询 | M30: 选配 | N30: 6.1717855 | O30: =56.43/F30/1.13*1.05 -> 7.8261128 | P30: 30.1 | Q30: 3.6572268 | R30: =SUBTOTAL(109,O30:Q30) -> 41.58334 | S30: 25 | T30: 条子 | U30: 电量计CW2217;HDMI2.0 IT66318FN; TPM:SLB 9672; USB3-10G GL9901VAE
A31: 3 | C31: DN79C(8L++通孔+OSP) | D31: 237.8*138.1 | E31: 20250908 | F31: 6.7 | G31: 全配 | H31: SKU47 | I31: 单Type C IC及双Type C 接口（CYPD6228） | J31: U-15W | K31: 选配 | L31: 现询 | M31: 选配 | N31: 6.3329047 | O31: =56.43/F31/1.13*1.05 -> 7.8261128 | P31: 22.3 | Q31: 3.2876639 | R31: =SUBTOTAL(109,O31:Q31) -> 33.413777 | S31: 19.6 | T31: 条子 | U31: TPM 9672; HDMI2.0 IT66318FN; USB 3-10G GL9901V ;电量计:CW2217;ROM;128Mb
A32: 3 | D32: 237.8*138.1 | E32: 20250908 | F32: 6.7 | G32: 全配 | H32: SKU48/SKU49 | I32: 单Type C IC及双Type C 接口（CYPD6228） | J32: H-28W/45W | K32: 选配 | L32: 现询 | M32: 选配 | N32: 6.3329047 | O32: =56.43/F32/1.13*1.05 -> 7.8261128 | P32: 24.2 | Q32: 3.2876639 | R32: =SUBTOTAL(109,O32:Q32) -> 35.313777 | S32: 21.4 | T32: 条子 | U32: TPM 9672; HDMI2.0 IT66318FN; USB 3-10G GL9901V ;电量计:CW2217;ROM;128Mb
A33: 3 | C33: DN50F(8L++通孔+OSP) | D33: 229.55*122.86 | E33: 202509090 | F33: 6.75 | G33: A.F.M.2400375 | H33: SKU5 | I33: 双Typc c及双Type c 接口(IT8856FN/CX) | J33: P-28W | K33: 选配 | L33: 现询 | M33: 选配 | N33: 6.7730349 | O33: 7.4503384 | P33: 31.08 | Q33: =25.99/F33/1.13 -> 3.4074074 | R33: =SUBTOTAL(109,O33:Q33) -> 41.937746 | S33: 27.9 | T33: 条子 | U33: 雷电JHL9040R*2； HDMI2.0 IT66318FN； TPM:SLB 9672VU; USB3.1-10G PS8811QFN36GTR2
A34: 3 | C34: DN50F(8L++通孔+OSP) | D34: 229.55*122.86 | E34: 46112 | F34: 6.75 | G34: A.F.M.2600626 | H34: SKU19 | I34: 双Typc c及双Type c 接口(IT8856FN/CX) | J34: U-15W | K34: 选配 | L34: 现询 | M34: 选配 | N34: 6.707444 | O34: 7.3781884 | P34: 32.35 | Q34: =25.99/F34/1.13 -> 3.4074074 | R34: =SUBTOTAL(109,O34:Q34) -> 43.135596 | S34: 25.53 | T34: 条子 | U34: 雷电JHL8040R*2； HDMI2.0 IT66318FN; USB3-10G :PS8811QFN36
A35: 3 | C35: DNTU146F(8L+通孔++OSP) | D35: 234.77*117.04 | E35: 20250915 | F35: 6.75 | G35: A.F.M.2502116 | H35: SKU1 | I35: 单Type c及含双Type c接口(ASL2330AN) | J35: U-15W | K35: CDW-61822CE | L35: 现询 | M35: - | N35: =40.94/6.78/1.13*1.05 -> 5.6108544 | O35: =51.63/6.73/1.13*1.05 -> 7.1284961 | P35: 15.2 | Q35: =21.2/F35/1.13 -> 2.7794166 | R35: =SUBTOTAL(109,O35:Q35) -> 25.107913 | S35: 13.03 | T35: 条子 | U35: 电量计：CW2217, ROM:128Mb
A36: 3 | D36: 234.77*117.04 | E36: 20250915 | F36: 6.75 | G36: A.F.M.2502117 | H36: SKU2 | I36: 双Type c及含双Type c接口(ANX7447QN) | J36: H-45W | K36: CDW-61852BE | L36: 现询 | M36: - | N36: =40.94/6.78/1.13*1.05 -> 5.6108544 | O36: =51.63/6.73/1.13*1.05 -> 7.1284961 | P36: 19.2 | Q36: =21.2/F36/1.13 -> 2.7794166 | R36: =SUBTOTAL(109,O36:Q36) -> 29.107913 | S36: 16.77 | T36: 条子 | U36: 电量计：CW2217, ROM:128Mb
A37: 3 | C37: DNTU146A(8L++通孔+OSP) | D37: 234.7*127.2 | E37: 20250825 | F37: 6.75 | G37: A.F.M.2502045-EVT | H37: SKU1 | I37: 双Type c及含双Type c接口((ANX7447QN)) | J37: U-15W | K37: WD_RTL8821CE | L37: 现询 | M37: - | N37: 5.9968766 | O37: =55.99/6.73/1.13*1.05 -> 7.7304764 | P37: 15 | Q37: =21.95/F37/1.13 -> 2.877745 | R37: =SUBTOTAL(109,O37:Q37) -> 25.608221 | S37: 12.76 | T37: 条子 | U37: 电量计：CW2217, ROM:128Mb
A38: 3 | D38: 234.7*127.2 | E38: 20250825 | F38: 6.75 | G38: A.F.M.2502046-EVT | H38: SKU2 | I38: 双Type c及含双Type c接口(ASL2330AN) | J38: H-28W | K38: CDW-61821CE | L38: 现询 | M38: - | N38: 5.9968766 | O38: =55.99/6.73/1.13*1.05 -> 7.7304764 | P38: 17.1 | Q38: =21.95/F38/1.13 -> 2.877745 | R38: =SUBTOTAL(109,O38:Q38) -> 27.708221 | S38: 14.73 | T38: 条子 | U38: 电量计：CW2217, ROM:128Mb
A39: 3 | D39: 234.7*127.2 | E39: 20250825 | F39: 6.75 | G39: A.F.M.2502047-EVT | H39: SKU3 | I39: 双Type c及含双Type c接口((ANX7447QN)) | J39: H-45W | K39: CDW-61822CE | L39: 现询 | M39: - | N39: 5.9968766 | O39: =55.99/6.73/1.13*1.05 -> 7.7304764 | P39: 17.3 | Q39: =21.95/F39/1.13 -> 2.877745 | R39: =SUBTOTAL(109,O39:Q39) -> 27.908221 | S39: 14.94 | T39: 条子 | U39: 电量计：CW2217, ROM:128Mb
A40: 3 | B40: 46246 | C40: DNTU146(8L++通孔+OSP) | D40: 234.7*127.2 | E40: 46058 | F40: 6.75 | G40: A.F.M.2501238-EVT | H40: SKU1 | I40: 单Type c及含双Type c接口(ANX7447QN) | J40: U-15W | K40: 61821CE | L40: 现询 | M40: - | N40: 5.5783446 | O40: =55.99/6.73/1.13*1.05 -> 7.7304764 | P40: 15.5 | Q40: =19.63/F40 -> 2.9081481 | R40: =SUBTOTAL(109,O40:Q40) -> 26.138625 | S40: 13.55 | T40: 条子 | U40: 电量计：CW2217, ROM:128Mb
A41: 3 | B41: 46246 | D41: 234.7*127.2 | E41: 20250613 | F41: 6.75 | G41: A.F.M.2501239-EVT | H41: SKU2 | I41: 双Type c及含双Type c接口(ANX7447QN) | J41: H-45W | K41: AX101.D2WG | L41: 现询 | M41: - | N41: 5.5783446 | O41: =55.99/6.73/1.13*1.05 -> 7.7304764 | P41: 19.2 | Q41: =19.63/F41 -> 2.9081481 | R41: =SUBTOTAL(109,O41:Q41) -> 29.838625 | S41: 17.05 | T41: 条子 | U41: HDMI2.0:IT66318FN/; TPM: SLB 9672;: 电量计：CW2217: ROM:128Mb
A42: 2 | B42: 46246 | D42: 234.7*127.2 | E42: 46057 | F42: 6.75 | G42: A.F.M.2501369 | H42: SKU3 | I42: 双Type c及含双Type c接口(ANX7447QN) | J42: H-28W | K42: 8852BE | L42: 现询 | M42: - | N42: 5.5783446 | O42: =55.99/6.73/1.13*1.05 -> 7.7304764 | P42: 18.7 | Q42: =19.63/F42 -> 2.9081481 | R42: =SUBTOTAL(109,O42:Q42) -> 29.338625 | S42: 16.57 | T42: 条子 | U42: TPM:NPCT760AACYX; ROM:256Mb; 电量计：CW2217:
A43: 3 | C43: DN792(8L++通孔+OSP) | D43: 190.2*134.2 | E43: 20250910 | F43: 6.7 | H43: 全配 | I43: 双Type c及含双Type c接口(ANX7447QN) | J43: U-15W | K43: 选配 | L43: 现询 | M43: 选配 | N43: 4.7834461 | O43: 5.2617907 | P43: 20.7 | Q43: 3.2974395 | R43: =SUBTOTAL(109,O43:Q43) -> 29.25923 | S43: 18 | T43: 条子 | U43: HDMI2.0 IT66318FN; TPM:SLB 9672VU; USB3-10G; ROM: 128Mb; 电量计：CW2217
A44: 2 | C44: DN792(8L++通孔+OSP) | D44: 190.2*134.2 | E44: 20250910 | F44: 6.7 | H44: 全配 | I44: 双Type c及含双Type c接口(ANX7447QN) | J44: H-28W | K44: 选配 | L44: 现询 | M44: 选配 | N44: 4.7834461 | O44: 5.2617907 | P44: 21.5 | Q44: 3.3117216 | R44: =SUBTOTAL(109,O44:Q44) -> 30.073512 | S44: 18.8 | T44: 条子 | U44: HDMI2.0 IT66318FN; TPM:SLB 9672VU; USB3-10G; ROM: 128Mb; 电量计：CW2217
A45: 3 | B45: 46246 | C45: MTNTU146(8L++通孔+OSP) | D45: 234.77*127.19 | E45: 46126 | F45: 6.75 | G45: A.F.M.2501275 | H45: SKU4 | I45: 双Type c及含双Type c接口(ANX7447QN) | J45: U-15W | K45: RTL8822CE | L45: 现询 | M45: - | N45: =41.71/6.78/1.13*1.05 -> 5.7163834 | O45: =55.99/6.73/1.13*1.05 -> 7.7304764 | P45: 19.1 | Q45: =21.6/F45 -> 3.2 | R45: =SUBTOTAL(109,O45:Q45) -> 30.030476 | S45: 16.3 | T45: 条子 | U45: 电量计：CW2217; ROM:256Mb
A46: 3 | B46: 46246 | D46: 234.77*127.19 | E46: 46126 | F46: 6.75 | G46: A.F.M.2501276 | H46: SKU5 | I46: 双Type c及含双Type c接口(ANX7447QN) | J46: H-28W | K46: AX101.D2WG | L46: 现询 | M46: - | N46: =41.71/6.78/1.13*1.05 -> 5.7163834 | O46: =55.99/6.73/1.13*1.05 -> 7.7304764 | P46: 21.3 | Q46: =21.6/F46 -> 3.2 | R46: =SUBTOTAL(109,O46:Q46) -> 32.230476 | S46: 18.4 | T46: 条子 | U46: 电量计：CW2217; ROM:256Mb
A47: 3 | B47: 46246 | D47: 234.77*127.19 | E47: 46126 | F47: 6.75 | G47: A.F.M.2501277 | H47: SKU6 | I47: 双Type c及含双Type c接口(ANX7447QN) | J47: H-45W | K47: 8852BE | L47: 现询 | M47: - | N47: 5.5486726 | O47: =55.99/6.73/1.13*1.05 -> 7.7304764 | P47: 23.4 | Q47: =21.6/F47 -> 3.2 | R47: =SUBTOTAL(109,O47:Q47) -> 34.330476 | S47: 20.2 | T47: 条子 | U47: HDMI2.0 IT66318FN; 电量计：CW2217; ROM:256Mb
A48: 3 | C48: MTNTU146L(8L++通孔+OSP) | D48: 234.7*127.2 | E48: 46083 | F48: 6.75 | G48: A.F.M.2600456 | H48: SKU1 | I48: 双Type c及含双Type c接口(ANX7447QN) | J48: 135H-22W | K48: CDW-61852BE-00 | L48: 现询 | M48: - | N48: 6.2718912 | O48: =55.99/6.73/1.13*1.05 -> 7.7304764 | P48: 24.5 | Q48: =21.54/6.91 -> 3.1172214 | R48: =SUBTOTAL(109,O48:Q48) -> 35.347698 | S48: 21.3 | T48: 条子 | U48: HDMI2.0 IT66318FN; USB3-10G,电量计：CW2217; ROM:256Mb
A49: 3 | C49: MTN21T(8L++通孔+OSP) | D49: 214.85*123.16 | E49: 20250916 | F49: 6.75 | G49: A.F.M.2402384-EVT | H49: SKU1 | I49: Type c(双Type c接口)(RTS5453H) | J49: U-15W | K49: 选配 | L49: 现询 | M49: 选配 | N49: 5.1660593 | O49: 5.6826653 | P49: 29.7 | Q49: =23.5/F49 -> 3.4814815 | R49: =SUBTOTAL(109,O49:Q49) -> 38.864147 | S49: 26.7 | T49: 条子 | U49: 雷电：JHL9040R*2； HDMI2.0 IT66318FN; TPM:SLB 9672VU; USB3-10G GL9901VAE 电量计：CW2217 ; ROM:256Mb
A50: 3 | C50: MTN21T(8L++通孔+OSP) | D50: 214.85*123.16 | E50: 20250916 | F50: 6.75 | G50: A.F.M.2402385 | H50: SKU2 | I50: Type c(双Type c接口)(RTS5453H) | J50: H-28W | K50: 选配 | L50: 现询 | M50: 选配 | N50: 5.1660593 | O50: 5.6826653 | P50: 31.4 | Q50: =23.5/6.91 -> 3.4008683 | R50: =SUBTOTAL(109,O50:Q50) -> 40.483534 | S50: 28.4 | T50: 条子 | U50: 雷电：JHL9040R*2； HDMI2.0 IT66318FN; TPM:SLB 9672VU; USB3-10G GL9901VAE 电量计：CW2217 ; ROM:256Mb
A51: 3 | B51: 46255 | C51: MTN21(8L++通孔+OSP) | D51: 214.85*123.16 | E51: 46081 | F51: 6.75 | G51: A.F.M.2502285 | I51: 单type c IC及一个Type c 接口（CYPD6228） | J51: U-15W | K51: 选配 | L51: 现询 | M51: 选配 | N51: 4.9552317 | O51: =47.5/F51/1.13 -> 6.2274664 | P51: 22.8 | Q51: =23.5/6.91 -> 3.4008683 | R51: =SUBTOTAL(109,O51:Q51) -> 32.428335 | S51: 20.45 | T51: 条子 | U51: HDMI2.0 IT66318FN; TPM:SLB 9672VU; USB3-10G GL9901VAE ； ROM:256Mb
A52: 3 | B52: 46255 | C52: MTN21(8L++通孔+OSP) | E52: 46081 | F52: 6.75 | G52: A.F.M.2402376-OOC | H52: SKU18 | I52: 单type c IC及一个Type c 接口（CYPD6228） | J52: H-28W | K52: 选配 | L52: 现询 | M52: 选配 | N52: 5.3300364 | O52: =47.5/F52/1.13 -> 6.2274664 | P52: 23.7 | Q52: =23.5/6.91 -> 3.4008683 | R52: =SUBTOTAL(109,O52:Q52) -> 33.328335 | S52: 21.4 | T52: 条子 | U52: HDMI2.0 IT66318FN; TPM:SLB 9672VU; USB3-10G GL9901VAE ； ROM:256Mb
A53: 3 | B53: 46254 | C53: MTN79T(8L++通孔+OSP) | D53: 237.8*138.1 | E53: 20250917 | F53: 6.7 | H53: SKU8 | I53: Type c(双Type c接口)(RTS5453H) | J53: U-15W | K53: - | L53: 现询 | M53: - | N53: 6.7889641 | O53: =56.43/F53/1.13*1.05 -> 7.8261128 | P53: 34.12 | Q53: 3.6572268 | R53: =SUBTOTAL(109,O53:Q53) -> 45.60334 | S53: 30.4 | T53: 条子 | U53: 雷电:JHL9040R; HDMI2.0 IT66318FN TPM SLB 9672VU USB3-10G GL9901VAE 电量计CW2217
A54: 3 | B54: 46254 | D54: 237.8*138.1 | E54: 20250917 | F54: 6.7 | H54: SKU9 | I54: Type c(双Type c接口)(RTS5453H) | J54: H-28W | K54: - | L54: 现询 | M54: - | N54: 6.7889641 | O54: =56.43/F54/1.13*1.05 -> 7.8261128 | P54: 32.8 | Q54: 3.6572268 | R54: =SUBTOTAL(109,O54:Q54) -> 44.28334 | S54: 29 | T54: 条子 | U54: 雷电:JHL9040R; HDMI2.0 IT66318FN TPM SLB 9672VU USB3-10G GL9901VAE 电量计CW2217
A55: 3 | B55: 46254 | D55: 237.8*138.1 | E55: 20250917 | F55: 6.7 | H55: SKU10 | I55: Type c(双Type c接口)(RTS5453H) | J55: H-45W | K55: - | L55: 现询 | M55: - | N55: 6.7889641 | O55: =56.43/F55/1.13*1.05 -> 7.8261128 | P55: 35.2 | Q55: 3.6572268 | R55: =SUBTOTAL(109,O55:Q55) -> 46.68334 | S55: 31.3 | T55: 条子 | U55: 雷电:JHL9040R; HDMI2.0 IT66318FN TPM SLB 9672VU USB3-10G GL9901VAE 电量计CW2217
A56: 3 | C56: LN25C(8L++通孔+OSP) | E56: 20250918 | F56: 6.75 | G56: A.F.M.2500394 | H56: SKU6 | I56: 单Type-C IC及双typeC接口（CS32G053H） | J56: 228V/17W（28W） | K56: AX211.D2WG | L56: 现询 | M56: 选配 | N56: 5.945341 | O56: =65.32/6.73/1.13 -> 8.5891991 | P56: 24.1 | Q56: 4.1796878 | R56: =SUBTOTAL(109,O56:Q56) -> 36.868887 | S56: 22.5 | T56: 条子 | U56: HDMI2.0 IT66318FN; 电量计：CW2217; ROM 256Mb
A57: 3 | C57: LN25C(8L++通孔+OSP) | E57: 20251009 | F57: 6.75 | G57: A.F.M.2500392 | H57: SKU4 | I57: 单Type-C IC及双typeC接口（CS32G053H） | J57: 28w | K57: AX211.D2WG | L57: 现询 | M57: 选配 | N57: 5.945341 | O57: =65.32/6.73/1.13 -> 8.5891991 | P57: 21.9 | Q57: 4.1796878 | R57: =SUBTOTAL(109,O57:Q57) -> 34.668887 | S57: 20.3 | T57: 条子 | U57: HDMI2.0 IT66318FN; 电量计：CW2217; ROM 256Mb,OLED: G2708CKU1U
A58: 3 | C58: PN99(10L++通孔+OSP) | E58: 20250918 | F58: 6.75 | G58: A.F.M.2501978 | H58: SKU3 | I58: 单Type c(一个Type c接口)（IT5272FN） | J58: H-45W | K58: 选配 | L58: 现询 | M58: 选配 | N58: 3.8807913 | O58: =36.63/6.75/1.13*1.05 -> 5.0424779 | P58: 25.54 | Q58: 3.4 | R58: =SUBTOTAL(109,O58:Q58) -> 33.982478 | S58: 22.5 | T58: LPDDR5X-315球8G*4 | U58: 雷电：JHL9040R*1； TPM::SLB 9672VU; ROM 256Mb;
A59: 3 | C59: PN99(10L++通孔+OSP) | E59: 46085 | F59: 6.75 | G59: A.F.M.2502465 | H59: SKU7 | I59: 单Type c(一个Type c接口)（IT5272FN） | J59: H-45W | K59: 选配 | L59: 现询 | M59: 选配 | N59: 3.8807913 | O59: =36.63/6.75/1.13*1.05 -> 5.0424779 | P59: 27.38 | Q59: 3.4 | R59: =SUBTOTAL(109,O59:Q59) -> 35.822478 | S59: 23.7 | T59: LPDDR5X-315球16G*4 | U59: 雷电：JHL9040R*1； TPM::SLB 9672VU; OLED:G2708CKU1U; ROM 256Mb;
A60: 3 | C60: DN253(10L++通孔+OSP) | D60: 193.6*100.2*1mm | E60: 20250922 | F60: 6.75 | G60: A.F.M.2501998 | H60: 全配 | I60: 单Type c(双Type c接口)（CS32G053HRCW6NR） | J60: U-15W | K60: AX210.D2WG | L60: 现询 | M60: - | N60: 4.8271733 | O60: 5.3098907 | P60: 23.6 | Q60: 5.2246097 | R60: =SUBTOTAL(109,O60:Q60) -> 34.1345 | S60: 20.7 | T60: 条子 | U60: HDMI2.0 IT66318FN; TPM:SLB9670; 电量计：CW2217; ROM：128Mb; 钽电
A61: 3 | C61: DN253(10L++通孔+OSP) | D61: 193.6*100.2*1mm | E61: 20250922 | F61: 6.75 | G61: A.F.M.2501999 | H61: 全配 | I61: 单Type c(双Type c接口)（CS32G053HRCW6NR） | J61: H-28W | K61: AX210.D2WG | L61: 现询 | M61: - | N61: 4.8271733 | O61: 5.3098907 | P61: 26.74 | Q61: 5.2246097 | R61: =SUBTOTAL(109,O61:Q61) -> 37.2745 | S61: 22.6 | T61: 条子 | U61: HDMI2.0 IT66318FN; TPM:SLB9670; 电量计：CW2217; ROM：128Mb; 钽电
A62: 3 | B62: 46251 | C62: DNTU(8L++通孔+OSP) | E62: 20250922 | F62: 6.75 | G62: A.F.M.2501736 | H62: SKU30 | I62: 单Type c及单Type c接口(ANX7447QN) | J62: U-15W | K62: 选配 | L62: 现询 | M62: 选配 | N62: =59.28/6.78/1.13 -> 7.7374892 | O62: =65.23/F62/1.13 -> 8.5519502 | P62: 15.3 | Q62: =22.42/F62/1.13 -> 2.9393641 | R62: =SUBTOTAL(109,O62:Q62) -> 26.791314 | S62: 12.7 | T62: 条子 | U62: 电量计：CW2217; ROM:128Mb
A63: 3 | B63: 46251 | C63: DNTU(8L++通孔+OSP) | E63: 20250922 | F63: 6.75 | G63: A.F.M.2501557-MP | H63: SKU27 | I63: 单Type c及单Type c接口(ANX7447QN) | J63: H-25W | K63: 选配 | L63: 现询 | M63: 选配 | N63: =59.28/6.78/1.13 -> 7.7374892 | O63: =65.23/F63/1.13 -> 8.5519502 | P63: 18.2 | Q63: =22.42/F63/1.13 -> 2.9393641 | R63: =SUBTOTAL(109,O63:Q63) -> 29.691314 | S63: 15.6 | T63: 条子 | U63: 电量计：CW2217; ROM:128Mb
A64: 3 | C64: DN102(8L++通孔+OSP) | E64: 20250923 | F64: 6.75 | G64: A.F.M.2402449-EVT | H64: SKU2 | I64: 单Type c及单Type c接口(ANX7447QN) | J64: U-15W | K64: 61821CE | L64: 现询 | M64: - | N64: 6.3951067 | O64: 7.0346174 | P64: 16.7 | Q64: 4 | R64: =SUBTOTAL(109,O64:Q64) -> 27.734617 | S64: 14.3 | T64: 条子 | U64: TPM:SLB 9672V; 电量计：CW2217; ROM:128Mb
A65: 3 | C65: PN50(8L++通孔+OSP) | D65: 230.7*120.78 | E65: 20250925 | F65: 6.75 | G65: A.F.M.2502016 | H65: SKU2 | I65: 单Type c(双Type c接口)IT5272FN | J65: H-25W | K65: 选配 | L65: 现询 | M65: 选配 | N65: 5.7485685 | O65: 6.3234253 | P65: 29.34 | Q65: 4.1796878 | R65: =SUBTOTAL(109,O65:Q65) -> 39.843113 | S65: 26.8 | T65: 条子 | U65: 雷电：JHL9040R*2; HDMI2.1; ANX7484Q42; TPM:SLB 9672; USB3-10G;GL9901VAE;ROM:256Mb
A66: 3 | C66: MTS12(8L++通孔+OSP) | E66: 20250928 | F66: 6.75 | G66: A.F.M.2502142 | H66: SKU5 | I66: 单Type c及一个Type c接口(RTS5453H) | J66: H-28W | K66: 选配 | L66: 现询 | M66: 选配 | N66: 8.6294118 | O66: 9.4923529 | P66: 75 | Q66: 5.2246097 | R66: =SUBTOTAL(109,O66:Q66) -> 89.716963 | S66: 68 | T66: 非贴片 | U66: 雷电：JHL9040R*2； HDMI2.1 ANX7484Q42 ; 万兆网口IC:RTL8127AT-CG; USB3-10G GL9901VAE ; ROM:256Mb
A67: 2 | C67: DN525E(8L++通孔+OSP) | E67: 20250928 | F67: 6.75 | G67: A.F.M.2502146 | H67: SKU8 | I67: 单Type c及含双Type c接口(ANX7447QN) | J67: H-25W | K67: AX101.D2WG | L67: 现询 | M67: - | N67: 4.4429984 | O67: 4.8872983 | P67: 16.53 | Q67: =20/F67 -> 2.962963 | R67: =SUBTOTAL(109,O67:Q67) -> 24.380261 | S67: 14.85 | T67: 条子 | U67: ROM:128Mb;
A68: 3 | C68: DNXU(8L++通孔+OSP) | D68: 207*178.7*1mm | E68: 20250928 | F68: 6.75 | G68: A.F.M.2402293-MP | H68: SKU25 | I68: 单Type c及单Type c接口(ANX7447QN) | J68: U-15W | K68: 9560.D2WG | L68: 现询 | M68: - | N68: 4.1025508 | O68: 4.5128058 | P68: 14.5 | Q68: =20.64/F68/1.13 -> 2.705998 | R68: =SUBTOTAL(109,O68:Q68) -> 21.718804 | S68: 12.33 | T68: 条子 | U68: 电量计：CW2015CHBD； ROM:128Mb
A69: 3 | C69: DNXU(8L++通孔+OSP) | D69: 207*178.7*1mm | E69: 20251010 | F69: 6.75 | G69: A.F.M.2401715-MP | H69: SKU23 | I69: 单Type c及单Type c接口(ANX7447QN) | J69: H-28W | K69: 9560.D2WG | L69: 现询 | M69: - | N69: 4.1025508 | O69: 4.5128058 | P69: 15.4 | Q69: =20.64/F69/1.13 -> 2.705998 | R69: =SUBTOTAL(109,O69:Q69) -> 22.618804 | S69: 13.2 | T69: 条子 | U69: 电量计：CW2015CHBD； ROM:128Mb
A70: 3 | C70: DNXU(8L++通孔+OSP) | D70: 207*178.7*1mm | E70: 20250928 | F70: 6.75 | G70: A.F.M.2401781-MP | H70: SKU24 | I70: 单Type c及单Type c接口(ANX7447QN) | J70: H-45W | K70: 9560.D2WG | L70: 现询 | M70: - | N70: 4.1025508 | O70: 4.5128058 | P70: 15.8 | Q70: =20.64/F70/1.13 -> 2.705998 | R70: =SUBTOTAL(109,O70:Q70) -> 23.018804 | S70: 13.58 | T70: 条子 | U70: 电量计：CW22217; ROM:128Mb
A71: 3 | C71: LP88（8L+HDI2+OSP） | D71: 231.55*80.94*0.8mm | E71: 20250929 | F71: 6.75 | G71: A.F.M.2502003-MP | H71: SKU7 | I71: 单Type c IC及双接口（CYPD6228） | J71: CPU/DDR一体式 | K71: BE200.D2WG | L71: 现询 | M71: - | N71: 7.6928683 | O71: 8.4621551 | P71: 42.7 | Q71: =24.05/F71 -> 3.562963 | R71: =SUBTOTAL(109,O71:Q71) -> 54.725118 | S71: 40.58 | T71: 条子 | U71: 雷电JHL9040R_*2： TPM:SLB 9672; ROM:256Mb; 钽电容
A72: 3 | C72: DN59E（8L+通孔+沉金） | D72: 269.1*134.33*1mm | E72: 20251013 | F72: 6.75 | G72: A.F.M.2302162 | H72: SKU7 | I72: 单Type c IC及双接口（CYPD6227） | J72: P-28W | K72: 选配 | L72: 现询 | M72: 选配 | N72: 7.0588235 | O72: 7.7647059 | P72: 27.83 | Q72: =24.78/F72/1.13 -> 3.2487709 | R72: =SUBTOTAL(109,O72:Q72) -> 38.843477 | S72: 24.88 | T72: 条子 | U72: 雷电：JHL8040R*1： HDMI2.0: IT66318FN;OLED:G2708CKU1U; USB3.1-10G:PS8811QFN36GTR2; ROM:128Mb；
A73: 3 | C73: DN5E(8L+HDI2+OSP) | D73: 185.0*110.8*1mm | E73: 20251013 | F73: 6.75 | G73: A.F.M.2401867-PVT | H73: SKU1 | I73: Type c(双Type c接口)(ANX7447QN) | J73: U-15W | K73: AX201.D2WG | L73: 现询 | M73: - | N73: 6.3982301 | O73: 7.0380531 | P73: 16.4 | Q73: =28.8941/F73/1.13 -> 3.7881481 | R73: =SUBTOTAL(109,O73:Q73) -> 27.226201 | S73: 13.8 | T73: LPDDR4X-556球8G*2+0 | U73: ROM:128Mb
A74: 3 | C74: MTP13(10L++通孔+OSP) | D74: 211.6*102.16*1.0mm | E74: 20250630 | F74: 6.72 | G74: A.F.M.2501448 | H74: SKU2 | I74: 双Type C IC及双Type C 接口（ANX7447QN） | J74: U-15W | K74: 选配 | L74: 现询 | M74: 现询 | N74: =61.21/6.78/1.13*1.05 -> 8.3888715 | O74: =81.78/F74/1.13 -> 10.769595 | P74: 27.1 | Q74: 4 | R74: =SUBTOTAL(109,O74:Q74) -> 41.869595 | S74: 24.5 | T74: LPDDR5-315球8G*4+0 | U74: HDMI2.0:IT66318FN: TPM;LB 9672VU; ROM:256Mb;
A75: 3 | C75: PN252(10L++通孔+OSP) | D75: 201.6*104.3*1.0mm | E75: 46059 | F75: 6.75 | G75: A.F.M.2502249 | H75: SKU1 | I75: 单Type C IC及双Type C 接口（IT5272FN） | J75: H-45W | K75: AX211.D2W | L75: 现询 | M75: - | N75: 5.5190005 | O75: 6.0709006 | P75: 26.9 | Q75: 4.1796878 | R75: =SUBTOTAL(109,O75:Q75) -> 37.150588 | S75: 23.93 | T75: LPDDR5-315球4G*4+0 | U75: （IT5272FN）； TPM； CW2217; 雷电IC*2pcs（9040）
A76: 3 | C76: PN252(10L++通孔+OSP) | D76: 201.6*104.3*1.0mm | E76: 46059 | F76: 6.75 | G76: A.F.M.2502619 | H76: SKU6 | I76: 单Type C IC及双Type C 接口（IT5272FN） | J76: H-45W | K76: AX211.D2W | L76: 现询 | M76: - | N76: 5.5190005 | O76: 6.0709006 | P76: 33.6 | Q76: 4.1796878 | R76: =SUBTOTAL(109,O76:Q76) -> 43.850588 | S76: 30.24 | T76: LPDDR5-315球8G*4+0 | U76: 雷电JHL9040R*2： HDMI2.0:IT66318FN; TPM:SLB 9672; OLED:G2708CKU1U; ROM:256Mb; 钽电
A77: 3 | C77: DP13C(10L++通孔+OSP) | E77: 20251128 | F77: 6.75 | G77: A.F.M.2502322 | H77: SKU4 | I77: 双Type c(双Type c接口)(ANX7447QN) | J77: U-15W | K77: AX201.D2WG | L77: 现询 | M77: - | N77: 6.7199375 | O77: 7.3919313 | P77: 21.9 | Q77: =23.73/F77/1.13 -> 3.1111111 | R77: =SUBTOTAL(109,O77:Q77) -> 32.403042 | S77: 19.3 | T77: LPDDR5X-315球6G*4+0 | U77: TPM:SLB 9672; 电量计： CW2217; ROM:128Mb
A78: 3 | C78: DN50Z(8L+通孔+沉金) | D78: 197.1*166.2*1.0 | E78: 46084 | F78: 6.75 | G78: A.F.M.2300377 | H78: SKU41 | I78: 双Type C IC及双Type C 接口（IT8856FN） | J78: P-28W | K78: 选配 | L78: 现询 | M78: 选配 | N78: 6.8604893 | O78: 7.5465383 | P78: 29.1 | Q78: =24.1/F78 -> 3.5703704 | R78: =SUBTOTAL(109,O78:Q78) -> 40.216909 | S78: 25.9 | T78: 条子 | U78: 雷电;JHL8040R*1; HDMI2.0:IT66318FN; USB3-10G:PS8811QFN36GTR2;
A79: 3 | C79: DN50Z(8L+通孔+沉金) | E79: 20240514 | F79: 6.75 | G79: A.F.M.2400398-MP | H79: SKU67 | I79: 双Type C IC及双Type C 接口（IT8856FN） | J79: U-15W | K79: 选配 | L79: 现询 | M79: 选配 | N79: 5.5674128 | O79: 6.1241541 | P79: 25.9 | Q79: =24.1/F79 -> 3.5703704 | R79: =SUBTOTAL(109,O79:Q79) -> 35.594524 | S79: 22.9 | T79: 条子 | U79: 雷电JHL8040R*1； HDMI2.0:IT66318FN ; USB3.1-10G:PS8811QFN36GTR2; ROM:256Mb
A80: 3 | C80: PN79(8L++通孔+OSP) | D80: 25mm*50mm_1.26mm | E80: 20251114 | F80: 6.7 | G80: A.F.M.2502580 | H80: SKU3 | I80: 单Type C IC及双Type C 接口（IT5272FN） | J80: H-45W | K80: 选配 | L80: 现询 | M80: 选配 | N80: 6.6949505 | O80: 7.3644456 | P80: 30.82 | Q80: 5.2246097 | R80: =SUBTOTAL(109,O80:Q80) -> 43.409055 | S80: 28.2 | T80: 条子 | U80: TPM TPM； CW2217; 雷电IC 9040*2PCS; HDMI2.0 :IT66318FN; TPM:SLB 9672; ROM: 256Mb；
A81: 3 | C81: DN39D(10L++通孔+OSP) | E81: 20251118 | F81: 6.75 | G81: A.F.M.2502956 | H81: SKU3 | I81: 单Type c(双Type c接口)（CS32G053HRCW6NR） | J81: U-15W | K81: 选配 | L81: 现询 | M81: 选配 | N81: 8.2769391 | O81: 9.104633 | P81: 19.1 | Q81: 4.3886722 | R81: =SUBTOTAL(109,O81:Q81) -> 32.593305 | S81: 15.8 | T81: 条子 | U81: HDMI2.0:IT66318FN; USB3.0 : ROM:128Mb; USB3.0:GL9901VAE-; PCB参考DN39的pcb
A82: 3 | B82: 46246 | C82: MTNTU146B(10L+HDI2+OSP) | D82: 206.6*127.2 | E82: 20251118 | F82: 6.75 | G82: A.F.M.2502661 | H82: SKU1 | I82: 单Type C IC及双Type C 接口（ANX7447QN） | J82: U-15W | K82: 61851BE | L82: 现询 | M82: - | N82: =86.75/6.78/1.13*1.1 -> 12.455295 | O82: =93.85/F82/1.13*1.05 -> 12.919371 | P82: 18.1 | Q82: =22.36/F82 -> 3.3125926 | R82: =SUBTOTAL(109,O82:Q82) -> 34.331963 | S82: 15.145853 | T82: LPDDR5X-496球8G*2+0 | U82: 电量计CW2217, ROM :256Mb,PCB为科翔价格
A83: 3 | B83: 46246 | C83: MTNTU146B(10L+HDI2+OSP) | D83: 206.6*127.2 | E83: 20251118 | F83: 6.75 | G83: A.F.M.2502662 | H83: SKU2 | I83: C口全功能及双Type C 接口（ASL2330AN） | J83: H-28W | K83: 61851BE | L83: 现询 | M83: - | N83: =86.75/6.78/1.13*1.1 -> 12.455295 | O83: =93.85/F83/1.13*1.05 -> 12.919371 | P83: 19.9 | Q83: =22.36/F83 -> 3.3125926 | R83: =SUBTOTAL(109,O83:Q83) -> 36.131963 | S83: 17 | T83: LPDDR5X-496球16G*2+0 | U83: 电量计CW2217, ROM :256Mb,PCB为科翔价格
A84: 2 | C84: DN87(8L++通孔+OSP) | D84: 258.0*128.0*1.0mm | E84: 20251114 | F84: 6.75 | G84: A.F.M.2401989-PVT | H84: SKU3 | I84: 单Type c IC (单Type c接口)ANX7447QN | J84: U-15W | K84: 选配 | L84: 现询 | M84: 选配 | N84: 5.9312858 | O84: 6.5244144 | P84: 14.9 | Q84: =22.6/F84/1.13 -> 2.962963 | R84: =SUBTOTAL(109,O84:Q84) -> 24.387377 | S84: 12.866631 | T84: 条子 | U84: 电量计 ：CW2217; ROM:128Mb
A85: 3 | C85: MTN21B(10L+HDI2+OSP) | D85: 214.9x123.2 | E85: 46126 | F85: 6.75 | G85: A.F.M.2503359 | H85: SKU4 | I85: 单Type C IC及双Type C 接口（CS32G053HRCW6NR） | K85: - | L85: 现询 | M85: - | N85: 10.413326 | O85: 11.454659 | P85: 19.5 | Q85: =27.12/F85/1.13 -> 3.5555556 | R85: =SUBTOTAL(109,O85:Q85) -> 34.510215 | S85: 16.8 | T85: LPDDR5X-496球8G*2+0 | U85: 电量计 ：CW2217; ROM:256Mb
A86: 3 | C86: MTN21B(10L+HDI2+OSP) | D86: 214.9x123.2 | E86: 20251128 | F86: 6.75 | G86: A.F.M.2502632 | H86: SKU3 | I86: 单type c IC及双Type c 接口（CS32G053HRCW6NR） | J86: H-28W | K86: 选配 | L86: 现询 | M86: 选配 | N86: 8.5533576 | O86: 9.4086934 | P86: 22.4 | Q86: =27.12/F86/1.13 -> 3.5555556 | R86: =SUBTOTAL(109,O86:Q86) -> 35.364249 | S86: 19.9 | T86: LPDDR5X-496球16G+0 | U86: HDMI2.0:IT66318FN; TPM:SLB 9672; 电量计：CW2217; USB-10G USB3.0:GL9901; ROM:256Mb USB3.1-10G:GL9901VAE;
A87: 3 | C87: LP13（8L+HDI2+沉金） | D87: 211.6*102.16*1.0mm | E87: 20251128 | F87: 6.75 | G87: A.F.M.2502474 | H87: SKU1 | I87: 双Type c(双Type c接口)（CS32G053HRCW6NR） | J87: Ultra-5-226V(16GB) | K87: AX211.D2WG | L87: 现询 | M87: - | N87: 10.761895 | O87: 11.838084 | P87: 34.2 | Q87: 4.1796878 | R87: =SUBTOTAL(109,O87:Q87) -> 50.217772 | S87: 31.8 | T87: 条子 | U87: 雷电：JHL9040R*1；HDMI2.0:IT66318 FN; ROM:256Mb ; USB3-10G GL9901VAE; 电量计：CW2217; ROM:128Mb
A88: 2 | C88: MTN793(10L++通孔+OSP) | D88: 190.2x134.2x1.0mm | E88: 20251212 | F88: 6.7 | G88: A.F.M.2502676 | H88: 496BALL DDR 15W满配置 | I88: 单type c IC及双Type c 接口（CS32G053HRCW6NR） | J88: H-28W | K88: AX101.D2WG | L88: 现询 | M88: - | N88: 6.36 | O88: 6.996 | P88: 24.8 | Q88: 4.1796878 | R88: =SUBTOTAL(109,O88:Q88) -> 35.975688 | S88: 21.4 | T88: LPDDR5X-496球转接小板 | U88: HDMI2.0:IT66318FN; TPM:SLB 9672: USB3-10G:GL9901VAE; 电量计：CW2217: ROM:256Mb
A89: 3 | C89: MTN793(10L++通孔+OSP) | D89: 190.2x134.2x1.0mm | E89: 46161 | F89: 6.7 | G89: A.F.M.2502675 | H89: 315BALL DDR 15W满配置 | I89: 单type c IC及双Type c 接口（CS32G053HRCW6NR） | J89: U-15W | K89: AX101.D2WG.NV | L89: 现询 | M89: - | N89: 6.36 | O89: 6.996 | P89: 22.5 | Q89: 4.1796878 | R89: =SUBTOTAL(109,O89:Q89) -> 33.675688 | S89: 18.9 | T89: LPDDR5 4GB*4 315球 | U89: HDMI2.0:IT66318FN; TPM:SLB 9672: USB3-10G:GL9901VAE; 电量计：CW2217: ROM:256Mb
A90: 3 | C90: DN21B(8L++通孔+OSP) | E90: 20251223 | F90: 6.75 | G90: A.F.M.2502043 | H90: SKU18 | I90: 单Type c IC及双接口（CYPD6227） | J90: P-28W | K90: 选配 | L90: 现询 | M90: 选配 | N90: 4.7678293 | O90: 5.2446122 | P90: 20.6 | Q90: =27.12/F90/1.13 -> 3.5555556 | R90: =SUBTOTAL(109,O90:Q90) -> 29.400168 | S90: 18.15 | T90: 条子 | U90: HDMI2.0 :IT66318FN; 电量计：CW2217； TPM :SLB 9672 ; USB3-10G GL9901; ROM：128Mb;
A91: 3 | C91: DN75(8L++通孔+OSP) | E91: 46035 | F91: 6.75 | G91: A.F.M.2402410 | H91: SKU10 | I91: 单Type c IC及双接口（CYPD6227） | J91: 28W | K91: 选配 | L91: 现询 | M91: 选配 | N91: 4.6272775 | O91: 5.0900052 | P91: 20.8 | Q91: =19.85/F91/1.13 -> 2.6024254 | R91: =SUBTOTAL(109,O91:Q91) -> 28.492431 | S91: 18.5 | T91: SODIM条子 | U91: TPM:SLB 9672V; ; ROM:256Mb
A92: 2 | C92: WN792(6L+通孔+OSP) | D92: 190.2*134.2*1mm | E92: 46120 | F92: 6.7 | G92: A.F.M.2600136高配 | H92: SKU1 | I92: 单Type c IC及双TYPE-C接口(IT5272F) | J92: U-15W | K92: - | L92: 现询 | M92: - | N92: 3.38886 | O92: 3.727746 | P92: 21.74 | Q92: =22/F92 -> 3.2835821 | R92: =SUBTOTAL(109,O92:Q92) -> 28.751328 | S92: 19 | T92: 条子+UFS | U92: HDMI2.0 LT86101UXS; USB3-10G GL9901VA; TPM SLB 9672; ROM:256ROM,钽电
A93: 3 | B93: 46251 | C93: WN21B(6L+通孔+OSP） | D93: 214.9x123.1x1mm | E93: 46115 | F93: 6.75 | G93: A.F.M.27000XX | H93: SKU1 | I93: 单Type c IC及双TYPE-C接口 | J93: U-15W | K93: - | L93: 现询 | M93: - | N93: 4.9394586 | O93: =38.5/F93/1.13*1.05 -> 5.2999017 | P93: 24.6 | Q93: =22/F93 -> 3.2592593 | R93: =SUBTOTAL(109,O93:Q93) -> 33.159161 | S93: 21.67 | T93: LPDDR5X 8GB*2+256UFS | U93: HDMI2.0:LT86101UXS; TPM SLB 9672 /OLED G2708CKU1U; 电量计：CW2217; ROM:256Mb; USB3-10G:GL9901VAE; 钽电
A94: 3 | C94: DN21D( 8L+HDI2+OSP) | D94: 214.8x119.9x1mm | E94: 46106 | F94: 6.75 | G94: A.F.M.2600726 | H94: SKU1 | I94: 单Type c IC及单TYPE-C接口(CS32G053HRCW6NR) | J94: U-15W | K94: 选配 | L94: 现询 | M94: 选配 | N94: =72.15/6.78/1.13*1.05 -> 9.8882058 | O94: =87.09/6.75/1.13 -> 11.417896 | P94: 15.2 | Q94: =24.03/6.91/1.13 -> 3.0774945 | R94: =SUBTOTAL(109,O94:Q94) -> 29.69539 | S94: 12.84 | T94: LPDDR4X 8GB*1+256UFS | U94: 电量计 ：CW2217; ROM:128Mb
A95: 3 | C95: WN25(6L+通孔+OSP+无卤) | D95: 187.0*99.2*1.0mm | E95: 20251224 | F95: 6.75 | G95: A.F.M.2600XXX | H95: SKU1 | I95: 单Type C IC及双Type C 接口（IT5272FN） | J95: U-15W | K95: AX211.D2WG | L95: 现询 | M95: - | N95: 3.3529412 | O95: =33.34/F95/1.13*1.05 -> 4.5895772 | P95: 23.9 | Q95: =20.1/F95 -> 2.9777778 | R95: =SUBTOTAL(109,O95:Q95) -> 31.467355 | S95: 21.1 | T95: LPDDR5-315球8G*2+0 | U95: HDMI 2.0 IT66318FN /TPM SLB 9672 /OLED G2708CKU1U/ROM, 256Mb; 无卤PCB ;钽电
A96: 3 | C96: PN793(10L++通孔+OSP) | D96: 190.2*134.2*1mm | E96: 46043 | F96: 6.7 | G96: A.F.M.2600014 | H96: SKU1 | I96: 单Type C IC及单Type C 接口 | J96: H-45W | K96: 现询 | L96: 现询 | M96: 现询 | N96: 5.9031754 | O96: 6.493493 | P96: 27 | Q96: =26/F96 -> 3.880597 | R96: =SUBTOTAL(109,O96:Q96) -> 37.37409 | S96: 24.4 | T96: LPDDR5-315球8G*4+0 | U96: 雷电JHL9040R*1：HDMI2.0 IT66318FN; TPM:SLB 9672; ROM: 256Mb; USB3-10G:GL9901,钽电
A97: 3 | B97: 46252 | C97: RPLK3（6L+通孔+OSP) | D97: 184x170x1.6mm | E97: 46049 | F97: 6.75 | G97: A.F.M.2600743 | H97: SKU5 | I97: - | J97: H-45W | K97: 选配 | L97: 现询 | M97: 选配 | N97: 4.6986438 | O97: =41.68/F97/1.13*1.05 -> 5.7376598 | P97: 18.8 | Q97: =32/F97 -> 4.7407407 | R97: =SUBTOTAL(109,O97:Q97) -> 29.278401 | S97: 16.32 | T97: 条子 | U97: RJ45:RTL8111H ; ROM 128Mb ;
A98: 3 | C98: WNTU146B（6L+通孔+OSP) | D98: 206.6mm*127.2mm*1mm | E98: 46097 | F98: 6.75 | G98: A.F.M.2600458 | H98: SKU3 | I98: 单Type c IC及双接口 | J98: 25W | K98: CDW-61851BE-00 | L98: 现询 | M98: - | N98: =30.95/6.78/1.13*1.05 -> 4.2417182 | O98: =36.22/6.73/1.13*1.2 -> 5.7152625 | P98: 17.8 | Q98: =22.5/F98 -> 3.3333333 | R98: =SUBTOTAL(109,O98:Q98) -> 26.848596 | S98: 15.5 | T98: 条子 | U98: DDR转接小板；电量计：CW217; ROM 256Mb;
A99: 3 | C99: WNTU146B（6L+通孔+OSP) | D99: 206.6*127.2*1mm | E99: 46120 | F99: 6.75 | G99: A.F.M.2600822（高配） | H99: SKU6 | I99: 单Type c IC及双接口 | J99: 28W | K99: WD_RTL8852BELGA | L99: 现询 | M99: - | N99: =30.95/6.78/1.13*1.05 -> 4.2417182 | O99: =36.22/6.73/1.13*1.2 -> 5.7152625 | P99: 21.3 | Q99: =22.5/F99 -> 3.3333333 | R99: =SUBTOTAL(109,O99:Q99) -> 30.348596 | S99: 18.7 | T99: 0+512UFS | U99: HDMI2.0 IT66318FN /TPM2.0 SLB 9672 /ROM :256Mb; 电量计：CW2217; 钽电容
A100: 3 | C100: WN35(8L+通孔+OSP+无卤） | D100: 182.3*101.0*1.0mm | E100: 46126 | F100: 6.75 | G100: A.F.M.2600712(高配） | H100: SKU1 | I100: 单Type C IC及双Type c 接口(IT5272) | J100: U-15W | K100: AX211.D2WG.NV | L100: 现询 | M100: - | N100: 3.782405 | O100: =39.3/F100/1.13*1.05 -> 5.4100295 | P100: 22.8 | Q100: =22.5/F100 -> 3.3333333 | R100: =SUBTOTAL(109,O100:Q100) -> 31.543363 | S100: 20 | T100: 8GB(315球)*2 +512UFS | U100: HDMI2.0 IT66318FN ；TPM：SLB 9672 ； AMOLED G2708CKU1U ；ROM:256Mb, SMT为预估计。普通PCB2.83U
...

Sheet 对比差异
B1: 12月份汇率：7.04币种:USA
B2: 机型 | C2: 功率 | D2: 配置 | E2: Others | F2: PCB | G2: SMT | H2: TTL | I2: 备注 | J2: 差异点
B3: MTNTU146(8L+通孔+OSP) | C3: H-28W | D3: 0+0 | E3: 17.965528 | F3: =35.53/7.04/1.13 -> 4.4662611 | G3: 3 | H3: =SUM(E3:G3) -> 25.431789 | I3: SMT预估 | J3: 两颗DIMM/DDR5座子，两颗7447
B4: MTNTU146B(10L+HDI2+OSP) | C4: H-28W | D4: 0+0 | E4: 16.189418 | F4: =47.32/7.04/1.13 -> 5.9483105 | G4: 3.2 | H4: =SUM(E4:G4) -> 25.337728 | I4: SMT预估 | J4: 单颗7447
D5: 差异 | E5: =E4-E3 -> -1.77611 | F5: =F4-F3 -> 1.4820495 | G5: =G4-G3 -> 0.2 | H5: =H4-H3 -> -0.094060547
B6: MTN21(8L+通孔+OSP) | C6: H-28W | D6: 0+0 | E6: 20.25 | F6: =30.43/7.04/1.13 -> 3.825171 | G6: =25.08/7.04/1.13 -> 3.1526549 | H6: =SUM(E6:G6) -> 27.227826
B7: MTN21B(10L+HDI2+OSP) | C7: H-28W | D7: 0+0 | E7: 20 | F7: =47.63/7.04/1.13 -> 5.9872788 | G7: =27.12/7.04/1.13 -> 3.4090909 | H7: =SUM(E7:G7) -> 29.39637 | I7: SMT预估
D8: 差异 | E8: =E7-E6 -> -0.25 | F8: =F7-F6 -> 2.1621078 | G8: =G7-G6 -> 0.25643604 | H8: =H7-H6 -> 2.1685438
B9: MTN79(8L+通孔+OSP) | C9: H-28W | D9: 0+0 | E9: 21.286257 | F9: =37.8775/7.04/1.13 -> 4.7613511 | G9: 3.5 | H9: =SUM(E9:G9) -> 29.547608 | I9: SMT预估 | J9: 9颗钽电容(15UF)，PD/赛普拉斯6228
B10: MTN793(10L+通孔+OSP) | C10: H-28W | D10: 0+0 | E10: =18.4933180946859 -> 18.493318 | F10: =37.8775/7.04/1.13 -> 4.7613511 | G10: 4 | H10: =SUM(E10:G10) -> 27.254669 | I10: SMT预估 | J10: PD/芯海035H，未加315转接小板
D11: 差异 | E11: =E10-E9 -> -2.7929391 | F11: =F10-F9 -> 0 | G11: =G10-G9 -> 0.5 | H11: =H10-H9 -> -2.2929391
E13: =0.7+1.25 -> 1.95

Sheet E BOM大核 (2)
B1: 汇率：6.75 | R1: pcb为普通材质OSP工艺，如用特殊材质请单独核;CPU;DDR;SSD;EMMC;WIFI请按需求选配 | T1: - | U1: 类型 | V1: 型号 | W1: 美金单项单价 | Y1: - | Z1: 类型 | AA1: 型号 | AB1: 美金单项单价
T2: - | U2: TYPC IC | V2: ANX7447QN | W2: 0.64 | Y2: - | Z2: 加密IC TPM | AA2: 9672 | AB2: 1.05
T3: - | V3: CYPD6228 | W3: 1.7769148 | Y3: - | Z3: 电量计 | AA3: CW2217 | AB3: 0.23
T4: - | V4: CYPD6227 | W4: 1.8079 | Y4: - | Z4: 雷电IC | AA4: 8040 | AB4: 2.948
T5: - | V5: ASL2330AN | W5: 0.52 | Y5: - | AA5: 9040 | AB5: 3.054
V6: IT8856FN/CX | W6: 0.93
A7: 厂区 | B7: 机型 | C7: PCB尺寸 | D7: 日期 | E7: 汇率 | F7: 料号 | G7: SKU | H7: Type c | I7: 功率 | J7: WIFI | K7: DDR 存储 | L7: WIFI | M7: PCB | N7: Others | O7: SMT | P7: TTL | Q7: 备注 | R7: 已含型号备注
A8: 1 | B8: ROBOT临时核价20260104 | D8: 20260104 | E8: 7.01 | F8: A.F.M.2401621-MP | J8: NA | K8: 选配 | L8: NA | M8: =[2]深圳英众PCB单价清单!$P$1014/E8/1.13 -> 3.7241362 | N8: 41.248623 | O8: 3.5 | P8: =SUM(K8:O8) -> 48.472759 | Q8: 条子 | R8: pcb按MTN25机型参考报价，SMT预估，后续正式bom再按实际核价为准,不含keypark报价
A9: 2 | B9: ROBOT临时核价20260105小板 | F9: A.F.M.2401623-MP | J9: NA | K9: NA | L9: NA | M9: 0.6 | N9: 0.48775694 | O9: 0.5 | P9: =SUM(K9:O9) -> 1.5877569 | Q9: 条子 | R9: pcb按xn25预估，smt预估
B10: DNN253 | E10: 6.78 | F10: A.F.M.2602447 | J10: - | K10: 现询 | L10: - | M10: =27.8/E10/1.13 -> 3.6285796 | N10: 14.1 | O10: =22/E10 -> 3.2448378 | P10: =SUM(K10:O10) -> 20.973417 | Q10: 条子 | R10: PCB持续上涨，实单前重新确认
B11: WN38(8L+通孔+OSP) | E11: 6.78 | F11: A.F.M.2400978 | H11: =H9-H10 -> 0 | J11: - | K11: 现询 | L11: - | M11: =58.17/E11/1.13*1.05 -> 7.9722375 | N11: =16.4*1.05 -> 17.22 | O11: =23/E11 -> 3.3923304 | P11: =SUM(K11:O11) -> 28.584568 | Q11: PCB价保一周
B12: WN38(8L+通孔+OSP) | E12: 6.78 | F12: A.F.M.2400991 | J12: - | K12: 现询 | L12: - | M12: =58.17/E12/1.13*1.05 -> 7.9722375 | N12: =16.4*1.05 -> 17.22 | O12: =23/E12 -> 3.3923304 | P12: =SUM(K12:O12) -> 28.584568 | Q12: PCB价保一周
B13: DN105(8L+通孔+OSP) | E13: 6.78 | F13: A.F.M.2501240 | J13: - | K13: 现询 | L13: - | M13: =62.5/E13/1.13 -> 8.157778 | N13: =13.95*1.05 -> 14.6475 | O13: =22/E13 -> 3.2448378 | P13: =SUM(K13:O13) -> 26.050116 | Q13: PCB价格有效期一周
B14: DN105(8L+通孔+OSP) | E14: 6.78 | F14: A.F.M.2501241 | J14: - | K14: 现询 | L14: - | M14: =62.5/E14/1.13 -> 8.157778 | N14: =15.4*1.05 -> 16.17 | O14: =22/E14 -> 3.2448378 | P14: =SUM(K14:O14) -> 27.572616 | Q14: PCB价格有效期一周
B15: DN87(8L++通孔+OSP) | C15: 258.0*128.0*1.0mm | D15: 46241 | E15: 6.78 | F15: A.F.M.2503104 | J15: - | K15: 现询 | L15: - | M15: =59.12/E15/1.13 -> 7.7166053 | N15: 14.2 | O15: 2.94 | P15: =SUM(K15:O15) -> 24.856605 | Q15: PCB有效期8-15 | R15: 12.866631 | S15: 条子 | T15: 电量计 ：CW2217; ROM:128Mb
B16: WS17(6L+通孔+OSP) | C16: 183.4*285.8*1.6 | E16: 6.75 | F16: A.F.M.2601815 | G16: SKU1 | J16: - | K16: 现询 | L16: - | M16: =340.5/E16/1.13 -> 44.641101 | N16: 55.6 | O16: =34/E16 -> 5.037037 | P16: =SUM(K16:O16) -> 105.27814 | Q16: PCB按快板厂价格,smt为批量预估价
B17: WS17(6L+通孔+OSP) | C17: 183.4*285.8*1.6 | E17: 6.75 | F17: A.F.M.2601816 | G17: SKU2 | J17: - | K17: 现询 | L17: - | M17: =340.5/E17/1.13 -> 44.641101 | N17: 54.9 | O17: =34/E17 -> 5.037037 | P17: =SUM(K17:O17) -> 104.57814 | Q17: PCB按快板厂价格,smt为批量预估价
B18: WS17(6L+通孔+OSP) | C18: 183.4*285.8*1.6 | E18: 6.75 | F18: A.F.M.2602249 | G18: SKU3 | J18: - | K18: 现询 | L18: - | M18: =340.5/E18/1.13 -> 44.641101 | N18: 54.8 | O18: =34/E18 -> 5.037037 | P18: =SUM(K18:O18) -> 104.47814 | Q18: PCB按快板厂价格,smt为批量预估价
B19: WS17(6L+通孔+OSP) | C19: 183.4*285.8*1.6 | E19: 6.72 | F19: A.F.M.2602505 | J19: - | K19: 现询 | L19: - | M19: =73.78/E19/1.13 -> 9.7160767 | N19: 57.7 | O19: =34/E19 -> 5.0595238 | P19: =SUM(K19:O19) -> 72.475601 | Q19: 65套PCB价格
B20: PS21(10L+通孔+OSP） | C20: 216.4*167.2*1.6mm | D20: 46275 | E20: 6.72 | F20: A.F.M.2602442 | J20: - | K20: 现询 | L20: - | M20: =352.5/E20/1.13 -> 46.42067 | N20: 77.1 | O20: =40/E20 -> 5.952381 | P20: =SUM(K20:O20) -> 129.47305 | Q20: LPDDR5X_8GB 315球*4 | R20: 不含屏蔽罩价格
B21: PS21(10L+通孔+OSP） | C21: 216.4*167.2*1.6mm | D21: 46275 | E21: 6.72 | F21: A.F.M.2602443 | J21: - | K21: 现询 | L21: - | M21: =352.5/E21/1.13 -> 46.42067 | N21: 77.7 | O21: =40/E21 -> 5.952381 | P21: =SUM(K21:O21) -> 130.07305 | Q21: LPDDR5X_8GB 315球*4 | R21: 不含屏蔽罩价格
B22: PS21(10L+通孔+OSP） | C22: 216.4*167.2*1.6mm | D22: 46275 | E22: 6.72 | F22: A.F.M.2602931 | J22: - | K22: 现询 | L22: - | M22: =352.5/E22/1.13 -> 46.42067 | N22: 77.7 | O22: =40/E22 -> 5.952381 | P22: =SUM(K22:O22) -> 130.07305 | Q22: LPDDR5X_16GB 315球*4 | R22: 不含屏蔽罩价格
B23: DN38 | E23: 6.78 | F23: A.F.M.2501241 | N23: =16.02*1.1 -> 17.622 | O23: =22/E23 -> 3.2448378
A24: 3 | B24: LP13（8L+HDI+沉金）预估LP13C | D24: 20251128 | E24: 7.01 | F24: A.F.M.2502474 | G24: SKU1 | H24: 双Type c(两个Type c接口)（LT7911D/CS32G053HRCW6NR） | I24: Ultra-5-226V(16GB) | J24: AX211.D2WG | K24: 选配 | L24: 7.5 | M24: =68.912/E220/1.13 -> 8.5054492 | N24: =29.9075200457023+2.5 -> 32.40752 | O24: 4 | P24: =SUM(L24:O24) -> 52.412969 | Q24: 条子 | R24: 此项目为预估报价，PCB直接参考LP13,Others部分建议参考A.F.M.2502474（LP13-SKU1、WIFI 6 WIFI AX211）+加一颗G2708C 芯片
A25: 1 | B25: LP13C（8L+HDI+OSP） | D25: 46126 | E25: 6.837 | F25: A.F.M.2600129 | L25: 7.5 | M25: =68.91/E25/1.3 -> 7.7530631 | N25: 30.1 | O25: 4 | P25: =SUBTOTAL(109,L25:O25) -> 49.353063
B26: PN50(8L+通孔+OSP) | D26: 20251229 | E26: 7.01 | F26: A.F.M.2600118 | H26: 单Type c(两个Type c接口)IT5272FN | I26: H-25W | J26: 选配 | K26: 选配 | L26: 选配 | N26: 28.2 | O26: 0.3 | P26: =SUM(M26:O26) -> 28.5 | Q26: 报价不含EPTAD-A5R，CKD
A27: 4 | B27: PN50(8L+通孔+OSP) | D27: 20251229 | E27: 7.01 | F27: / | H27: 单Type c(两个Type c接口)IT5272FN | I27: H-25W | J27: 选配 | K27: 选配 | L27: 选配 | M27: =60.16/E27/1.13 -> 7.594713 | N27: 29.581934 | O27: 4 | P27: =SUM(M27:O27) -> 41.176647 | Q27: 条子 | R27: 全功能(IT5272FN)；含加密IC TPM,含UDP;pcb按样品单价核算
A28: 6 | B28: WN25(6L+通孔+OSP) | C28: 187.0*99.2*1.0mm | D28: 46087 | E28: 6.8226 | F28: A.F.M.2600389 | G28: SKU3 | H28: 单Type c(两个Type c接口)IT5272FN | I28: 25W | J28: BE211.D2WG.NVQ | K28: 现询 | L28: 11.5 | M28: =17.24/E28/1.13 -> 2.2361911 | N28: =14.4+0.57 -> 14.97 | O28: =20.5/E28 -> 3.0047196 | P28: =SUM(L28:O28) -> 31.710911 | Q28: 0+512 UFS | R28: HDMI2.0,ROM:256Mb,含496球DDR转接小板,
A29: 1 | C29: 187.0*99.2*1.0mm | D29: 46136 | E29: 6.8225 | F29: A.F.M.2600388 | G29: SKU2 | H29: 单Type c(两个Type c接口)IT5272FN | I29: 25W | J29: WD_RTL8821CE_V20(MS) | K29: 现询 | L29: =12.9/E29/1.13 -> 1.6732765 | M29: =17.24/E29/1.13 -> 2.2362238 | N29: =15.3+0.57 -> 15.87 | O29: =20.5/E29 -> 3.0047636 | P29: =SUM(L29:O29) -> 22.784264 | Q29: 496球（小板）+512 UFS | R29: HDMI2.0,TPM,ROM 256Mb,含496球DDR转接小板
A30: 1 | C30: 187.0*99.2*1.0mm | D30: 46163 | E30: 6.8 | F30: A.F.M.2601423 | J30: - | K30: 现询 | L30: - | M30: =32.32/E30/1.13 -> 4.2061426 | N30: 15.2 | O30: =20.5/E30 -> 3.0147059 | P30: =SUM(L30:O30) -> 22.420849
A31: 1 | C31: 187.0*99.2*1.0mm | D31: 46175 | E31: 6.8 | F31: A.F.M.2601434 | M31: =26.51/E31/1.13 -> 3.450026 | N31: 16.4 | O31: =20.5/E31 -> 3.0147059 | P31: =SUM(L31:O31) -> 22.864732 | R31: PCB无卤
A32: 1 | C32: 187.0*99.2*1.0mm | D32: 46134 | E32: 6.8225 | F32: A.F.M.2600780 | G32: SKU5 | H32: 单Type c(两个Type c接口)IT5272FN | I32: 25W | J32: CDW-61851BE-00 | K32: 现询 | L32: =17.46/E32/1.13 -> 2.2647603 | M32: =17.24/E32/1.13 -> 2.2362238 | N32: 13.5 | O32: =20.1/E32 -> 2.9461341 | P32: =SUM(L32:O32) -> 20.947118 | Q32: 条子
A33: 1 | C33: 187.0*99.2*1.0mm | D33: 46135 | E33: 6.8225 | F33: A.F.M.2600839 | G33: SKU10 | H33: 单Type c(两个Type c接口)IT5272FN | J33: CDW-61852BE-00 | K33: 现询 | L33: =25.72/E33/1.13 -> 3.3361762 | M33: =18.89/E33/1.13 -> 2.4502476 | N33: =14.4+0.57 -> 14.97 | O33: =20.5/E33 -> 3.0047636 | P33: =SUM(L33:O33) -> 23.761187 | Q33: 条子 | R33: HDMI2.0.无卤PCB,含496转接小板
A34: 1 | C34: 187.0*99.2*1.0mm | D34: 46135 | E34: 6.8225 | F34: A.F.M.2600853 | G34: SKU11 | H34: 单Type c(两个Type c接口)IT5272FN | J34: - | K34: 现询 | L34: - | M34: =23.2/E34/1.13*1.2 -> 3.6111643 | N34: 16.8 | O34: =20.1/E34+0.1 -> 3.0461341 | P34: =SUM(L34:O34) -> 23.457298 | Q34: 条子 | R34: HDMI2.0,含496转接小板，HFPCB
A35: 7 | C35: 187.0*99.2*1.0mm | D35: 46101 | E35: 6.8225 | F35: A.F.M.2600390 | G35: SKU4 | H35: 单Type c(两个Type c接口)IT5272FN | I35: 25W | J35: AX211.D2WG | K35: 现询 | L35: 7.5 | M35: =17.24/E35/1.13 -> 2.2362238 | N35: 14.1 | O35: =20.1/E35 -> 2.9461341 | P35: =SUM(L35:O35) -> 26.782358 | Q35: LPDDR5-315球8G*2+256 UFS | R35: HDMI2.0,ROM:256Mb
A36: 1 | C36: 187.0*99.2*1.0mm | D36: 20251224 | E36: 6.8225 | F36: A.F.M.2503155 | G36: SKU1 | H36: 单Type C IC及两个Type C 接口（IT5272FN） | I36: 15w | J36: AX211.D2WG | K36: 现询 | L36: 7.5 | M36: =17.24/E36/1.13 -> 2.2362238 | N36: 14.7 | O36: =20.1/E36 -> 2.9461341 | P36: =SUM(M36:O36) -> 19.882358 | Q36: LPDDR5-315球8G*2+0 | R36: HDMI2.0/TPM/ROM 256Mb
A37: 1 | B37: RPLK3（6L+通孔+OSP) | C37: 184x170x1.6mm | D37: 46128 | E37: 6.7739 | F37: A.F.M.2600743 | J37: - | K37: 现询 | L37: - | M37: =41.68/E37/1.13 -> 5.445158 | N37: 18 | O37: =32/E37 -> 4.7240142 | P37: =SUBTOTAL(109,M37:O37) -> 28.169172
A38: 1 | B38: RPLK3（6L+通孔+OSP) | C38: 184x170x1.6mm | D38: 46128 | E38: 6.7739 | F38: A.F.M.2600589 | J38: - | K38: 现询 | L38: - | M38: =32.35/E38/1.13 -> 4.2262683 | N38: 15.8 | O38: =32/E38 -> 4.7240142 | P38: =SUBTOTAL(109,M38:O38) -> 24.750282
A39: 1 | B39: RPLK3（6L+通孔+OSP) | C39: 184x170x1.6mm | D39: 46128 | E39: 6.7739 | F39: A.F.M.2600590 | J39: - | K39: 现询 | L39: - | M39: =32.35/E39/1.13 -> 4.2262683 | N39: 15.8 | O39: =32/E39 -> 4.7240142 | P39: =SUBTOTAL(109,M39:O39) -> 24.750282
A40: 1 | B40: RPLK3（6L+通孔+OSP) | C40: 184x170x1.6mm | D40: 46153 | E40: 6.7986 | F40: A.F.M.2601222 | M40: =32.35/E40/1.13 -> 4.2109138 | N40: 15.6
A41: 1 | B41: RPLK3（6L+通孔+OSP) | C41: 184x170x1.6mm | D41: 46153 | E41: 6.7986 | F41: A.F.M.2601256 | M41: =32.35/E41/1.13 -> 4.2109138 | N41: 13.8
A42: 1 | B42: RPLK3（6L+通孔+OSP) | C42: 184x170x1.6mm | D42: 46153 | E42: 6.7986 | F42: A.F.M.2601257 | M42: =32.35/E42/1.13 -> 4.2109138 | N42: 14.5
A43: 9 | B43: RPLK3（6L+通孔+OSP) | C43: 184x170x1.6mm | D43: 46049 | E43: 6.8819 | F43: A.F.M.2503286 | G43: SKU1 | H43: 无TYPE C | I43: H-45W | J43: 选配 | K43: 现询 | L43: 选配 | M43: =32.35/E43/1.13 -> 4.159944 | N43: 16.8 | O43: =32/E43 -> 4.6498787 | P43: =SUM(M43:O43) -> 25.609823 | Q43: 条子 | R43: 芯海CSCS2010RBR6NR，瑞昱RTL8111H-CG,SMT为预估计
A44: 10 | B44: RPLK3（6L+通孔+OSP) | C44: 184x170x1.6mm | D44: 46126 | E44: 6.837 | F44: A.F.M.2503287/A.F.M.2600589/A.F.M.2600590 | G44: SKU2 | H44: 台式机 | I44: H-45W | J44: 选配 | K44: 现询 | L44: 现询 | M44: =32.35/E44/1.13 -> 4.1872632 | N44: 14.58 | O44: =32/E44 -> 4.6804154 | P44: =SUM(M44:O44) -> 23.447679 | Q44: 条子 | R44: 芯海CSCS2010RBR6NR，瑞昱RTL8111H-CG,SMT为预估计
A45: 1 | B45: RPLM3S4(6L+通孔+OSP) | C45: 239.2x195x1.6mm | D45: 46132 | E45: 6.76 | F45: 高配 | G45: 高配 | H45: - | I45: 65W | J45: - | K45: 现询 | L45: - | M45: =56.5/E45/1.13 -> 7.3964497 | N45: 19.93 | O45: =32/E45 -> 4.7337278 | P45: =SUM(K45:O45) -> 32.060178 | Q45: 条子 | R45: HDMI2.0:LT86101UXS; 网卡IC:RTL8125D; 报价有效期6月30日
A46: 1 | C46: 239.2x195x1.6mm | D46: 46189 | E46: 6.76 | F46: A.F.M.2600886 | H46: - | I46: 65W | K46: 现询 | M46: =56.5/E46/1.13 -> 7.3964497 | N46: 19.9 | O46: =32/E46 -> 4.7337278 | P46: =SUM(K46:O46) -> 32.030178 | R46: HDMI2.0:LT86101UXS; 网卡IC:RTL8125D; ROM:128Mb; 报价有效期6月30日 | S46: 电源方案：RT3624BEGQW； DRMOS: SPT5516*6; AUDIO:ALC897
A47: 1 | C47: 239.2x195x1.6mm | D47: 46135 | E47: 6.8 | F47: A.F.M.2600884 | G47: SKU1 | H47: - | I47: 65W | J47: - | K47: 现询 | L47: - | N47: 17.4 | O47: =30/E45 -> 4.4378698 | P47: =SUM(M47:O47) -> 21.83787 | Q47: 条子
A48: 1 | C48: 239.2x195x1.6mm | D48: 46132 | E48: 6.76 | F48: A.F.M.2600885 | G48: SKU2 | H48: - | I48: 65W | J48: - | K48: 现询 | L48: - | M48: =56.5/E48/1.13 -> 7.3964497 | N48: 17.5 | O48: =30/E48 -> 4.4378698 | P48: =SUM(M48:O48) -> 29.33432 | Q48: 条子
A49: 11 | B49: LN89C(预估) | D49: 20250928 | E49: 7.07 | F49: A.F.M.2401762 | G49: SKU13-8L | H49: 单Type c IC及两个接口（CS32G053HRCW6NR） | I49: 30W | J49: 选配 | K49: 选配 | L49: 选配 | M49: =42.7/E49/1.13 -> 5.3447823 | N49: 20.173442 | O49: / | P49: 20.173442 | Q49: 条子 | R49: 全功能（CS32G053HRCW6NR），含TPM;适用于IPS
A50: 1 | B50: PTLT19(定制) | C50: 180.1*170.0*1.6mm | D50: 46170 | E50: 6.7963 | F50: A.F.M.2600920 | G50: SKU4 | H50: 单TYPE C IC+双TYPE-C连接器 | I50: 25W | J50: - | K50: 现询 | L50: - | M50: =49.93/E50/1.13 -> 6.5014553 | N50: 70.8 | O50: =40/E50 -> 5.8855554 | P50: =SUBTOTAL(109,M50:O50) -> 83.187011 | R50: 雷电：JHL9040R*2 ；HDMI2.0: IT66318FN; 万兆网卡：RTL8127AT*2；ROM:256Mb ; PCIE-SATA; | S50: 电源方案：MP29011； Drmos:MP86941*5; codec:ALC897; EC:CSCE2010WBR6NR;
A51: 12 | B51: PTLT19(定制) | C51: 180.1*170.0*1.6mm | D51: 46093 | E51: 6.9264 | F51: A.F.M.2502641 | G51: SKU2 | H51: 单Type C IC及两个Type C 接口（IT5272FN） | I51: U-25W | J51: - | K51: 现询 | L51: - | M51: =49.93/6.8/1.13*1.1 -> 7.1477095 | N51: 75 | O51: =40/E51 -> 5.7750058 | P51: =SUM(K51:O51) -> 87.922715 | Q51: 条子 | R51: 全功能（IT5272FN）；含加密IC TPM；含CW2217 PM反馈这是最全的SKU
A52: 13 | B52: ROBOT临时核价 1124 | D52: 20251124 | E52: 7.1 | F52: / | J52: NA | K52: 选配 | L52: NA | M52: =[2]深圳英众PCB单价清单!$P$1014/E52/1.13 -> 3.6769288 | N52: 17.403377 | O52: 3.5 | P52: =SUM(K52:O52) -> 24.580306 | Q52: 条子 | R52: pcb按MTN25机型参考报价，SMT预估，后续正式bom再按实际核价为准,不含keypark报价
A53: 14 | B53: ROBOT临时核价 1128 | D53: 20251128 | E53: 7.1 | F53: / | J53: NA | K53: 选配 | L53: NA | M53: =[2]深圳英众PCB单价清单!$P$1014/E53/1.13 -> 3.6769288 | N53: 19.273622 | O53: 3.5 | P53: =SUM(K53:O53) -> 26.450551 | Q53: 条子 | R53: pcb按MTN25机型参考报价，SMT预估，后续正式bom再按实际核价为准,不含keypark报价
A54: 15 | B54: DNP67 | D54: 20251110 | E54: 6.901 | F54: / | G54: SKU1 | H54: 双Tpye c IC及两个Type c接口（ANX7447QN） | I54: N-6W | J54: AX101.D2WG | K54: 按实际 | L54: 3.1 | M54: 2.6883789 | N54: 14.668771 | O54: =20.1/E54 -> 2.9126214 | P54: =SUM(K54:O54) -> 23.369771 | Q54: LPDDR5x-315球4G
A55: 16 | B55: DNP67 | D55: 46043 | E55: 6.9667 | F55: A.F.M.2502013 | G55: SKU1 | H55: 双Tpye c IC及两个Type c接口（ANX7447QN） | I55: N-6W | J55: AX101.D2WG | K55: 选配 | L55: 3.1 | M55: 2.76 | N55: 15.5 | O55: =4*1.01 -> 4.04 | P55: =SUM(K55:O55) -> 25.4 | Q55: LPDDR5x-315球4G | R55: TYPE-C:ANX7447QN-AC-R,电量计:CW2217
A56: 17 | B56: DNP67 | D56: 46099 | E56: 6.901 | F56: A.F.M.2600245 | G56: SKU3 | H56: 双Tpye c IC及两个Type c接口（ANX7447QN） | J56: AX101.D2WG.NV | K56: 选配 | L56: 3.1 | M56: =24.24*1.1/6.901/1.13 -> 3.4192813 | N56: 16 | O56: =20.1/E56 -> 2.9126214 | P56: =SUM(K56:O56) -> 25.431903 | Q56: LPDDR5x-315球4G*2 | R56: TYPE-C:ANX7447QN-AC-R,电量计:CW2217,视频桥接：IT6113FN
A57: 1 | B57: PN99(10L+通孔+OSP) | D57: 46150 | E57: 6.8215 | F57: A.F.M.2502463 | M57: =24.85/E57/1.13 -> 3.2237998 | N57: 22 | O57: =23/E57 -> 3.3716924 | P57: =SUM(K57:O57) -> 28.595492 | R57: 70W
A58: 1 | B58: PN99(10L+通孔+OSP) | D58: 46150 | E58: 6.8215 | F58: A.F.M.2502465 | M58: =24.85/E58/1.13 -> 3.2237998 | N58: 22.8 | O58: =23/E58 -> 3.3716924 | P58: =SUM(K58:O58) -> 29.395492 | R58: OLED
A59: 19 | B59: PN99(10L+通孔+OSP) | D59: 20250918 | E59: 6.8802 | F59: A.F.M.2501978 | G59: SKU3 | H59: 单Type c(一个Type c接口)（IT5272FN） | I59: H-45W | J59: 选配 | K59: 现询 | L59: 选配 | M59: =43.6/E59/1.13 -> 5.6079868 | N59: 24.506763 | O59: =23/E59 -> 3.3429261 | P59: =SUM(K59:O59) -> 33.457676 | Q59: LPDDR5X-315球8G*4 | R59: 全功能（IT5272FN）；含加密IC TPM；含CW2217;含雷电IC9040*1;
A60: 20 | B60: PN99(10L+通孔+OSP) | D60: 46085 | E60: 6.8802 | F60: A.F.M.2502464 | G60: SKU6 | H60: 单个Type c(两个Type c接口)（IT5272FN） | I60: 25W | J60: 选配 | K60: 现询 | L60: 选配 | M60: =43.6/E60/1.13 -> 5.6079868 | N60: 20.33 | O60: =23/E60 -> 3.3429261 | P60: =SUM(K60:O60) -> 29.280913 | Q60: LPDDR5X-315球4G*4 | R60: 全功能（TYPE-C:IT5272FN, TPM；SLB 9672 含雷电IC9040*1,无电量计
A61: 21 | B61: PN99(10L+通孔+OSP) | D61: 46085 | E61: 6.8802 | F61: A.F.M.2502464 | G61: SKU6 | H61: 单个Type c(两个Type c接口)（IT5272FN） | I61: 25W | J61: 选配 | K61: 现询 | L61: 选配 | M61: =43.6/E61/1.13 -> 5.6079868 | N61: 20.33 | O61: =23/E61 -> 3.3429261 | P61: =SUM(K61:O61) -> 29.280913 | Q61: LPDDR5X-315球4G*4 | R61: 全功能（TYPE-C:IT5272FN, TPM；SLB 9672 含雷电IC9040*1,无电量计
A62: 22 | B62: APS16主板2盘位 | F62: / | I62: 临时bom预估报价 | J62: 选配 | K62: 选配 | L62: 选配 | M62: =28.5/7.13/1.13 -> 3.5373407 | N62: 33.719503 | O62: 4.5 | P62: =SUM(K62:O62) -> 41.756843 | Q62: 0+64 | R62: 含RTL8127AT，pcb无资料，按备注要求预估'MB 尺寸223.75*96.3/板厚1.6/无卤/八层通孔
A63: 27 | B63: SSD DB | D63: 46034 | E63: 6.9783 | F63: A.F.D.2500492 | G63: EVT | H63: / | J63: / | K63: / | L63: / | M63: =9.3/E63/1.13 -> 1.179383 | N63: 0.5 | O63: / | P63: =SUM(M63:N63) -> 1.679383 | Q63: / | R63: 沉金板贵,SMT待BOM成型再核
A64: 28 | B64: SATA DB | D64: 46034 | E64: 6.9783 | F64: A.F.D.2500491 | G64: EVT | H64: HDD CON*2， 谱瑞PS8527CTQFN20GTR2*2 | J64: / | K64: / | L64: / | M64: =10.57/E64/1.13 -> 1.3404385 | N64: 3.3 | O64: / | P64: =SUM(M64:N64) -> 4.6404385 | Q64: / | R64: 沉金板贵,SMT待BOM成型再核
A65: 29 | B65: TN29 | D65: 46057 | E65: 6.9514 | F65: A.P.0TN29018 | G65: SKU18 | J65: / | K65: / | L65: / | M65: =36/E65/1.14 -> 4.5428183 | N65: 13.02 | O65: =22/6.9514 -> 3.1648301 | P65: =SUM(M65:N65) -> 17.562818 | Q65: 条子
A66: 31 | B66: HDD-DB | F66: / | I66: DNS13/ A.F.D.2500175参考报价 | J66: 选配 | K66: 选配 | L66: 选配 | M66: =7.5/7.13/1.13 -> 0.93087912 | N66: 3.4092776 | O66: 0.3 | P66: =SUM(K66:O66) -> 4.6401567 | Q66: 0+64 | R66: pcb无资料，按备注要求预估'HDD DB尺寸：91.18*86.01/板厚1.6/无卤/四层通孔
A67: 32 | B67: APS16主板4盘位 | F67: / | I67: 临时bom预估报价 | J67: 选配 | K67: 选配 | L67: 选配 | M67: =49/7.13/1.13 -> 6.0817436 | N67: 48.067369 | O67: 4.5 | P67: =SUM(K67:O67) -> 58.649112 | Q67: 0+64 | R67: 含RTL8127AT，pcb无资料，按备注要求预估'MB尺寸:249.3*150/板厚1.6/无卤/八层通孔
A68: 33 | B68: HDD-DB | F68: / | I68: DNS9/A.F.D.2500026参考报价 | J68: 选配 | K68: 选配 | L68: 选配 | M68: =11.3/7.13/1.13 -> 1.4025245 | N68: 8.7426948 | O68: 0.6 | P68: =SUM(K68:O68) -> 10.745219 | Q68: 0+64 | R68: /JMB585，pcb无资料，按备注要求预估'HDD DB尺寸：137*86.75/板厚1.6/无卤/四层通孔
A69: 34 | B69: DN59(8L+通孔+OSP) | D69: 20251110 | E69: 7.13 | F69: A.F.M.2400959-MP | G69: SKU28 | I69: I5-1235U(不带IPU)(15W) | J69: 选配 | K69: 选配 | L69: 选配 | M69: =43.37/7.13/1.13 -> 5.3829637 | N69: 20.203259 | O69: =24.78/7.13/1.13 -> 3.0756246 | P69: 128.50201 | Q69: 条子 | R69: 单Type c；含英特尔雷电IC;
A70: 35 | B70: LN89（8L+HDI2+OSP） | D70: 20250928 | E70: 7.13 | F70: A.F.M.2401580-PVT | G70: SKU14-8L | H70: 单Type c IC及两个接口（CYPD6228） | I70: 30W | J70: 选配 | K70: 选配 | L70: 选配 | M70: =43.88/7.13/1.13*1.03 -> 5.6096514 | N70: 24.926766 | O70: 3.5 | P70: 33.30209 | Q70: 条子 | R70: 全功能（CYPD6228），含TPM;CW2217；适用于OLED,预估pcb 无卤单价，后续有订单按实际为准
A71: 36 | B71: LN25C(8L+通孔+OSP) | D71: 20250918 | E71: 7.13 | F71: A.F.M.2500394 | G71: SKU6 | H71: 单Type-C IC及两个typeC接口（CS32G053H） | I71: H-28W | J71: AX211.D2WG | K71: 选配 | L71: 7.5 | M71: =38.55/E71/1.13 -> 4.7847187 | N71: 22.878676 | O71: =23.5/6.91 -> 3.4008683 | P71: =SUM(K71:O71) -> 38.564263 | R71: 全功能（CS32G053H）；含加密IC TPM；含CW2217，PCB为无卤板材预估价格
A72: 37 | D72: 46090 | E72: 6.91 | F72: A.F.M.2600075 | G72: SKU25 | H72: 单Type-C IC及两个typeC接口（CS32G053H） | I72: 226V-17W | J72: AX211.D2WG | K72: 现询 | L72: 7.5 | M72: =38.55/E72/1.13 -> 4.9370542 | N72: 19.3 | O72: =23.5/6.91 -> 3.4008683 | P72: =SUM(L72:O72) -> 35.137922 | Q72: 条子 | R72: CS32G053H）；含CW2217
D73: 46286 | E73: 6.7 | F73: A.F.M.2603041 | G73: SKU43 | J73: - | K73: 现询 | L73: - | M73: =59.85/E73/1.13 -> 7.9051644 | N73: 21.1 | O73: =23.5/6.91 -> 3.4008683 | P73: =SUM(L73:O73) -> 32.406033 | Q73: LINYA 216PCS
E74: 6.75 | F74: A.F.M.2601780 | J74: - | K74: 现询 | L74: - | M74: =60/E74/1.13 -> 7.8662734 | N74: 23.7 | O74: =23.5/6.91 -> 3.4008683 | P74: =SUBTOTAL(109,M74:O74) -> 34.967142 | R74: 四会有卤PCB，暂无板料
D75: 46272 | E75: 6.72 | F75: A.F.M.2503211/A.F.M.2503298 | J75: - | K75: 现询 | L75: - | M75: =65.32/E75/1.13 -> 8.6019806 | N75: 21.9 | O75: =23.5/6.91 -> 3.4008683 | P75: =SUBTOTAL(109,M75:O75) -> 33.902849 | R75: PCB有效期一周
E76: 6.72 | F76: A.F.M.2601530 | J76: - | K76: 现询 | L76: - | M76: =65.32/E76/1.13 -> 8.6019806 | N76: 22.3 | O76: =23.5/6.91 -> 3.4008683 | P76: =SUBTOTAL(109,M76:O76) -> 34.302849
E77: 6.72 | F77: A.F.M.2602796 | J77: - | K77: 现询 | L77: - | M77: =65.32/E77/1.13 -> 8.6019806 | N77: 23.52 | O77: =23.5/6.91 -> 3.4008683 | P77: =SUBTOTAL(109,M77:O77) -> 35.522849
A78: 1 | E78: 6.7963 | F78: A.F.M.2600134 | G78: SKU28 | J78: AX211.D2WG.NV | K78: 现询 | M78: =38.55/E78/1.13 -> 5.0196496 | N78: 21 | O78: =23.5/6.91 -> 3.4008683 | P78: =SUBTOTAL(109,L78:O78) -> 29.420518
A79: 1 | E79: 6.7739 | F79: A.F.M.2601529 | G79: SKU37 | J79: - | K79: 现询 | L79: - | M79: =52.17/6.7739/1.13 -> 6.8155924 | N79: =21.2+20/6.7739/1.13 -> 23.81284 | O79: =23.5/E79 -> 3.469198 | P79: =SUM(L79:O79) -> 34.09763
A80: 38 | D80: 46107 | E80: 6.91 | F80: A.F.M.2600133 | G80: SKU27 | H80: 单Type-C IC及两个typeC接口（CS32G053H） | J80: AX211.D2WG. | K80: 现询 | L80: 7.5 | M80: =38.55/E80/1.13 -> 4.9370542 | N80: 20.9 | O80: =23.5/6.91 -> 3.4008683 | P80: =SUM(L80:O80) -> 36.737922 | Q80: 条子
A81: 1 | D81: 46122 | E81: 6.8819 | F81: A.F.M.2600318 | G81: SKU29 | H81: 单Type-C IC及两个typeC接口（CS32G053H） | J81: AX211.D2WG. | K81: 现询 | L81: 7.5 | M81: =38.55/E81/1.13 -> 4.957213 | N81: 21.2 | O81: 3.4 | P81: =SUM(L81:O81) -> 37.057213
A82: 1 | D82: 46182 | E82: 6.7851 | F82: A.F.M.2601227 | M82: =38.07/E82/1.13 -> 4.9653307 | N82: 22.1 | O82: 3.4 | P82: =SUM(L82:O82) -> 30.465331 | Q82: 含PCB 100套工程费4000
A83: 39 | D83: 46106 | E83: 6.91 | F83: A.F.M.2600076 | G83: SKU26 | H83: 单Type-C IC及两个typeC接口（CS32G053H） | J83: AX211.D2WG | K83: 现询 | L83: 7.5 | M83: =38.55/E83/1.13 -> 4.9370542 | N83: =18.65+0.86 -> 19.51 | O83: =23.5/6.91 -> 3.4008683 | P83: =SUM(L83:O83) -> 35.347922 | Q83: 条子 | R83: CS32G053H）；含CW2217
A84: 40 | B84: WN792 | D84: 20251104 | E84: 7.13 | F84: / | J84: 选配 | K84: 选配 | L84: 选配 | M84: =21.7/E84/1.13 -> 2.6933436 | N84: =11.62+0.72 -> 12.34 | O84: 3.5 | P84: =SUM(K84:O84) -> 18.533344 | R84: Others按WNTU146预估，pcb按mtn792预估，SMT为预估，实际待正式bom出后再估算,CPU/WIF/UFS/PCB新机型暂未核价，待确认后重新安排核价
A85: 41 | B85: WN792 | D85: 20251104 | E85: 7.13 | F85: / | I85: 临时bom估价1104/15w核价 | J85: 选配 | K85: 选配 | L85: UFS | M85: =21.7/E85/1.13 -> 2.6933436 | N85: =11.62+0.72 -> 12.34 | O85: 3.5 | P85: =SUM(K85:O85) -> 18.533344 | R85: Others按WNTU146预估，pcb按mtn792预估，SMT为预估，实际待正式bom出后再估算,CPU/WIF/UFS/PCB新机型暂未核价，待确认后重新安排核价
A86: 42 | B86: WN792 | D86: 46056 | E86: 6.9514 | F86: A.F.M.2600136 | G86: SKU1 | H86: 单Type c IC及两个接口 | J86: 选配 | K86: 选配 | L86: UFS | M86: =21.7/E86/1.13 -> 2.7625428 | N86: =16.78+0.72 -> 17.5 | O86: =22/E86 -> 3.1648301 | P86: =SUM(K86:O86) -> 23.427373 | R86: TYPE-C:联阳IT5272FN;TPM:SLB 9672;PCB 1.2KPCS以上可按2.71U，SMT为预估价
A87: 43 | B87: WN792(6L+通孔+OSP) | D87: 46101 | E87: 6.902 | F87: A.F.M.2600137 | G87: SKU2 | H87: 单Type c(两个Type c接口)IT5272FN | I87: 25W | J87: 选配 | K87: 现询 | L87: 选配 | M87: =21.7/6.91/1.13 -> 2.779094 | N87: =13.32+0.72 -> 14.04 | O87: =22/E87 -> 3.1874819 | P87: =SUM(K87:O87) -> 20.006576 | Q87: 0+512UFS | R87: 电量计：BQ24780SRUYR
B88: WN21B | D88: 46251 | E88: 6.75 | F88: A.F.M.2600756 | J88: 选配 | K88: 现询 | L88: 选配 | M88: =38.98/E88/1.13 -> 5.1104556 | N88: 17.1 | O88: =22/E88 -> 3.2592593 | P88: =SUM(K88:O88) -> 25.469715
A89: 44 | B89: WN21B | D89: 46058 | E89: 6.9514 | F89: A.F.M.2501978 | G89: SKU1 | H89: 单Type c IC及两个接口 | J89: 选配 | K89: 现询 | L89: 选配 | M89: =24.33/E89/1.13 -> 3.0973579 | N89: 15.01 | O89: =22/E89 -> 3.1648301 | P89: =SUM(K89:O89) -> 21.272188 | R89: TYPE-C:联阳IT5272FN，TPM：9672,PCB 1.2KPCS以上可按2.71U核价，SMT为预估价
A90: 45 | B90: WN21B(6L+通孔+OSP) | D90: 46101 | E90: 6.901 | F90: A.F.M.2600507 | G90: SKU2 | H90: 单Type c IC及两个接口 | I90: 25W | J90: 选配 | K90: 现询 | L90: 选配 | M90: =24.33/E90/1.13 -> 3.1199788 | N90: =13.99+0.72 -> 14.71 | O90: =22/E90 -> 3.1879438 | P90: =SUM(K90:O90) -> 21.017923 | Q90: LPDDR5-8GB 315球+512 UFS | R90: TPM：9672,电量计CW2217
A91: 46 | B91: WNTU146 | D91: 46081 | E91: 6.9264 | F91: A.F.M.2502465 | I91: 临时bom估价1027 | J91: 选配 | K91: 现询 | L91: UFS | M91: 暂无待定 | N91: 21.9 | O91: 3.5 | P91: =N91+O91 -> 25.4 | R91: 全功能(IT5272FN)；含CW2217;其中flash为估价，后面按实际验证为准。CPU/WIF/UFS/PCB新机型暂未核价，待确认后重新安排核价
A92: 47 | B92: DN21C(8L+通孔+OSP) | D92: 20240919 | E92: 7.13 | F92: A.F.M.2401621-MP | G92: SKU135 | H92: 单Tpye c IC及两个Type c接口（ANX7447QN） | I92: U-15W | J92: 选配 | K92: 现询 | L92: 选配 | M92: =3.85264748791615/7.21*7.17 -> 3.8312736 | N92: =15.2241732953349+0.23 -> 15.454173 | O92: =23.73/E113/1.13 -> 3.0522369 | P92: =SUM(K92:O92) -> 22.337684 | Q92: 条子/SSD PCIE3.0 | R92: 全功能（ANX7447QN）；含有加密IC TPM(9672)；含CW2217
A93: 48 | D93: 46056 | E93: 6.9514 | F93: A.F.M.2401484 | G93: SKU132 | H93: 单Tpye c IC及两个Type c接口（ANX7447QN） | I93: H-28W | J93: 选配 | K93: 现询 | L93: 选配 | M93: =3.85264748791615/7.21*7.17 -> 3.8312736 | N93: 13.5 | O93: 3.09 | P93: =SUM(K93:O93) -> 20.421274 | Q93: 条子/SSD PCIE3.0,TYPC-C 7447,电量计BQ24780SRUYR
A94: 1 | D94: 46176 | E94: 6.75 | F94: A.F.M.2500762 | J94: - | K94: 现询 | L94: - | M94: =38.264/E94/1.13*1.05 -> 5.267414 | N94: 12.5 | O94: 3.09 | P94: =SUBTOTAL(109,M94:O94) -> 20.857414 | Q94: 报价有效期8-21日内
E95: 6.7 | F95: A.F.M.2500665 | J95: - | K95: 现询 | L95: - | M95: =54.21/E95/1.13 -> 7.1602166 | N95: 14.6 | O95: 3.09 | P95: =O95+N95+M95 -> 24.850217
D96: 46246 | E96: 6.75 | F96: A.F.M.2401268 | J96: - | K96: 现询 | L96: - | M96: =38.264/E96/1.13*1.05 -> 5.267414 | N96: 14.92 | O96: 3.09 | P96: =SUBTOTAL(109,M96:O96) -> 23.277414 | Q96: PCB有效期8-21日内
F97: A.F.M.2600731 | J97: 选配 | K97: 现询 | L97: 选配 | M97: =34.78*1.4/6.78/1.13 -> 6.3554964 | N97: 15.5 | O97: 3.09 | P97: =SUM(K97:O97) -> 24.945496
E98: 6.75 | F98: A.F.M.2503181 | J98: - | K98: 现询 | L98: - | M98: =38.264/E98/1.13*1.05 -> 5.267414 | N98: 15 | O98: 3.09 | P98: =SUM(K98:O98) -> 23.357414
E99: 6.7 | F99: A.F.M.2502587 | J99: - | K99: 现询 | L99: - | M99: =45.18/E99/1.13 -> 5.9675076 | N99: 15.9 | O99: 3.09 | P99: =SUM(K99:O99) -> 24.957508
D100: 46288 | E100: 6.7 | F100: A.F.M.2401481 | J100: - | K100: 现询 | L100: - | M100: =45.18/E99/1.13*1.05 -> 6.265883 | N100: 15.1 | O100: 3.09 | P100: =SUM(K100:O100) -> 24.455883
...

Sheet E BOM大核 (3)
B1: 汇率：6.75 | S1: pcb为普通材质OSP工艺，如用特殊材质请单独核;CPU;DDR;SSD;EMMC;WIFI请按需求选配 | U1: - | V1: 类型 | W1: 型号 | X1: 美金单项单价 | Z1: - | AA1: 类型 | AB1: 型号 | AC1: 美金单项单价
U2: - | V2: TYPC IC | W2: ANX7447QN | X2: 0.64 | Z2: - | AA2: 加密IC TPM | AB2: 9672 | AC2: 1.05
U3: - | W3: CYPD6228 | X3: 1.7769148 | Z3: - | AA3: 电量计 | AB3: CW2217 | AC3: 0.23
U4: - | W4: CYPD6227 | X4: 1.8079 | Z4: - | AA4: 雷电IC | AB4: 8040 | AC4: 2.948
U5: - | W5: ASL2330AN | X5: 0.52 | Z5: - | AB5: 9040 | AC5: 3.054
W6: IT8856FN/CX | X6: 0.93
B7: WN35B 成本差异说明
A8: 厂区 | B8: 机型 | C8: PCB尺寸 | D8: 日期 | E8: 汇率 | F8: 料号 | G8: SKU | H8: Type c | I8: 功率 | J8: WIFI | K8: DDR 存储 | L8: WIFI | M8: PCB | N8: Others | O8: SMT | P8: 小板 | Q8: TTL | R8: 备注 | S8: 已含型号备注
A9: 1 | B9: ROBOT临时核价20260104 | D9: 20260104 | E9: 7.01 | F9: A.F.M.2401621-MP | J9: NA | K9: 选配 | L9: NA | M9: =[2]深圳英众PCB单价清单!$P$1014/E9/1.13 -> 3.7241362 | N9: 41.248623 | O9: 3.5 | Q9: =SUM(K9:O9) -> 48.472759 | R9: 条子 | S9: pcb按MTN25机型参考报价，SMT预估，后续正式bom再按实际核价为准,不含keypark报价
A10: 2 | B10: ROBOT临时核价20260105小板 | F10: A.F.M.2401623-MP | J10: NA | K10: NA | L10: NA | M10: 0.6 | N10: 0.48775694 | O10: 0.5 | Q10: =SUM(K10:O10) -> 1.5877569 | R10: 条子 | S10: pcb按xn25预估，smt预估
B11: DNN253 | E11: 6.78 | F11: A.F.M.2602447 | J11: - | K11: 现询 | L11: - | M11: =27.8/E11/1.13 -> 3.6285796 | N11: 14.1 | O11: =22/E11 -> 3.2448378 | Q11: =SUM(K11:O11) -> 20.973417 | R11: 条子 | S11: PCB持续上涨，实单前重新确认
B12: WN38(8L+通孔+OSP) | E12: 6.78 | F12: A.F.M.2400978 | H12: =H10-H11 -> 0 | J12: - | K12: 现询 | L12: - | M12: =58.17/E12/1.13*1.05 -> 7.9722375 | N12: =16.4*1.05 -> 17.22 | O12: =23/E12 -> 3.3923304 | Q12: =SUM(K12:O12) -> 28.584568 | R12: PCB价保一周
B13: WN38(8L+通孔+OSP) | E13: 6.78 | F13: A.F.M.2400991 | J13: - | K13: 现询 | L13: - | M13: =58.17/E13/1.13*1.05 -> 7.9722375 | N13: =16.4*1.05 -> 17.22 | O13: =23/E13 -> 3.3923304 | Q13: =SUM(K13:O13) -> 28.584568 | R13: PCB价保一周
B14: DN105(8L+通孔+OSP) | E14: 6.78 | F14: A.F.M.2501240 | J14: - | K14: 现询 | L14: - | M14: =62.5/E14/1.13 -> 8.157778 | N14: =13.95*1.05 -> 14.6475 | O14: =22/E14 -> 3.2448378 | Q14: =SUM(K14:O14) -> 26.050116 | R14: PCB价格有效期一周
B15: DN105(8L+通孔+OSP) | E15: 6.78 | F15: A.F.M.2501241 | J15: - | K15: 现询 | L15: - | M15: =62.5/E15/1.13 -> 8.157778 | N15: =15.4*1.05 -> 16.17 | O15: =22/E15 -> 3.2448378 | Q15: =SUM(K15:O15) -> 27.572616 | R15: PCB价格有效期一周
B16: DN87(8L++通孔+OSP) | C16: 258.0*128.0*1.0mm | D16: 46241 | E16: 6.78 | F16: A.F.M.2503104 | J16: - | K16: 现询 | L16: - | M16: =59.12/E16/1.13 -> 7.7166053 | N16: 14.2 | O16: 2.94 | Q16: =SUM(K16:O16) -> 24.856605 | R16: PCB有效期8-15 | S16: 12.866631 | T16: 条子 | U16: 电量计 ：CW2217; ROM:128Mb
B17: WS17(6L+通孔+OSP) | C17: 183.4*285.8*1.6 | E17: 6.75 | F17: A.F.M.2601815 | G17: SKU1 | J17: - | K17: 现询 | L17: - | M17: =340.5/E17/1.13 -> 44.641101 | N17: 55.6 | O17: =34/E17 -> 5.037037 | Q17: =SUM(K17:O17) -> 105.27814 | R17: PCB按快板厂价格,smt为批量预估价
B18: WS17(6L+通孔+OSP) | C18: 183.4*285.8*1.6 | E18: 6.75 | F18: A.F.M.2601816 | G18: SKU2 | J18: - | K18: 现询 | L18: - | M18: =340.5/E18/1.13 -> 44.641101 | N18: 54.9 | O18: =34/E18 -> 5.037037 | Q18: =SUM(K18:O18) -> 104.57814 | R18: PCB按快板厂价格,smt为批量预估价
B19: WS17(6L+通孔+OSP) | C19: 183.4*285.8*1.6 | E19: 6.75 | F19: A.F.M.2602249 | G19: SKU3 | J19: - | K19: 现询 | L19: - | M19: =340.5/E19/1.13 -> 44.641101 | N19: 54.8 | O19: =34/E19 -> 5.037037 | Q19: =SUM(K19:O19) -> 104.47814 | R19: PCB按快板厂价格,smt为批量预估价
B20: WS17(6L+通孔+OSP) | C20: 183.4*285.8*1.6 | E20: 6.72 | F20: A.F.M.2602505 | J20: - | K20: 现询 | L20: - | M20: =73.78/E20/1.13 -> 9.7160767 | N20: 57.7 | O20: =34/E20 -> 5.0595238 | Q20: =SUM(K20:O20) -> 72.475601 | R20: 65套PCB价格
B21: PS21(10L+通孔+OSP） | C21: 216.4*167.2*1.6mm | D21: 46275 | E21: 6.72 | F21: A.F.M.2602442 | J21: - | K21: 现询 | L21: - | M21: =352.5/E21/1.13 -> 46.42067 | N21: 77.1 | O21: =40/E21 -> 5.952381 | Q21: =SUM(K21:O21) -> 129.47305 | R21: LPDDR5X_8GB 315球*4 | S21: 不含屏蔽罩价格
B22: PS21(10L+通孔+OSP） | C22: 216.4*167.2*1.6mm | D22: 46275 | E22: 6.72 | F22: A.F.M.2602443 | J22: - | K22: 现询 | L22: - | M22: =352.5/E22/1.13 -> 46.42067 | N22: 77.7 | O22: =40/E22 -> 5.952381 | Q22: =SUM(K22:O22) -> 130.07305 | R22: LPDDR5X_8GB 315球*4 | S22: 不含屏蔽罩价格
B23: PS21(10L+通孔+OSP） | C23: 216.4*167.2*1.6mm | D23: 46275 | E23: 6.72 | F23: A.F.M.2602931 | J23: - | K23: 现询 | L23: - | M23: =352.5/E23/1.13 -> 46.42067 | N23: 77.7 | O23: =40/E23 -> 5.952381 | Q23: =SUM(K23:O23) -> 130.07305 | R23: LPDDR5X_16GB 315球*4 | S23: 不含屏蔽罩价格
B24: DN38 | E24: 6.78 | F24: A.F.M.2501241 | N24: =16.02*1.1 -> 17.622 | O24: =22/E24 -> 3.2448378
A25: 3 | B25: LP13（8L+HDI+沉金）预估LP13C | D25: 20251128 | E25: 7.01 | F25: A.F.M.2502474 | G25: SKU1 | H25: 双Type c(两个Type c接口)（LT7911D/CS32G053HRCW6NR） | I25: Ultra-5-226V(16GB) | J25: AX211.D2WG | K25: 选配 | L25: 7.5 | M25: =68.912/E220/1.13 -> 8.5054492 | N25: =29.9075200457023+2.5 -> 32.40752 | O25: 4 | Q25: =SUM(L25:O25) -> 52.412969 | R25: 条子 | S25: 此项目为预估报价，PCB直接参考LP13,Others部分建议参考A.F.M.2502474（LP13-SKU1、WIFI 6 WIFI AX211）+加一颗G2708C 芯片
A26: 1 | B26: LP13C（8L+HDI+OSP） | D26: 46126 | E26: 6.837 | F26: A.F.M.2600129 | L26: 7.5 | M26: =68.91/E26/1.3 -> 7.7530631 | N26: 30.1 | O26: 4 | Q26: =SUBTOTAL(109,L26:O26) -> 0
B27: PN50(8L+通孔+OSP) | D27: 20251229 | E27: 7.01 | F27: A.F.M.2600118 | H27: 单Type c(两个Type c接口)IT5272FN | I27: H-25W | J27: 选配 | K27: 选配 | L27: 选配 | N27: 28.2 | O27: 0.3 | Q27: =SUM(M27:O27) -> 28.5 | R27: 报价不含EPTAD-A5R，CKD
A28: 4 | B28: PN50(8L+通孔+OSP) | D28: 20251229 | E28: 7.01 | F28: / | H28: 单Type c(两个Type c接口)IT5272FN | I28: H-25W | J28: 选配 | K28: 选配 | L28: 选配 | M28: =60.16/E28/1.13 -> 7.594713 | N28: 29.581934 | O28: 4 | Q28: =SUM(M28:O28) -> 41.176647 | R28: 条子 | S28: 全功能(IT5272FN)；含加密IC TPM,含UDP;pcb按样品单价核算
A29: 6 | B29: WN25(6L+通孔+OSP) | C29: 187.0*99.2*1.0mm | D29: 46087 | E29: 6.8226 | F29: A.F.M.2600389 | G29: SKU3 | H29: 单Type c(两个Type c接口)IT5272FN | I29: 25W | J29: BE211.D2WG.NVQ | K29: 现询 | L29: 11.5 | M29: =17.24/E29/1.13 -> 2.2361911 | N29: =14.4+0.57 -> 14.97 | O29: =20.5/E29 -> 3.0047196 | Q29: =SUM(L29:O29) -> 31.710911 | R29: 0+512 UFS | S29: HDMI2.0,ROM:256Mb,含496球DDR转接小板,
A30: 1 | C30: 187.0*99.2*1.0mm | D30: 46136 | E30: 6.8225 | F30: A.F.M.2600388 | G30: SKU2 | H30: 单Type c(两个Type c接口)IT5272FN | I30: 25W | J30: WD_RTL8821CE_V20(MS) | K30: 现询 | L30: =12.9/E30/1.13 -> 1.6732765 | M30: =17.24/E30/1.13 -> 2.2362238 | N30: =15.3+0.57 -> 15.87 | O30: =20.5/E30 -> 3.0047636 | Q30: =SUM(L30:O30) -> 22.784264 | R30: 496球（小板）+512 UFS | S30: HDMI2.0,TPM,ROM 256Mb,含496球DDR转接小板
A31: 1 | C31: 187.0*99.2*1.0mm | D31: 46163 | E31: 6.8 | F31: A.F.M.2601423 | J31: - | K31: 现询 | L31: - | M31: =32.32/E31/1.13 -> 4.2061426 | N31: 15.2 | O31: =20.5/E31 -> 3.0147059 | Q31: =SUM(L31:O31) -> 22.420849
A32: 1 | C32: 187.0*99.2*1.0mm | D32: 46175 | E32: 6.8 | F32: A.F.M.2601434 | M32: =26.51/E32/1.13 -> 3.450026 | N32: 16.4 | O32: =20.5/E32 -> 3.0147059 | Q32: =SUM(L32:O32) -> 22.864732 | S32: PCB无卤
A33: 1 | C33: 187.0*99.2*1.0mm | D33: 46134 | E33: 6.8225 | F33: A.F.M.2600780 | G33: SKU5 | H33: 单Type c(两个Type c接口)IT5272FN | I33: 25W | J33: CDW-61851BE-00 | K33: 现询 | L33: =17.46/E33/1.13 -> 2.2647603 | M33: =17.24/E33/1.13 -> 2.2362238 | N33: 13.5 | O33: =20.1/E33 -> 2.9461341 | Q33: =SUM(L33:O33) -> 20.947118 | R33: 条子
A34: 1 | C34: 187.0*99.2*1.0mm | D34: 46135 | E34: 6.8225 | F34: A.F.M.2600839 | G34: SKU10 | H34: 单Type c(两个Type c接口)IT5272FN | J34: CDW-61852BE-00 | K34: 现询 | L34: =25.72/E34/1.13 -> 3.3361762 | M34: =18.89/E34/1.13 -> 2.4502476 | N34: =14.4+0.57 -> 14.97 | O34: =20.5/E34 -> 3.0047636 | Q34: =SUM(L34:O34) -> 23.761187 | R34: 条子 | S34: HDMI2.0.无卤PCB,含496转接小板
A35: 1 | C35: 187.0*99.2*1.0mm | D35: 46135 | E35: 6.8225 | F35: A.F.M.2600853 | G35: SKU11 | H35: 单Type c(两个Type c接口)IT5272FN | J35: - | K35: 现询 | L35: - | M35: =23.2/E35/1.13*1.2 -> 3.6111643 | N35: 16.8 | O35: =20.1/E35+0.1 -> 3.0461341 | Q35: =SUM(L35:O35) -> 23.457298 | R35: 条子 | S35: HDMI2.0,含496转接小板，HFPCB
A36: 7 | C36: 187.0*99.2*1.0mm | D36: 46101 | E36: 6.8225 | F36: A.F.M.2600390 | G36: SKU4 | H36: 单Type c(两个Type c接口)IT5272FN | I36: 25W | J36: AX211.D2WG | K36: 现询 | L36: 7.5 | M36: =17.24/E36/1.13 -> 2.2362238 | N36: 14.1 | O36: =20.1/E36 -> 2.9461341 | Q36: =SUM(L36:O36) -> 26.782358 | R36: LPDDR5-315球8G*2+256 UFS | S36: HDMI2.0,ROM:256Mb
A37: 1 | C37: 187.0*99.2*1.0mm | D37: 20251224 | E37: 6.8225 | F37: A.F.M.2503155 | G37: SKU1 | H37: 单Type C IC及两个Type C 接口（IT5272FN） | I37: 15w | J37: AX211.D2WG | K37: 现询 | L37: 7.5 | M37: =17.24/E37/1.13 -> 2.2362238 | N37: 14.7 | O37: =20.1/E37 -> 2.9461341 | Q37: =SUM(M37:O37) -> 19.882358 | R37: LPDDR5-315球8G*2+0 | S37: HDMI2.0/TPM/ROM 256Mb
A38: 1 | B38: RPLK3（6L+通孔+OSP) | C38: 184x170x1.6mm | D38: 46128 | E38: 6.7739 | F38: A.F.M.2600743 | J38: - | K38: 现询 | L38: - | M38: =41.68/E38/1.13 -> 5.445158 | N38: 18 | O38: =32/E38 -> 4.7240142 | Q38: =SUBTOTAL(109,M38:O38) -> 0
A39: 1 | B39: RPLK3（6L+通孔+OSP) | C39: 184x170x1.6mm | D39: 46128 | E39: 6.7739 | F39: A.F.M.2600589 | J39: - | K39: 现询 | L39: - | M39: =32.35/E39/1.13 -> 4.2262683 | N39: 15.8 | O39: =32/E39 -> 4.7240142 | Q39: =SUBTOTAL(109,M39:O39) -> 0
A40: 1 | B40: RPLK3（6L+通孔+OSP) | C40: 184x170x1.6mm | D40: 46128 | E40: 6.7739 | F40: A.F.M.2600590 | J40: - | K40: 现询 | L40: - | M40: =32.35/E40/1.13 -> 4.2262683 | N40: 15.8 | O40: =32/E40 -> 4.7240142 | Q40: =SUBTOTAL(109,M40:O40) -> 0
A41: 1 | B41: RPLK3（6L+通孔+OSP) | C41: 184x170x1.6mm | D41: 46153 | E41: 6.7986 | F41: A.F.M.2601222 | M41: =32.35/E41/1.13 -> 4.2109138 | N41: 15.6
A42: 1 | B42: RPLK3（6L+通孔+OSP) | C42: 184x170x1.6mm | D42: 46153 | E42: 6.7986 | F42: A.F.M.2601256 | M42: =32.35/E42/1.13 -> 4.2109138 | N42: 13.8
A43: 1 | B43: RPLK3（6L+通孔+OSP) | C43: 184x170x1.6mm | D43: 46153 | E43: 6.7986 | F43: A.F.M.2601257 | M43: =32.35/E43/1.13 -> 4.2109138 | N43: 14.5
A44: 9 | B44: RPLK3（6L+通孔+OSP) | C44: 184x170x1.6mm | D44: 46049 | E44: 6.8819 | F44: A.F.M.2503286 | G44: SKU1 | H44: 无TYPE C | I44: H-45W | J44: 选配 | K44: 现询 | L44: 选配 | M44: =32.35/E44/1.13 -> 4.159944 | N44: 16.8 | O44: =32/E44 -> 4.6498787 | Q44: =SUM(M44:O44) -> 25.609823 | R44: 条子 | S44: 芯海CSCS2010RBR6NR，瑞昱RTL8111H-CG,SMT为预估计
A45: 10 | B45: RPLK3（6L+通孔+OSP) | C45: 184x170x1.6mm | D45: 46126 | E45: 6.837 | F45: A.F.M.2503287/A.F.M.2600589/A.F.M.2600590 | G45: SKU2 | H45: 台式机 | I45: H-45W | J45: 选配 | K45: 现询 | L45: 现询 | M45: =32.35/E45/1.13 -> 4.1872632 | N45: 14.58 | O45: =32/E45 -> 4.6804154 | Q45: =SUM(M45:O45) -> 23.447679 | R45: 条子 | S45: 芯海CSCS2010RBR6NR，瑞昱RTL8111H-CG,SMT为预估计
A46: 1 | B46: RPLM3S4(6L+通孔+OSP) | C46: 239.2x195x1.6mm | D46: 46132 | E46: 6.76 | F46: 高配 | G46: 高配 | H46: - | I46: 65W | J46: - | K46: 现询 | L46: - | M46: =56.5/E46/1.13 -> 7.3964497 | N46: 19.93 | O46: =32/E46 -> 4.7337278 | Q46: =SUM(K46:O46) -> 32.060178 | R46: 条子 | S46: HDMI2.0:LT86101UXS; 网卡IC:RTL8125D; 报价有效期6月30日
A47: 1 | C47: 239.2x195x1.6mm | D47: 46189 | E47: 6.76 | F47: A.F.M.2600886 | H47: - | I47: 65W | K47: 现询 | M47: =56.5/E47/1.13 -> 7.3964497 | N47: 19.9 | O47: =32/E47 -> 4.7337278 | Q47: =SUM(K47:O47) -> 32.030178 | S47: HDMI2.0:LT86101UXS; 网卡IC:RTL8125D; ROM:128Mb; 报价有效期6月30日 | T47: 电源方案：RT3624BEGQW； DRMOS: SPT5516*6; AUDIO:ALC897
A48: 1 | C48: 239.2x195x1.6mm | D48: 46135 | E48: 6.8 | F48: A.F.M.2600884 | G48: SKU1 | H48: - | I48: 65W | J48: - | K48: 现询 | L48: - | M48: =39.83/E46/1.13*1.15 -> 5.9962952 | N48: 15.1 | O48: =30/E46 -> 4.4378698 | Q48: =SUM(M48:O48) -> 25.534165 | R48: 条子
A49: 1 | C49: 239.2x195x1.6mm | D49: 46132 | E49: 6.76 | F49: A.F.M.2600885 | G49: SKU2 | H49: - | I49: 65W | J49: - | K49: 现询 | L49: - | M49: =56.5/E49/1.13 -> 7.3964497 | N49: 17.5 | O49: =30/E49 -> 4.4378698 | Q49: =SUM(M49:O49) -> 29.33432 | R49: 条子
A50: 11 | B50: LN89C(预估) | D50: 20250928 | E50: 7.07 | F50: A.F.M.2401762 | G50: SKU13-8L | H50: 单Type c IC及两个接口（CS32G053HRCW6NR） | I50: 30W | J50: 选配 | K50: 选配 | L50: 选配 | M50: =42.7/E50/1.13 -> 5.3447823 | N50: 20.173442 | O50: / | Q50: 20.173442 | R50: 条子 | S50: 全功能（CS32G053HRCW6NR），含TPM;适用于IPS
A51: 1 | B51: PTLT19(定制) | C51: 180.1*170.0*1.6mm | D51: 46170 | E51: 6.7963 | F51: A.F.M.2600920 | G51: SKU4 | H51: 单TYPE C IC+双TYPE-C连接器 | I51: 25W | J51: - | K51: 现询 | L51: - | M51: =49.93/E51/1.13 -> 6.5014553 | N51: 70.8 | O51: =40/E51 -> 5.8855554 | Q51: =SUBTOTAL(109,M51:O51) -> 0 | S51: 雷电：JHL9040R*2 ；HDMI2.0: IT66318FN; 万兆网卡：RTL8127AT*2；ROM:256Mb ; PCIE-SATA; | T51: 电源方案：MP29011； Drmos:MP86941*5; codec:ALC897; EC:CSCE2010WBR6NR;
A52: 12 | B52: PTLT19(定制) | C52: 180.1*170.0*1.6mm | D52: 46093 | E52: 6.9264 | F52: A.F.M.2502641 | G52: SKU2 | H52: 单Type C IC及两个Type C 接口（IT5272FN） | I52: U-25W | J52: - | K52: 现询 | L52: - | M52: =49.93/6.8/1.13*1.1 -> 7.1477095 | N52: 75 | O52: =40/E52 -> 5.7750058 | Q52: =SUM(K52:O52) -> 87.922715 | R52: 条子 | S52: 全功能（IT5272FN）；含加密IC TPM；含CW2217 PM反馈这是最全的SKU
A53: 13 | B53: ROBOT临时核价 1124 | D53: 20251124 | E53: 7.1 | F53: / | J53: NA | K53: 选配 | L53: NA | M53: =[2]深圳英众PCB单价清单!$P$1014/E53/1.13 -> 3.6769288 | N53: 17.403377 | O53: 3.5 | Q53: =SUM(K53:O53) -> 24.580306 | R53: 条子 | S53: pcb按MTN25机型参考报价，SMT预估，后续正式bom再按实际核价为准,不含keypark报价
A54: 14 | B54: ROBOT临时核价 1128 | D54: 20251128 | E54: 7.1 | F54: / | J54: NA | K54: 选配 | L54: NA | M54: =[2]深圳英众PCB单价清单!$P$1014/E54/1.13 -> 3.6769288 | N54: 19.273622 | O54: 3.5 | Q54: =SUM(K54:O54) -> 26.450551 | R54: 条子 | S54: pcb按MTN25机型参考报价，SMT预估，后续正式bom再按实际核价为准,不含keypark报价
A55: 15 | B55: DNP67 | D55: 20251110 | E55: 6.901 | F55: / | G55: SKU1 | H55: 双Tpye c IC及两个Type c接口（ANX7447QN） | I55: N-6W | J55: AX101.D2WG | K55: 按实际 | L55: 3.1 | M55: 2.6883789 | N55: 14.668771 | O55: =20.1/E55 -> 2.9126214 | Q55: =SUM(K55:O55) -> 23.369771 | R55: LPDDR5x-315球4G
A56: 16 | B56: DNP67 | D56: 46043 | E56: 6.9667 | F56: A.F.M.2502013 | G56: SKU1 | H56: 双Tpye c IC及两个Type c接口（ANX7447QN） | I56: N-6W | J56: AX101.D2WG | K56: 选配 | L56: 3.1 | M56: 2.76 | N56: 15.5 | O56: =4*1.01 -> 4.04 | Q56: =SUM(K56:O56) -> 25.4 | R56: LPDDR5x-315球4G | S56: TYPE-C:ANX7447QN-AC-R,电量计:CW2217
A57: 17 | B57: DNP67 | D57: 46099 | E57: 6.901 | F57: A.F.M.2600245 | G57: SKU3 | H57: 双Tpye c IC及两个Type c接口（ANX7447QN） | J57: AX101.D2WG.NV | K57: 选配 | L57: 3.1 | M57: =24.24*1.1/6.901/1.13 -> 3.4192813 | N57: 16 | O57: =20.1/E57 -> 2.9126214 | Q57: =SUM(K57:O57) -> 25.431903 | R57: LPDDR5x-315球4G*2 | S57: TYPE-C:ANX7447QN-AC-R,电量计:CW2217,视频桥接：IT6113FN
A58: 1 | B58: PN99(10L+通孔+OSP) | D58: 46150 | E58: 6.8215 | F58: A.F.M.2502463 | M58: =24.85/E58/1.13 -> 3.2237998 | N58: 22 | O58: =23/E58 -> 3.3716924 | Q58: =SUM(K58:O58) -> 28.595492 | S58: 70W
A59: 1 | B59: PN99(10L+通孔+OSP) | D59: 46150 | E59: 6.8215 | F59: A.F.M.2502465 | M59: =24.85/E59/1.13 -> 3.2237998 | N59: 22.8 | O59: =23/E59 -> 3.3716924 | Q59: =SUM(K59:O59) -> 29.395492 | S59: OLED
A60: 19 | B60: PN99(10L+通孔+OSP) | D60: 20250918 | E60: 6.8802 | F60: A.F.M.2501978 | G60: SKU3 | H60: 单Type c(一个Type c接口)（IT5272FN） | I60: H-45W | J60: 选配 | K60: 现询 | L60: 选配 | M60: =43.6/E60/1.13 -> 5.6079868 | N60: 24.506763 | O60: =23/E60 -> 3.3429261 | Q60: =SUM(K60:O60) -> 33.457676 | R60: LPDDR5X-315球8G*4 | S60: 全功能（IT5272FN）；含加密IC TPM；含CW2217;含雷电IC9040*1;
A61: 20 | B61: PN99(10L+通孔+OSP) | D61: 46085 | E61: 6.8802 | F61: A.F.M.2502464 | G61: SKU6 | H61: 单个Type c(两个Type c接口)（IT5272FN） | I61: 25W | J61: 选配 | K61: 现询 | L61: 选配 | M61: =43.6/E61/1.13 -> 5.6079868 | N61: 20.33 | O61: =23/E61 -> 3.3429261 | Q61: =SUM(K61:O61) -> 29.280913 | R61: LPDDR5X-315球4G*4 | S61: 全功能（TYPE-C:IT5272FN, TPM；SLB 9672 含雷电IC9040*1,无电量计
A62: 21 | B62: PN99(10L+通孔+OSP) | D62: 46085 | E62: 6.8802 | F62: A.F.M.2502464 | G62: SKU6 | H62: 单个Type c(两个Type c接口)（IT5272FN） | I62: 25W | J62: 选配 | K62: 现询 | L62: 选配 | M62: =43.6/E62/1.13 -> 5.6079868 | N62: 20.33 | O62: =23/E62 -> 3.3429261 | Q62: =SUM(K62:O62) -> 29.280913 | R62: LPDDR5X-315球4G*4 | S62: 全功能（TYPE-C:IT5272FN, TPM；SLB 9672 含雷电IC9040*1,无电量计
A63: 22 | B63: APS16主板2盘位 | F63: / | I63: 临时bom预估报价 | J63: 选配 | K63: 选配 | L63: 选配 | M63: =28.5/7.13/1.13 -> 3.5373407 | N63: 33.719503 | O63: 4.5 | Q63: =SUM(K63:O63) -> 41.756843 | R63: 0+64 | S63: 含RTL8127AT，pcb无资料，按备注要求预估'MB 尺寸223.75*96.3/板厚1.6/无卤/八层通孔
A64: 27 | B64: SSD DB | D64: 46034 | E64: 6.9783 | F64: A.F.D.2500492 | G64: EVT | H64: / | J64: / | K64: / | L64: / | M64: =9.3/E64/1.13 -> 1.179383 | N64: 0.5 | O64: / | Q64: =SUM(M64:N64) -> 1.679383 | R64: / | S64: 沉金板贵,SMT待BOM成型再核
A65: 28 | B65: SATA DB | D65: 46034 | E65: 6.9783 | F65: A.F.D.2500491 | G65: EVT | H65: HDD CON*2， 谱瑞PS8527CTQFN20GTR2*2 | J65: / | K65: / | L65: / | M65: =10.57/E65/1.13 -> 1.3404385 | N65: 3.3 | O65: / | Q65: =SUM(M65:N65) -> 4.6404385 | R65: / | S65: 沉金板贵,SMT待BOM成型再核
A66: 29 | B66: TN29 | D66: 46057 | E66: 6.9514 | F66: A.P.0TN29018 | G66: SKU18 | J66: / | K66: / | L66: / | M66: =36/E66/1.14 -> 4.5428183 | N66: 13.02 | O66: =22/6.9514 -> 3.1648301 | Q66: =SUM(M66:N66) -> 17.562818 | R66: 条子
A67: 31 | B67: HDD-DB | F67: / | I67: DNS13/ A.F.D.2500175参考报价 | J67: 选配 | K67: 选配 | L67: 选配 | M67: =7.5/7.13/1.13 -> 0.93087912 | N67: 3.4092776 | O67: 0.3 | Q67: =SUM(K67:O67) -> 4.6401567 | R67: 0+64 | S67: pcb无资料，按备注要求预估'HDD DB尺寸：91.18*86.01/板厚1.6/无卤/四层通孔
A68: 32 | B68: APS16主板4盘位 | F68: / | I68: 临时bom预估报价 | J68: 选配 | K68: 选配 | L68: 选配 | M68: =49/7.13/1.13 -> 6.0817436 | N68: 48.067369 | O68: 4.5 | Q68: =SUM(K68:O68) -> 58.649112 | R68: 0+64 | S68: 含RTL8127AT，pcb无资料，按备注要求预估'MB尺寸:249.3*150/板厚1.6/无卤/八层通孔
A69: 33 | B69: HDD-DB | F69: / | I69: DNS9/A.F.D.2500026参考报价 | J69: 选配 | K69: 选配 | L69: 选配 | M69: =11.3/7.13/1.13 -> 1.4025245 | N69: 8.7426948 | O69: 0.6 | Q69: =SUM(K69:O69) -> 10.745219 | R69: 0+64 | S69: /JMB585，pcb无资料，按备注要求预估'HDD DB尺寸：137*86.75/板厚1.6/无卤/四层通孔
A70: 34 | B70: DN59(8L+通孔+OSP) | D70: 20251110 | E70: 7.13 | F70: A.F.M.2400959-MP | G70: SKU28 | I70: I5-1235U(不带IPU)(15W) | J70: 选配 | K70: 选配 | L70: 选配 | M70: =43.37/7.13/1.13 -> 5.3829637 | N70: 20.203259 | O70: =24.78/7.13/1.13 -> 3.0756246 | Q70: 128.50201 | R70: 条子 | S70: 单Type c；含英特尔雷电IC;
A71: 35 | B71: LN89（8L+HDI2+OSP） | D71: 20250928 | E71: 7.13 | F71: A.F.M.2401580-PVT | G71: SKU14-8L | H71: 单Type c IC及两个接口（CYPD6228） | I71: 30W | J71: 选配 | K71: 选配 | L71: 选配 | M71: =43.88/7.13/1.13*1.03 -> 5.6096514 | N71: 24.926766 | O71: 3.5 | Q71: 33.30209 | R71: 条子 | S71: 全功能（CYPD6228），含TPM;CW2217；适用于OLED,预估pcb 无卤单价，后续有订单按实际为准
A72: 36 | B72: LN25C(8L+通孔+OSP) | D72: 20250918 | E72: 7.13 | F72: A.F.M.2500394 | G72: SKU6 | H72: 单Type-C IC及两个typeC接口（CS32G053H） | I72: H-28W | J72: AX211.D2WG | K72: 选配 | L72: 7.5 | M72: =38.55/E72/1.13 -> 4.7847187 | N72: 22.878676 | O72: =23.5/6.91 -> 3.4008683 | Q72: =SUM(K72:O72) -> 38.564263 | S72: 全功能（CS32G053H）；含加密IC TPM；含CW2217，PCB为无卤板材预估价格
A73: 37 | D73: 46090 | E73: 6.91 | F73: A.F.M.2600075 | G73: SKU25 | H73: 单Type-C IC及两个typeC接口（CS32G053H） | I73: 226V-17W | J73: AX211.D2WG | K73: 现询 | L73: 7.5 | M73: =38.55/E73/1.13 -> 4.9370542 | N73: 19.3 | O73: =23.5/6.91 -> 3.4008683 | Q73: =SUM(L73:O73) -> 35.137922 | R73: 条子 | S73: CS32G053H）；含CW2217
D74: 46286 | E74: 6.7 | F74: A.F.M.2603041 | G74: SKU43 | J74: - | K74: 现询 | L74: - | M74: =59.85/E74/1.13 -> 7.9051644 | N74: 21.1 | O74: =23.5/6.91 -> 3.4008683 | Q74: =SUM(L74:O74) -> 32.406033 | R74: LINYA 216PCS
E75: 6.75 | F75: A.F.M.2601780 | J75: - | K75: 现询 | L75: - | M75: =60/E75/1.13 -> 7.8662734 | N75: 23.7 | O75: =23.5/6.91 -> 3.4008683 | Q75: =SUBTOTAL(109,M75:O75) -> 0 | S75: 四会有卤PCB，暂无板料
D76: 46272 | E76: 6.72 | F76: A.F.M.2503211/A.F.M.2503298 | J76: - | K76: 现询 | L76: - | M76: =65.32/E76/1.13 -> 8.6019806 | N76: 21.9 | O76: =23.5/6.91 -> 3.4008683 | Q76: =SUBTOTAL(109,M76:O76) -> 0 | S76: PCB有效期一周
E77: 6.72 | F77: A.F.M.2601530 | J77: - | K77: 现询 | L77: - | M77: =65.32/E77/1.13 -> 8.6019806 | N77: 22.3 | O77: =23.5/6.91 -> 3.4008683 | Q77: =SUBTOTAL(109,M77:O77) -> 0
E78: 6.72 | F78: A.F.M.2602796 | J78: - | K78: 现询 | L78: - | M78: =65.32/E78/1.13 -> 8.6019806 | N78: 23.52 | O78: =23.5/6.91 -> 3.4008683 | Q78: =SUBTOTAL(109,M78:O78) -> 0
A79: 1 | E79: 6.7963 | F79: A.F.M.2600134 | G79: SKU28 | J79: AX211.D2WG.NV | K79: 现询 | M79: =38.55/E79/1.13 -> 5.0196496 | N79: 21 | O79: =23.5/6.91 -> 3.4008683 | Q79: =SUBTOTAL(109,L79:O79) -> 0
A80: 1 | E80: 6.7739 | F80: A.F.M.2601529 | G80: SKU37 | J80: - | K80: 现询 | L80: - | M80: =52.17/6.7739/1.13 -> 6.8155924 | N80: =21.2+20/6.7739/1.13 -> 23.81284 | O80: =23.5/E80 -> 3.469198 | Q80: =SUM(L80:O80) -> 34.09763
A81: 38 | D81: 46107 | E81: 6.91 | F81: A.F.M.2600133 | G81: SKU27 | H81: 单Type-C IC及两个typeC接口（CS32G053H） | J81: AX211.D2WG. | K81: 现询 | L81: 7.5 | M81: =38.55/E81/1.13 -> 4.9370542 | N81: 20.9 | O81: =23.5/6.91 -> 3.4008683 | Q81: =SUM(L81:O81) -> 36.737922 | R81: 条子
A82: 1 | D82: 46122 | E82: 6.8819 | F82: A.F.M.2600318 | G82: SKU29 | H82: 单Type-C IC及两个typeC接口（CS32G053H） | J82: AX211.D2WG. | K82: 现询 | L82: 7.5 | M82: =38.55/E82/1.13 -> 4.957213 | N82: 21.2 | O82: 3.4 | Q82: =SUM(L82:O82) -> 37.057213
A83: 1 | D83: 46182 | E83: 6.7851 | F83: A.F.M.2601227 | M83: =38.07/E83/1.13 -> 4.9653307 | N83: 22.1 | O83: 3.4 | Q83: =SUM(L83:O83) -> 30.465331 | R83: 含PCB 100套工程费4000
A84: 39 | D84: 46106 | E84: 6.91 | F84: A.F.M.2600076 | G84: SKU26 | H84: 单Type-C IC及两个typeC接口（CS32G053H） | J84: AX211.D2WG | K84: 现询 | L84: 7.5 | M84: =38.55/E84/1.13 -> 4.9370542 | N84: =18.65+0.86 -> 19.51 | O84: =23.5/6.91 -> 3.4008683 | Q84: =SUM(L84:O84) -> 35.347922 | R84: 条子 | S84: CS32G053H）；含CW2217
A85: 40 | B85: WN792 | D85: 20251104 | E85: 7.13 | F85: / | J85: 选配 | K85: 选配 | L85: 选配 | M85: =21.7/E85/1.13 -> 2.6933436 | N85: =11.62+0.72 -> 12.34 | O85: 3.5 | Q85: =SUM(K85:O85) -> 18.533344 | S85: Others按WNTU146预估，pcb按mtn792预估，SMT为预估，实际待正式bom出后再估算,CPU/WIF/UFS/PCB新机型暂未核价，待确认后重新安排核价
A86: 41 | B86: WN792 | D86: 20251104 | E86: 7.13 | F86: / | I86: 临时bom估价1104/15w核价 | J86: 选配 | K86: 选配 | L86: UFS | M86: =21.7/E86/1.13 -> 2.6933436 | N86: =11.62+0.72 -> 12.34 | O86: 3.5 | Q86: =SUM(K86:O86) -> 18.533344 | S86: Others按WNTU146预估，pcb按mtn792预估，SMT为预估，实际待正式bom出后再估算,CPU/WIF/UFS/PCB新机型暂未核价，待确认后重新安排核价
A87: 42 | B87: WN792 | D87: 46056 | E87: 6.9514 | F87: A.F.M.2600136 | G87: SKU1 | H87: 单Type c IC及两个接口 | J87: 选配 | K87: 选配 | L87: UFS | M87: =21.7/E87/1.13 -> 2.7625428 | N87: =16.78+0.72 -> 17.5 | O87: =22/E87 -> 3.1648301 | Q87: =SUM(K87:O87) -> 23.427373 | S87: TYPE-C:联阳IT5272FN;TPM:SLB 9672;PCB 1.2KPCS以上可按2.71U，SMT为预估价
A88: 43 | B88: WN792(6L+通孔+OSP) | D88: 46101 | E88: 6.902 | F88: A.F.M.2600137 | G88: SKU2 | H88: 单Type c(两个Type c接口)IT5272FN | I88: 25W | J88: 选配 | K88: 现询 | L88: 选配 | M88: =21.7/6.91/1.13 -> 2.779094 | N88: =13.32+0.72 -> 14.04 | O88: =22/E88 -> 3.1874819 | Q88: =SUM(K88:O88) -> 20.006576 | R88: 0+512UFS | S88: 电量计：BQ24780SRUYR
B89: WN21B | D89: 46251 | E89: 6.75 | F89: A.F.M.2600756 | J89: 选配 | K89: 现询 | L89: 选配 | M89: =38.98/E89/1.13 -> 5.1104556 | N89: 17.1 | O89: =22/E89 -> 3.2592593 | Q89: =SUM(K89:O89) -> 25.469715
A90: 44 | B90: WN21B | D90: 46058 | E90: 6.9514 | F90: A.F.M.2501978 | G90: SKU1 | H90: 单Type c IC及两个接口 | J90: 选配 | K90: 现询 | L90: 选配 | M90: =24.33/E90/1.13 -> 3.0973579 | N90: 15.01 | O90: =22/E90 -> 3.1648301 | Q90: =SUM(K90:O90) -> 21.272188 | S90: TYPE-C:联阳IT5272FN，TPM：9672,PCB 1.2KPCS以上可按2.71U核价，SMT为预估价
A91: 45 | B91: WN21B(6L+通孔+OSP) | D91: 46101 | E91: 6.901 | F91: A.F.M.2600507 | G91: SKU2 | H91: 单Type c IC及两个接口 | I91: 25W | J91: 选配 | K91: 现询 | L91: 选配 | M91: =24.33/E91/1.13 -> 3.1199788 | N91: =13.99+0.72 -> 14.71 | O91: =22/E91 -> 3.1879438 | Q91: =SUM(K91:O91) -> 21.017923 | R91: LPDDR5-8GB 315球+512 UFS | S91: TPM：9672,电量计CW2217
A92: 46 | B92: WNTU146 | D92: 46081 | E92: 6.9264 | F92: A.F.M.2502465 | I92: 临时bom估价1027 | J92: 选配 | K92: 现询 | L92: UFS | M92: 暂无待定 | N92: 21.9 | O92: 3.5 | Q92: =N92+O92 -> 25.4 | S92: 全功能(IT5272FN)；含CW2217;其中flash为估价，后面按实际验证为准。CPU/WIF/UFS/PCB新机型暂未核价，待确认后重新安排核价
A93: 47 | B93: DN21C(8L+通孔+OSP) | D93: 20240919 | E93: 7.13 | F93: A.F.M.2401621-MP | G93: SKU135 | H93: 单Tpye c IC及两个Type c接口（ANX7447QN） | I93: U-15W | J93: 选配 | K93: 现询 | L93: 选配 | M93: =3.85264748791615/7.21*7.17 -> 3.8312736 | N93: =15.2241732953349+0.23 -> 15.454173 | O93: =23.73/E113/1.13 -> 3.0522369 | Q93: =SUM(K93:O93) -> 22.337684 | R93: 条子/SSD PCIE3.0 | S93: 全功能（ANX7447QN）；含有加密IC TPM(9672)；含CW2217
A94: 48 | D94: 46056 | E94: 6.9514 | F94: A.F.M.2401484 | G94: SKU132 | H94: 单Tpye c IC及两个Type c接口（ANX7447QN） | I94: H-28W | J94: 选配 | K94: 现询 | L94: 选配 | M94: =3.85264748791615/7.21*7.17 -> 3.8312736 | N94: 13.5 | O94: 3.09 | Q94: =SUM(K94:O94) -> 20.421274 | R94: 条子/SSD PCIE3.0,TYPC-C 7447,电量计BQ24780SRUYR
A95: 1 | D95: 46176 | E95: 6.75 | F95: A.F.M.2500762 | J95: - | K95: 现询 | L95: - | M95: =38.264/E95/1.13*1.05 -> 5.267414 | N95: 12.5 | O95: 3.09 | Q95: =SUBTOTAL(109,M95:O95) -> 0 | R95: 报价有效期8-21日内
E96: 6.7 | F96: A.F.M.2500665 | J96: - | K96: 现询 | L96: - | M96: =54.21/E96/1.13 -> 7.1602166 | N96: 14.6 | O96: 3.09 | Q96: =O96+N96+M96 -> 24.850217
D97: 46246 | E97: 6.75 | F97: A.F.M.2401268 | J97: - | K97: 现询 | L97: - | M97: =38.264/E97/1.13*1.05 -> 5.267414 | N97: 14.92 | O97: 3.09 | Q97: =SUBTOTAL(109,M97:O97) -> 0 | R97: PCB有效期8-21日内
F98: A.F.M.2600731 | J98: 选配 | K98: 现询 | L98: 选配 | M98: =34.78*1.4/6.78/1.13 -> 6.3554964 | N98: 15.5 | O98: 3.09 | Q98: =SUM(K98:O98) -> 24.945496
E99: 6.75 | F99: A.F.M.2503181 | J99: - | K99: 现询 | L99: - | M99: =38.264/E99/1.13*1.05 -> 5.267414 | N99: 15 | O99: 3.09 | Q99: =SUM(K99:O99) -> 23.357414
E100: 6.7 | F100: A.F.M.2502587 | J100: - | K100: 现询 | L100: - | M100: =45.18/E100/1.13 -> 5.9675076 | N100: 15.9 | O100: 3.09 | Q100: =SUM(K100:O100) -> 24.957508
...

Sheet E BOM小核
V1: pcb为普通材质OSP工艺，如用特殊材质请单独核;CPU;DDR;SSD;EMMC;WIFI请按需求选配 | W1: - | X1: 类型 | Y1: 型号 | Z1: 美金单项单价 | AB1: - | AC1: 类型 | AD1: 型号 | AE1: 美金单项单价
W2: - | X2: TYPEC IC | Y2: ANX7447QN | Z2: 0.64 | AB2: - | AC2: 加密IC TPM | AD2: 9672 | AE2: 1.05
B3: 9月份汇率：6.71 | F3: 6月份汇率：6.8 | H3: 币种:USD | W3: - | Y3: CYPD6228 | Z3: 1.7769148 | AB3: - | AC3: 电量计 | AD3: CW2217 | AE3: 0.23
W4: - | Y4: CYPD6227 | Z4: 1.75 | AB4: - | AC4: 雷电IC | AD4: 8040 | AE4: 2.948
W5: - | Y5: ASL2330AN | Z5: 0.52 | AB5: - | AD5: 9040 | AE5: 3.054
Y6: IT8856FN/CX | Z6: 0.93
B7: 机型 | C7: PCB尺寸 | D7: 日期 | E7: 更新汇率 | F7: 料号 | G7: 规格 | H7: Type c | I7: 功率 | J7: 配置 | K7: WIFI | L7: CPU 存储 | M7: WIFI | N7: PCB | O7: PCB | P7: PCB | Q7: Others | R7: SMT | S7: TTL | U7: DDR/SSD | V7: 备注
A8: 2 | B8: DNN21S（6L+通孔+OSP） | C8: 214.5*119.9*1.0mm | D8: 20250901 | E8: 6.75 | F8: A.F.M.2302171-MP | G8: SKU22 | H8: 单Tpye c IC及单Type c接口（ANX7447QN） | I8: N-15W | J8: 0+128G | K8: 选配 | L8: 现询 | M8: 选配 | N8: =25.7/E8/1.13 -> 3.3693871 | O8: 5.57 | P8: 6.127 | Q8: 15.2 | R8: =21.1/E8/1.13 -> 2.7663061 | S8: =SUBTOTAL(109,P8:R8) -> 24.093306 | T8: 13.05 | U8: 条子 | V8: TPM:SLB 9672; 电量计： CW2015CHBD； ROM:128Mb;
A9: 2 | B9: DNN25（6L+通孔+OSP） | C9: 188.1*99.2*1.0mm | D9: 20250901 | E9: 6.75 | F9: A.F.M.250000X | G9: 全配 | H9: 双Type C IC及双Type c接口(ANX7447QN) | I9: N-15W | J9: 0+0 | K9: 选配 | L9: 现询 | M9: 选配 | N9: =26.63/E9/1.13 -> 3.4913143 | O9: 4.1587715 | P9: 4.5746486 | Q9: 17.92 | R9: =20.4/E9/1.13 -> 2.6745329 | S9: =SUBTOTAL(109,P9:R9) -> 25.169182 | T9: 14.53 | U9: LPDDR5-315球8G*2(江波龙) | V9: HDMI2.0 IT66318FN; TPM:SLB 9672;电量计：CW2217; ROM:128Mb;
A10: 2 | B10: JN11S(8L+通孔+OSP) | C10: 184.2*110.8*1.0mm | D10: 20250902 | E10: 6.75 | F10: A.F.M.2500669 | G10: SKU28 | H10: 单Type IC及Type C 单接口(ANX7447QN) | I10: N-15W | J10: 0+0 | K10: AX101.D2WG | L10: 现询 | M10: 选配 | N10: =22.47/E10/1.13 -> 2.9459194 | O10: =42.48/6.78/1.13 -> 5.5446785 | P10: 6.0991464 | Q10: 15.6 | R10: =23.45/E10/1.13 -> 3.0744018 | S10: =SUBTOTAL(109,P10:R10) -> 24.773548 | T10: 13 | U10: 条子 | V10: TPM:SLB 9672; 电量计：CW2015CHBD； ROM:128Mb ;
A11: 2 | B11: DNNXU(6L+通孔+OSP) | C11: 207.0*178.7*1.0mm | D11: 20250904 | E11: 6.75 | F11: A.F.M.2401323-MP | G11: SKU13 | H11: 单Tpye c IC及单Type c接口（ANX7447QN） | I11: N-15W | J11: 0+0 | K11: 选配 | L11: 现询 | M11: 选配 | N11: =17/E11/1.13 -> 2.2287775 | O11: 2.6548673 | P11: 2.920354 | Q11: 14.8 | R11: =19.77/E11/1.13 -> 2.5919371 | S11: =SUBTOTAL(109,P11:R11) -> 20.312291 | T11: 12.3 | U11: 条子 | V11: 电量计：CW2015CHBD； ROM:128Mb ;
A12: 2 | B12: DNN11S(8L+通孔+OSP) | C12: 184.2*110.8*1.0 | D12: 20250909 | E12: 6.75 | F12: A.F.M.2500505-MP | G12: SKU16 | H12: 单Tpye c IC及双Type c接口（ANX7447QN） | I12: N-6W | J12: 0+0 | K12: AX201.D2WG.NVW | L12: 现询 | M12: 选配 | N12: =27.55/E12/1.13 -> 3.6119305 | O12: 4.3024466 | P12: =51.02/E12/1.13*1.05 -> 7.0234022 | Q12: 17.1 | R12: =20.1/E12/1.13 -> 2.6352016 | S12: =SUBTOTAL(109,P12:R12) -> 26.758604 | T12: 13.4 | U12: 条子 | V12: TPM:SLB 9672; 电量计：CW2015CHBD； ROM:128Mb ;
A13: 2 | B13: DNP13C(6L+通孔+OSP) | C13: 211.7*102.0*1.0MM | D13: 20250902 | E13: 6.75 | F13: A.F.M.2502098 | G13: SKU17 | H13: 双Type c IC(双Type C 接口)(ANX7447QN) | I13: N-15W | J13: 0+0 | K13: 选配 | L13: 现询 | M13: 选配 | N13: =33.47/E13/1.13*1.2 -> 5.2656834 | O13: 6.2723581 | P13: =38.12/6.72/1.13*1.05 -> 5.2710177 | Q13: 18.4 | R13: =21.72/E13/1.13 -> 2.847591 | S13: =SUBTOTAL(109,P13:R13) -> 26.518609 | T13: 15.5 | U13: LPDDR5X-315球4G*2 | V13: ROM:128Mb
B14: DNN21(8L+HDI3+OSP) | C14: 214.5*119.9*1.0mm | D14: 20250909 | E14: 6.75 | F14: A.F.M.2401219-MP | G14: SKU9 | H14: 单Type c IC及单Type c 接口（ANX7447QN） | I14: N-15W | J14: 0+0 | K14: 选配 | L14: 现询 | M14: 选配 | N14: =74.66/E14/1.13 -> 9.7882661 | O14: 11.659552 | P14: 12.825508 | Q14: 16 | R14: =24.43/E14/1.13 -> 3.2028843 | S14: =SUBTOTAL(109,P14:R14) -> 32.028392 | T14: 11.9 | U14: LPDDR5-496球16G | V14: 电量计：CW2015CHBD； ROM:128Mb ;
A15: 2 | B15: DNN21F(6L+通孔+OSP) | C15: 214.9*119.9*1.0mm | D15: 20250910 | E15: 6.75 | F15: A.F.M.2402477-PVT | G15: SKU6 | H15: Type c(l双Type C 接口)(ANX7447QN) | I15: N-15w | J15: 0+128G | K15: 选配 | L15: 现询 | M15: 选配 | N15: =23.1/E15/1.13 -> 3.0285152 | O15: 3.6074961 | P15: 3.9682457 | Q15: 16.6 | R15: 2.6608507 | S15: =SUBTOTAL(109,P15:R15) -> 23.229096 | T15: 13.9 | U15: 群联/条子 | V15: HDMI2.0:IT66318FN; TPM:SLB 9672; USB3-10G:GL9901VAE; 电量计：CW2217; ROM:128Mb
A16: 2 | B16: DNN81S(6L+通孔+OSP) | C16: 190.0*114.0*1.0mm | D16: 20250912 | E16: 6.75 | F16: A.F.M.2402361-OOC3 | G16: SKU6 | H16: Type Ic(单Type c 接口)ANX7447QN | I16: N-6W | J16: 0+0 | K16: 选配 | L16: 现询 | M16: 选配 | N16: =20.2954/E16/1.13 -> 2.6608194 | O16: =28.6/6.78/1.13 -> 3.7329992 | P16: 4.1062991 | Q16: 14.8 | R16: =18.6/E16/1.13 -> 2.4385447 | S16: =SUBTOTAL(109,P16:R16) -> 21.344844 | T16: 11.6 | U16: 条子 | V16: 电量计：CW2015CHBD； ROM:128Mb ;
A17: 2 | B17: DNNTU146(4L+通孔+OSP) | C17: 207*131*1.0mm | D17: 20250806 | E17: 6.75 | F17: A.F.M.2501936-PVT | G17: SKU3 | H17: Type c(l双Type C 接口)(ANX7447QN) | I17: N-6W | J17: 0+0 | K17: 原RTL8821CE待更新 | L17: 现询 | M17: 选配 | N17: =21.57/E17/1.13 -> 2.8279253 | O17: 4.46 | P17: 4.906 | Q17: 13 | R17: =18.52/E17/1.13 -> 2.4280564 | S17: =SUBTOTAL(109,P17:R17) -> 20.334056 | T17: 10.43 | U17: 条子 | V17: 电量计：CW2217； ROM:128Mb ;
A18: 2 | B18: DNNTU146(4L+通孔+OSP) | C18: 207*131*1.0mm | D18: 20250806 | E18: 6.75 | F18: A.F.M.2501938 | G18: SKU5 | H18: Type c(l双Type C 接口)(ANX7447QN) | I18: N-15W | J18: 0+0 | K18: 8852BE | L18: 现询 | M18: 选配 | N18: =21.57/E18/1.13 -> 2.8279253 | O18: 4.46 | P18: 4.906 | Q18: 13.6 | R18: =18.52/E18/1.13 -> 2.4280564 | S18: =SUBTOTAL(109,P18:R18) -> 20.934056 | T18: 11.1 | U18: 条子 | V18: 电量计：CW2217； ROM:128Mb ;
A19: 2 | B19: JN106(6L+通孔+OSP) | C19: 189.9*114.0*1.0mm | D19: 20250626 | E19: 6.75 | F19: A.F.M.2501350-EVT | G19: SKU2 | H19: Type c(单Type C 接口)ANX7447QN | I19: N-6W | J19: 0+0 | K19: 选配 | L19: 现询 | M19: 选配 | N19: =21.65/E19/1.13 -> 2.8384136 | O19: 3.3810515 | P19: 3.7191567 | Q19: 14.4 | R19: =18.5/E19 -> 2.7407407 | S19: =SUBTOTAL(109,P19:R19) -> 20.859897 | T19: 12.3 | U19: 条子 | V19: 电量计：CW2015CHBD； ROM:128Mb ;
A20: 2 | B20: JN21S（8L+通孔+OSP） | C20: 214.5*119.9*1.0mm | D20: 20250916 | E20: 6.75 | F20: A.F.M.2302474 | G20: SKU1 | H20: Type c(双Type C 接口)(ANX7447QN) | I20: N-15W | J20: 0+0 | K20: 选配 | L20: 现询 | M20: 选配 | N20: =28.42/E20/1.13 -> 3.7259915 | O20: 4.4383134 | P20: 4.8821447 | Q20: 14.1 | R20: =22/E20/1.13 -> 2.8843002 | S20: =SUBTOTAL(109,P20:R20) -> 21.866445 | T20: 12.3 | U20: 条子 | V20: ROM:128Mb
A21: 2 | B21: JN21S（8L+通孔+OSP） | C21: 214.5*119.9*1.0mm | D21: 20250916 | E21: 6.75 | F21: A.F.M.2501017 | G21: SKU11 | H21: Type c(双Type C 接口)(ANX7447QN) | I21: N-6W | J21: 0+0 | K21: 选配 | L21: 现询 | M21: 选配 | N21: =28.42/E21/1.13 -> 3.7259915 | O21: 4.4383134 | P21: 4.8821447 | Q21: 13.9 | R21: =22/E21/1.13 -> 2.8843002 | S21: =SUBTOTAL(109,P21:R21) -> 21.666445 | T21: 11.1 | U21: 条子 | V21: ROM:128Mb
A22: 2 | B22: DNP28A(8L+HDI1+OSP) | C22: 155.0*89.0*1.2mm | D22: 20250915 | E22: 6.75 | F22: A.F.M.2302473-MP | G22: SKU4 | H22: 单Type c IC及单Type c 接口（ANX7447QN） | I22: N-15W | J22: 16G+256G | K22: AX201.D2WG | L22: 现询 | M22: 选配 | N22: =16.56/E22/1.13 -> 2.1710914 | O22: 2.586153 | P22: 2.8447683 | Q22: 16.7 | R22: =19.63/E22 -> 2.9081481 | S22: =SUBTOTAL(109,P22:R22) -> 22.452916 | T22: 14.8 | U22: LPDDR5-496球16G，EMMC群联 | V22: 电量计：CW2015CHBD； ROM:128Mb ;
A23: 2 | B23: DNN15B(8L+HDI1+OSP) | C23: 164.4*101.6*1.0mm | D23: 20250923 | E23: 6.75 | F23: A.F.M.2301127 | G23: SKU5 | H23: 单Type IC及Type C 单接口(ANX7447QN) | I23: N-15W | J23: 16G+0 | K23: 9560.D2WG | L23: 现询 | M23: 选配 | N23: =31.44/E23/1.13 -> 4.1219272 | O23: 4.9099427 | P23: =43.7/6.73/1.13*1.05 -> 6.0336099 | Q23: 13.9 | R23: =20.51/E23/1.13 -> 2.6889544 | S23: =SUBTOTAL(109,P23:R23) -> 22.622564 | T23: 11.9 | U23: LPDDR5-496球16G | V23: 全功能(ANX7447QN);
A24: 2 | B24: DNN20A(6L+通孔+OSP) | C24: 171.2*105.5*1.0 | D24: 20251009 | E24: 6.75 | F24: A.F.M.2500693 | G24: SKU9 | H24: 双Type C IC及双Type c接口(ANX7447QN) | I24: N-6W | J24: 16G+0 | K24: AX101.D2WG | L24: 现询 | M24: 选配 | N24: =42.7/E24/1.13 -> 5.5981645 | O24: 6.6684019 | P24: 7.3352421 | Q24: 17.8 | R24: =23.83/E24/1.13 -> 3.1242216 | S24: =SUBTOTAL(109,P24:R24) -> 28.259464 | T24: 14.83 | U24: LPDDR5X-496球16G | V24: 全功能(ANX7447QN);定制案
A25: 2 | B25: DNS13(8L+通孔+OSP) | C25: 150*101.1 | D25: 46056 | E25: 6.75 | F25: A.F.M.2501899-MP A.F.M.2502886 | G25: SKU5 | H25: Type c(单Type C 接口)(VL162) | I25: N-6W | J25: 0+32G | K25: 选配 | L25: 现询 | M25: 选配 | N25: =18.22/E25/1.13 -> 2.388725 | O25: =24.73/6.78/1.13*1.05 -> 3.3892631 | P25: =28.52/E25/1.13 -> 3.7391019 | Q25: 16.1 | R25: =26.66/E25/1.13 -> 3.4952475 | S25: =SUBTOTAL(109,P25:R25) -> 23.334349 | T25: 14 | U25: 0+EMMC5.1 32GB | V25: HDMI2.0:IT66318FN; RJ45:RTL8125BG; USB3-10G:GL9901VAE; ROM:128Mb
A26: 2 | B26: DNP59（6L+通孔+OSP） | C26: 134.16*126.50*1.0mm | D26: 20251020 | E26: 6.75 | F26: A.F.M.2501663 | G26: SKU3 | H26: 单Type IC及Type C 单接口(RTS5453H) | I26: N-6W | J26: 8G*2+0 | K26: AX201.D2WG | L26: 现询 | M26: 选配 | N26: =17.59/E26/1.13 -> 2.3061291 | O26: 2.7470068 | P26: 3.0217074 | Q26: 18.2 | R26: 3.5749467 | S26: =SUBTOTAL(109,P26:R26) -> 24.796654 | T26: 15.6 | U26: LPDDR5-315球8G | V26: 全功能(RTS5453H)；含TPM
A27: 2 | B27: DNP59（6L+通孔+OSP） | C27: 134.16*126.50*1.0mm | D27: 20251020 | E27: 6.75 | F27: A.F.M.2501664 | G27: SKU4 | H27: 单Type IC及Type C 单接口(RTS5453H) | I27: N-6W | J27: 4G*2+0 | K27: AX201.D2WG | L27: 现询 | M27: 选配 | N27: =18.5/E27/1.13*1.15 -> 2.7892494 | O27: 3.3224883 | P27: 3.6547371 | Q27: 16.9 | R27: 3.5749467 | S27: =SUBTOTAL(109,P27:R27) -> 24.129684 | T27: 14.3 | U27: LPDDR5X-315球4G | V27: ROM:128Mb
A28: 2 | B28: DNN11(8L+HDI+OSP) | C28: 166.3*107.9*1.0mm | D28: 20240116 | E28: 6.75 | F28: A.F.M.2301317-MP | G28: SKU7 | H28: 双Type C IC及双Type c接口(ANX7447QN/HUSB238) | I28: N-6W | J28: 0+0 | K28: AX201.D2WG | L28: 现询 | M28: 选配 | N28: =33.72/E28/1.13 -> 4.4208456 | O28: 5.2660073 | P28: 5.792608 | Q28: 16.6 | R28: =22.08/E28/1.13 -> 2.8947886 | S28: =SUBTOTAL(109,P28:R28) -> 25.287397 | T28: 14.72 | U28: 时创意/LPDDR5-496球16G? | V28: TPM:SLB 9672VU2.0; 电量计： CW2015CHBD； ROM:256Mb;
A29: 2 | B29: DNP15C(8L+HDI1+OSP) | C29: 142.0*109.2*0.8mm | D29: 20250508 | E29: 6.75 | F29: A.F.M.2500752-OOC | G29: SKU12 | H29: 双Type c(双Type C 接口) | I29: N350(7W) | J29: 16G+0 | K29: 9560.D2WG | L29: 现询 | M29: 选配 | N29: =21.71/E29/1.13 -> 2.8462799 | O29: 3.3904217 | P29: 3.7294638 | Q29: 16.7 | R29: =24.73/E29/1.13 -> 3.2422157 | S29: =SUBTOTAL(109,P29:R29) -> 23.671679 | T29: 13.9 | U29: LPDDR5-496球16G | V29: ROM:128Mb
A30: 2 | B30: DNS11(6L+通孔+OSP) | C30: 180.0*145.0*1.6mm | D30: 20251113 | E30: 6.75 | F30: A.F.M.2501021-MP | G30: SKU6 | H30: Type c(单Type C 接口)(VL162) | I30: N-6W | J30: 0+32G | K30: 61851BE | L30: 现询 | M30: 选配 | N30: =32.1/E30/1.13 -> 4.2084562 | O30: 5.0130141 | P30: 5.5143155 | Q30: 19 | R30: =25.96/E30/1.13 -> 3.4034743 | S30: =SUBTOTAL(109,P30:R30) -> 27.91779 | T30: 16.5 | U30: 群联 | V30: HDMI:IT66318FN; RJ45:RTL8125BG; ROM:128Mb
B31: DNNTUS(6L+通孔+OSP) | C31: 199.4*114.0*1.0mm | D31: 20250611 | E31: 6.75 | F31: A.F.M.2501038-MP | G31: SKU13 | H31: Type c(单Type C 接口)ANX7447QN | I31: N150(6W) | J31: 0+0 | K31: WD-RTL8821CE | L31: 现询 | M31: 选配 | N31: =22.67/E31/1.13 -> 2.9721403 | O31: 3.5403436 | P31: 3.8943779 | Q31: 17.5 | R31: =20.61/E31/1.13 -> 2.7020649 | S31: =SUBTOTAL(109,P31:R31) -> 24.096443 | T31: 12.33 | U31: 条子 | V31: 电量计：CW2015CHBD； ROM:128Mb ;
A32: 2 | B32: JN56(8L+通孔+OSP) | C32: 264.6*167.6*1.05mm | D32: 20251225 | E32: 6.75 | F32: A.F.M.2401298-OOC | G32: SKU11 | H32: 三TYPE C IC 及双Type c 接口(ANX7447QN&ANX7443QN&ANX7411QN) | I32: N-6W | J32: 2G*2+64G | K32: AX201.D2WG | L32: 现询 | M32: 选配 | N32: =25.5/E32/1.13 -> 3.3431662 | O32: 3.9823009 | P32: 4.380531 | Q32: 31 | R32: =19.47/E32/1.13 -> 2.5526057 | S32: =SUBTOTAL(109,P32:R32) -> 37.933137 | T32: 28 | U32: 条子 | V32: HDMI2.0:IT66318FN; ROM:128Mb
A33: 2 | B33: JN81S(6L+通孔+OSP) | C33: 190*114*1.0mm | D33: 20250306 | E33: 6.75 | F33: A.F.M.2500306-MP | G33: SKU8 | H33: Type c(单接口)（ANX7447QN） | I33: N-6W | J33: 0+0 | K33: 选配 | L33: 现询 | M33: 选配 | N33: =18.628/E33/1.13 -> 2.4422157 | O33: 2.9091098 | P33: 3.2000208 | Q33: 14.1 | R33: =20.36/E33/1.13 -> 2.6692888 | S33: =SUBTOTAL(109,P33:R33) -> 19.96931 | T33: 12.1 | U33: 条子 | V33: 电量计：CW2015CHBD； ROM:128Mb ;
A34: 2 | B34: JS6(8L+通孔+OSP) | C34: 170*125.5*1.6mm | D34: 46092 | E34: 6.75 | F34: A.F.M.2400516 | G34: SKU8 | H34: Type c(单接口) | I34: N-10W | J34: 0+32G | K34: 选配 | L34: 现询 | M34: 选配 | N34: =25.5/E34/1.13 -> 3.3431662 | O34: 3.9823009 | P34: 4.380531 | Q34: 24.15 | R34: =22.63/E34 -> 3.3525926 | S34: =SUBTOTAL(109,P34:R34) -> 31.883124 | T34: 22.65 | U34: 江波龙EMMC 32GB | V34: E-BOM,，含散热模组,INTEL网卡IC:I226-V,ROM:128Mb;
A35: 2 | B35: DNN25B(8L+HDI+OSP+HF) | C35: 188.1x99.2x1.0mm | D35: 46164 | E35: 6.75 | F35: A.F.M.260XXXX全配 | G35: SKU7 | H35: 双Type C IC及双Type c接口(ANX7447QN） | I35: N-15W | J35: 16GB+128 | K35: AX211.D2WG.NV | L35: 现询 | M35: 选配 | N35: =47/E35/1.13 -> 6.1619141 | O35: 7.3399271 | P35: =57.5/E35/1.13*1.05 -> 7.9154376 | Q35: 19.7 | R35: =21.5/E35 -> 3.1851852 | S35: =SUBTOTAL(109,P35:R35) -> 30.800623 | T35: 16.95 | U35: 16GB 496球+ EMMC 128 | V35: HDMI2.0 IT66318FN; TPM:SLB 9672; OLED :G2708CKU1U; 电量计：CW2217; ROM:128Mb ; SMT预估价
B36: DNN253(6L+通孔+OSP) | C36: 193.6x100.2x1mm | D36: 46248 | E36: 6.75 | F36: A.F.M.2602447低配 | G36: SKU1 | I36: N-15W | J36: 0+0 | K36: CDW-61852BE-00T | L36: - | M36: - | P36: =33.81/E36/1.13*1.05 -> 4.6542773 | Q36: 14.4 | R36: =18/E36 -> 2.6666667 | S36: =SUBTOTAL(109,P36:R36) -> 21.720944 | U36: 条子
N73: 12.5
M74: =32.2/E74/1.13 -> #DIV/0!
C110: MTP13(10L+OSP+通孔)
N112: =63.76/F112/1.13 -> #DIV/0!
N113: =63.76/F113/1.13 -> #DIV/0!
F129: SKU30 | N129: =37.88/D129/1.13 -> #DIV/0! | R129: 3.15 | T129: 19.29
N134: =32.97/D134/1.13 -> #DIV/0!
N193: =23.49+20/6.7739/1.13 -> 26.10284
L365: 现询
F366: A.F.M.2602447 | L366: 现询 | O366: 15.3
F384: A.F.M.2502750/A.F.M.2502879
A653: NZ126D | E653: A.F.D.2600315 | H653: 2.92 | J653: 9.82 | K653: 0.76 | N653: PCB为8-26日价格，持续上涨，实单前重新确认

Sheet E BOM小核 (2)
B1: 1月份汇率：7.01 | L1: 现询 | T1: pcb为普通材质OSP工艺，如用特殊材质请单独核;CPU;DDR;SSD;EMMC;WIFI请按需求选配 | U1: - | V1: 类型 | W1: 型号 | X1: 美金单项单价 | Z1: - | AA1: 类型 | AB1: 型号 | AC1: 美金单项单价
U2: - | V2: TYPEC IC | W2: ANX7447QN | X2: 0.64 | Z2: - | AA2: 加密IC TPM | AB2: 9672 | AC2: 1.05
U3: - | W3: CYPD6228 | X3: 1.7769148 | Z3: - | AA3: 电量计 | AB3: CW2217 | AC3: 0.23
U4: - | W4: CYPD6227 | X4: 1.8079 | Z4: - | AA4: 雷电IC | AB4: 8040 | AC4: 2.948
U5: - | W5: ASL2330AN | X5: 0.52 | Z5: - | AB5: 9040 | AC5: 3.054
W6: IT8856FN/CX | X6: 0.93
A7: 厂区 | B7: 机型 | C7: PCB尺寸 | D7: 日期 | E7: 更新汇率 | F7: 料号 | G7: SKU | H7: Type c | I7: 功率 | J7: 配置 | K7: WIFI | L7: CPU/存储 | M7: WIFI | N7: PCB | O7: Others | P7: SMT | Q7: 5/9更新(RMB含税) | R7: TTL | S7: DDR/SSD | T7: 备注
B8: GL2(VR眼镜)/50套预估价格 | D8: 20241009 | E8: 7.1 | F8: A.F.M.2401739 | G8: SKU1 | H8: - | I8: - | J8: - | K8: - | L8: - | M8: - | N8: =11.56/E8/1.13 -> 1.4408575 | O8: 14.036821 | P8: =6800/7.13/1.13/50 -> 16.879941 | R8: =SUM(L8:P8) -> 32.357619 | T8: 数量少按此前一批估算 试产费用预估6800￥，平摊50套。含VL822；未算上14颗客供料的成本；含龙讯HDMI2.0用量1颗，含连接器502244-1530 两个用量；PCB分两个工艺价格，8.56无树塞/11.26按树脂塞孔(二种报价都写上),EQ上有表明二种工艺,此项按树脂塞孔核算
D9: 20241009 | E9: 7.1 | F9: A.F.D.2400256 | G9: A.F.D.2400256 SENSOR DB | H9: - | I9: - | J9: - | K9: - | L9: - | M9: - | N9: =0.57/7.1/1.13 -> 0.071045743 | O9: 0.00028792222 | P9: 0.2 | R9: =SUM(L9:P9) -> 0.27133367 | T9: 含客供料OPT101P-J | U9: .
D10: 20241009 | E10: 7.1 | F10: A.F.D.2400258 | G10: A.F.D.2400258 KEY DB | H10: - | I10: - | J10: - | K10: - | L10: - | M10: - | N10: =2.24/7.1/1.13 -> 0.27919731 | O10: 0.12650256 | P10: 0.2 | R10: =SUM(L10:P10) -> 0.60569986 | U10: .
D11: 20241009 | E11: 7.1 | F11: A.F.D.2400257 | G11: A.F.D.2400257 PIC18F14K50 DB | H11: - | I11: - | J11: - | K11: - | L11: - | M11: - | N11: =1.2/E11/1.13 -> 0.14956999 | O11: 5.2902151 | P11: =1130/7.13/1.13/50 -> 2.8050491 | R11: =SUM(L11:P11) -> 8.2448342 | T11: 数量少按此前一批估算 试产费用预估1150￥，平摊50套,cpu含PIC18F14K50-I/SO，PIC18F14K50-I/SO目前现货价格是40 | U11: .
B12: 预估PST价格 | D12: 20250915 | E12: 7.13 | G12: SU_PST_LAN_DB_V10_250915A | N12: =3/E12/1.13 -> 0.37235165 | O12: 2.1992851 | P12: 0.3 | R12: =SUBTOTAL(9,J12:P12) -> 2.8716368 | T12: PCB用E.P.P.0002088预估
B13: 预估PST价格 | D13: 20250915 | E13: 7.13 | G13: SU_PST_LED_DB_V10_250915A | N13: =1.25/E13/1.13*1.05 -> 0.16290385 | O13: 0.065965818 | P13: 0.3 | R13: =SUBTOTAL(9,J13:P13) -> 0.52886966 | T13: PCB用E.P.P.0004934预估
B14: 预估PST价格 | D14: 20250915 | E14: 7.13 | G14: SU_PST_U3+SD_DB_V10_250915A | N14: =3/E14/1.13 -> 0.37235165 | O14: 1.3500903 | P14: 0.3 | R14: =SUBTOTAL(9,J14:P14) -> 2.022442 | T14: PCB用E.P.P.0002088预估
B15: 预估PST价格 | D15: 20250915 | E15: 7.13 | G15: SU_PST_WCL-U_MB_V10_250915 | N15: =25.21/E15/1.13*1.05 -> 3.2854448 | O15: 19.248546 | P15: 3.5 | R15: =SUBTOTAL(9,J15:P15) -> 26.033991 | T15: PCB用DN253预估E.P.P.0006645；
B16: DNNTU146(4L+通孔+OSP) | D16: 20250806 | E16: 6.9667 | F16: A.F.M.2501936-PVT | G16: SKU3 | H16: Type c(l两个Type C 接口)(ANX7447QN) | I16: N-6W | J16: 0+0 | K16: 原RTL8821CE待更新 | L16: 现询 | M16: 1.66 | N16: 2.7399623 | O16: 8.733728 | P16: 2.3525314 | R16: 15.486222 | S16: 全功能（ANX7447QN）； | T16: 全功能（ANX7447QN）；
B17: DNNTU146(4L+通孔+OSP) | D17: 20250806 | E17: 6.9667 | F17: A.F.M.2501938 | G17: SKU5 | H17: Type c(l两个Type C 接口)(ANX7447QN) | I17: N-15W | J17: 0+0 | K17: 8852BE | L17: 现询 | M17: =26.17/E17/1.13 -> 3.3242844 | N17: 2.7399623 | O17: 9.3075577 | P17: 2.3525314 | R17: 17.724336 | S17: 全功能（ANX7447QN）； | T17: 全功能（ANX7447QN）；
B18: DNNTU146(4L+通孔+OSP) | D18: 46079 | E18: 6.8802 | F18: A.F.M.2502429 | G18: SKU7 | H18: 无TYPE-C IC,l两个Type C 接口) | K18: 8821 SMD | M18: =13.3/E18/1.13 -> 1.7106932 | N18: =21.4/E18/1.13 -> 2.752544 | O18: 9.31 | P18: 2.35 | R18: =SUM(M18:P18) -> 16.123237
B19: DNP15C | D19: 20250508 | E19: 7.13 | F19: A.F.M.2500752-OOC | G19: SKU12 | H19: 双Type c(两个Type C 接口) | I19: N-7W | J19: 16G+0 | K19: 9560.D2WG | L19: 选配 | M19: 2.3 | N19: 2.6945848 | O19: 12.03773 | P19: 3.0694188 | R19: =SUM(L19:P19) -> 20.101733 | S19: LPDDR5-496球16G | T19: 双Type C IC及两个Type c接口；DDR使用镁光暂无价格;ALC269Q;IT5570E;MP2964GQKT;
B20: DNN25（6L+通孔+OSP） | D20: 20250901 | E20: 7.13 | G20: 全配 | H20: 双Type C IC及两个Type c接口(ANX7447QN) | I20: N-15W | J20: 0+0 | K20: - | L20: 缺货 | M20: 按需选配 | N20: =17.692/E20/1.13 -> 2.1958818 | O20: =11.5887894468418 -> 11.588789 | P20: 3 | R20: =SUM(L20:P20) -> 16.784671 | S20: LPDDR5-315球8G*2(江波龙) | T20: 全功能（ANX7447QN）；含有加密IC TPM(9672)；
B21: DNNXU(6L+通孔+OSP) | D21: 20250904 | E21: 7.13 | F21: A.F.M.2401762 | G21: SKU13 | H21: 单Tpye c IC及一个Type c接口（ANX7447QN） | I21: N-15W | J21: 0+0 | M21: 按需选配 | N21: =17/E21/1.13 -> 2.1099927 | O21: =42.7/E21/1.13 -> 5.2998051 | P21: 28.5 | Q21: 19.77 | R21: =SUM(L21:P21) -> 35.909798 | S21: 条子 | T21: 全功能（ANX7447QN）
D23: 20250909 | E23: 7.13 | F23: A.F.M.2500505-MP | G23: SKU16 | H23: Type c(两个Type c个接口)（ANX7447QN） | I23: N-6W | J23: 0+0 | M23: 选配 | N23: =23.5/E23/1.13 -> 2.9167546 | O23: 11.496677 | P23: =Q23/E23/1.13 -> 2.494756 | Q23: 20.1 | R23: =SUM(L23:P23) -> 16.908187 | S23: 条子 | T23: ,PCB沿用ARNIU146B的pcb价格（科翔最便宜价），.单Typec(两个Type c接口)6600H，0thers部分用ARNTU146 sku4评估，smt待正式量产后确认最新核价
B24: DNN21(8L+HDI1+OSP) | D24: 20250909 | E24: 7.13 | F24: A.F.M.2401219-MP | G24: SKU9 | H24: 单Type c IC及一个Type c 接口（ANX7447QN） | I24: N-15W | J24: 0+0 | N24: =67.01/E24/1.13 -> 8.3170947 | O24: 10.222436 | P24: =Q24/E24/1.13 -> 3.0321836 | Q24: 24.43 | R24: =SUM(L24:P24) -> 21.571715 | S24: LPDDR5-496球16G | T24: 全功能（ANX7447QN）;含CW2015CHBD
B25: DNP13C（6L+通孔+OSP） | C25: 211.7*102.0*1.0MM | D25: 46078 | E25: 6.8802 | F25: A.F.M.2502098 | G25: SKU17 | H25: 双Type c IC(两个Type C 接口)(ANX7447QN) | I25: N-15W | J25: 0+0 | K25: 按需选配 | L25: 按需选配 | M25: 按需选配 | N25: =26.56/E25/1.13 -> 3.4162415 | O25: =1.05+13.58165475074 -> 14.631655 | P25: =21.72/E25/1.13 -> 2.7937035 | R25: =SUBTOTAL(9,J25:P25) -> 20.8416 | S25: LPDDR5X-315球4G*2 | T25: 全功能(ANX7447QN);含加密IC TPM;
B26: DNP13C（6L+通孔+OSP） | C26: 211.7*102.0*1.0MM | D26: 46275 | E26: 6.72 | F26: A.F.M.2601374 | K26: - | L26: 现询 | M26: - | N26: =38.12/E26/1.13 -> 5.0200169 | O26: 16.9 | P26: =21.72/E26/1.13 -> 2.8603034 | R26: =SUBTOTAL(9,J26:P26) -> 24.78032
B27: DNP13C（6L+通孔+OSP） | C27: 211.7*102.0*1.0MM | D27: 46049 | E27: 6.8802 | F27: A.F.M.2500159 | G27: SKU9 PVT | H27: 双Type c IC(两个Type C 接口)(ANX7447QN) | I27: N-15W | J27: 0+0 | K27: 选配 | L27: 选配 | M27: 选配 | N27: =26.56/E27/1.13 -> 3.4162415 | O27: 14.1 | P27: =21.72/E27/1.13 -> 2.7937035 | R27: =SUBTOTAL(9,J27:P27) -> 20.309945 | S27: LPDDR5X-315球4G*2 | T27: 全功能(ANX7447QN);电量计bq24715RGRR
B28: DNP13C（6L+通孔+OSP） | C28: 211.7*102.0*1.0MM | E28: 6.7693 | F28: A.F.M.2500154 | N28: =26.56/E28/1.13 -> 3.4722091 | O28: 15.3 | P28: =21.72/E28/1.13 -> 2.8394722
B29: DNN21F(8L+HDI1+OSP) | C29: 214.5mm*120.0mm*1.0 | D29: 46134 | E29: 6.8225 | F29: A.F.M.2401659 | G29: SKU1 | H29: 单TYPE-C IC+单TYPE-C座 | I29: 6W | J29: - | K29: - | L29: 现询 | M29: - | N29: =22.94/E29/1.13 -> 2.9755786 | O29: 10.6 | P29: 2.61 | R29: =SUBTOTAL(109,N29:P29) -> 16.185579 | S29: 条子
B30: DNN21F(8L+HDI1+OSP) | C30: 214.5mm*120.0mm*1.0 | D30: 20250910 | E30: 7.13 | F30: A.F.M.2402477-PVT | G30: SKU6 | H30: Type c(l两个Type C 接口)(ANX7447QN) | I30: N355(15w) | J30: 0+128G | K30: - | L30: 缺货 | M30: - | N30: =22.14/E30/1.13 -> 2.7479552 | O30: 12.535711 | P30: 2.6050675 | R30: =SUBTOTAL(9,J30:P30) -> 17.888733 | S30: 群联/条子 | T30: 全功能(ANX7447QN);含加密IC TPM;
B31: GN10B | D31: 46081 | E31: 6.8802 | G31: SKU50 | I31: 6W | L31: 客供 | M31: 现询 | N31: =16.9/E31/1.13 -> 2.173738 | O31: 7.17 | P31: =20.45/E31/1.13 -> 2.6303516 | R31: =SUBTOTAL(9,J31:P31) -> 11.97409
B32: DNN81S(6L+通孔+OSP) | D32: 20250912 | E32: 7.13 | F32: A.F.M.2402361-OOC3 | G32: SKU6 | H32: Type Ic(一个Type c 接口)ANX7447QN | I32: N-6W | J32: 0+0 | N32: =20.2954/E32/1.13 -> 2.5190086 | O32: 10.355818 | P32: 16 | Q32: 18.6 | R32: =SUM(L32:P32) -> 28.874827 | U32: TYPE-C:ANX7447QN-AC-R,电量计:CW2217,视频桥接：IT6113FN
B33: DNN81S(6L+通孔+OSP)
B34: DNA10(8L+通孔+OSP) | E34: 7.17 | G34: SKU2 | H34: Non Type c | I34: N95(15W) | J34: - | K34: - | L34: 缺货 | M34: - | N34: 2.5660728 | O34: 14.248904 | P34: =Q34/E34/1.13 -> 2.5857494 | Q34: 20.95 | R34: =SUM(L34:P34) -> 19.400726 | S34: 条子
E35: 7.17 | G35: SKU3 | H35: Non Type c | I35: N100(6W) | J35: - | K35: - | L35: 缺货 | M35: - | N35: 2.5660728 | O35: 13.76343 | P35: =Q35/E35/1.13 -> 2.5857494 | Q35: 20.95 | R35: =SUM(L35:P35) -> 18.915253 | S35: 条子 | T35: 含加密IC TPM
D36: 20240423 | E36: 7.17 | F36: A.F.M.2400614-MP | G36: SKU4 | H36: Non Type c | I36: N95(15W) | J36: - | K36: - | L36: 缺货 | M36: - | N36: 2.5660728 | O36: 12.991924 | P36: =Q36/E36/1.13 -> 2.5857494 | Q36: 20.95 | R36: =SUM(L36:P36) -> 18.143747 | S36: 条子 | T36: 含有RTL8111H；含有ALC897
D37: 20240529 | E37: 7.17 | F37: A.F.M.2400832-MP | G37: SKU5 | H37: Non Type c | I37: N95(15W) | J37: - | K37: - | L37: 缺货 | M37: - | N37: 2.5660728 | O37: 13.193476 | P37: =Q37/E37/1.13 -> 2.5857494 | Q37: 20.95 | R37: =SUM(L37:P37) -> 18.345298 | S37: 条子 | T37: 含有RTL8111H；含有ALC897
B38: DNN21S | D38: 20240221 | E38: 7.17 | F38: A.F.M.2300280-MP | G38: SKU12 | H38: Type c | I38: N305(15W) | J38: 0+0 | K38: - | L38: 缺货 | M38: - | N38: =25.7/E38/1.13 -> 3.1720171 | O38: 11.857598 | P38: =Q38/E38/1.13 -> 2.6042631 | Q38: 21.1 | R38: =SUM(L38:P38) -> 17.633878 | S38: 条子 | T38: 单Type C | U38: .
D39: 20250901 | E39: 7.13 | F39: A.F.M.2302171-MP | G39: SKU22 | H39: 单Tpye c IC及一个Type c接口（ANX7447QN） | I39: N-15W | J39: 0+128G | K39: - | L39: 缺货 | M39: - | N39: =25.7/E39/1.13 -> 3.1898125 | O39: =12.4 -> 12.4 | P39: =Q39/E39/1.13 -> 2.6188733 | Q39: 21.1 | R39: =SUM(L39:P39) -> 18.208686 | S39: 条子 | T39: 全功能（ANX7447QN）;含加密IC TPM 9672；
E40: 7.17 | F40: A.F.M.2503122 | G40: SKU13 | H40: Type c | I40: N95(15W) | J40: 0+0 | K40: - | L40: 缺货 | M40: - | N40: =25.7/E40/1.13 -> 3.1720171 | O40: 13.13532 | P40: =Q40/E40/1.13 -> 2.6042631 | Q40: 21.1 | R40: =SUM(L40:P40) -> 18.911601 | S40: 条子 | T40: 单Type C | U40: .
E41: 7.17 | F41: A.F.M.2300627-MP | G41: SKU14 | H41: Non Type c | I41: N200(6W) | J41: 0+0 | K41: - | L41: 缺货 | M41: - | N41: =25.7/E41/1.13 -> 3.1720171 | O41: 12.483317 | P41: =Q41/E41/1.13 -> 2.6042631 | Q41: 21.1 | R41: =SUM(L41:P41) -> 18.259597 | S41: 条子 | U41: .
E42: 6.91 | F42: A.F.M.2600110 | G42: SKU17 | H42: Type c | I42: N200(6W) | J42: 0+0 | K42: - | L42: 缺货 | M42: - | N42: =25.7/E42/1.13 -> 3.2913694 | O42: 11.403644 | P42: =Q42/E42/1.13 -> 2.7022527 | Q42: 21.1 | R42: =SUM(L42:P42) -> 17.397266 | S42: 条子 | T42: 单Type C | U42: .
D43: 20240110 | E43: 7.17 | F43: A.F.M.2301957-MP | G43: SKU18 | H43: Non Type c | I43: N95(15W) | J43: 0+0 | K43: - | L43: 缺货 | M43: - | N43: =25.7/E43/1.13 -> 3.1720171 | O43: 11.184748 | P43: =Q43/E43/1.13 -> 2.6042631 | Q43: 21.1 | R43: =SUM(L43:P43) -> 16.961028 | S43: 条子 | U43: .
D44: 20240517 | E44: 7.17 | F44: A.F.M.2302080-MP | G44: SKU19 | H44: Type c(2个TYPE接口) | I44: N100(6W) | J44: 0+0 | K44: - | L44: 缺货 | M44: - | N44: =25.7/E44/1.13 -> 3.1720171 | O44: 11.339239 | P44: =Q44/E44/1.13 -> 2.6042631 | Q44: 21.1 | R44: =SUM(L44:P44) -> 17.115519 | S44: 条子 | T44: 单Type C | U44: .
D45: 20240112 | E45: 7.17 | F45: A.F.M.2302170-MP | G45: SKU21 | H45: Type c | I45: N100(6W) | J45: 0+0 | K45: - | L45: 缺货 | M45: - | N45: =25.7/E45/1.13 -> 3.1720171 | O45: 12.013331 | P45: =Q45/E45/1.13 -> 2.6042631 | Q45: 21.1 | R45: =SUM(L45:P45) -> 17.789612 | S45: 条子 | T45: 单Type C | U45: .
D46: 20240112 | E46: 7.17 | F46: A.F.M.2302171-MP | G46: SKU22 | H46: Type c | I46: N95(15W) | J46: 0+128G | K46: - | L46: 缺货 | M46: - | N46: =25.7/E46/1.13 -> 3.1720171 | O46: =31.73/7.13/1.13 -> 3.9382393 | P46: =Q46/E46/1.13 -> 0.41975146 | Q46: =23.5/6.91 -> 3.4008683 | R46: =SUM(L46:P46) -> 7.5300079 | S46: 江波龙/条子 | T46: 单Type C;含有加密IC TPM | U46: .
D47: 20241120 | E47: 7.17 | F47: A.F.M.2302172-MP | G47: SKU23 | H47: Type c（1个TYPE接口) | I47: N100(6W) | J47: 0+128G | L47: 缺货 | N47: =25.7/E47/1.13 -> 3.1720171 | O47: 10.390721 | P47: =Q47/E47/1.13 -> 0.41975146 | Q47: =23.5/6.91 -> 3.4008683 | R47: =SUM(L47:P47) -> 13.982489 | S47: 群联/条子 | T47: 单Type C及一个type c接口；IT5570E；MP2964GQKT；ANX7447QN
D48: 20241012 | E48: 7.17 | F48: A.F.M.2400176-MP | G48: SKU26 | H48: Non Type c(2个TYPE接口) | I48: N97(12W) | J48: 0+0 | K48: - | L48: 缺货 | M48: - | N48: =25.7/E48/1.13 -> 3.1720171 | O48: =31.73/E48/1.13 -> 3.9162686 | P48: =Q48/E48/1.13 -> 0.41975146 | Q48: =23.5/6.91 -> 3.4008683 | R48: =SUM(L48:P48) -> 7.5080372 | S48: 条子 | T48: 2个Type C接口；含MP86941 | U48: .
D49: 20240417 | E49: 7.17 | F49: A.F.M.2400339-MP | G49: SKU28 | H49: Type c | I49: N100(6W) | J49: 0+0 | K49: - | L49: 缺货 | M49: - | N49: =25.7/E49/1.13 -> 3.1720171 | O49: =31.73/E49/1.13 -> 3.9162686 | P49: =Q49/E49/1.13 -> 0.41975146 | Q49: =23.5/6.91 -> 3.4008683 | R49: =SUM(L49:P49) -> 7.5080372 | S49: 条子 | T49: 单Type C
D50: 20241120 | E50: 7.17 | F50: A.F.M.2400453-OOC | G50: SKU29 | H50: Type c | I50: N100(6W) | J50: 0+128G | K50: - | L50: 缺货 | M50: - | N50: =25.7/E50/1.13 -> 3.1720171 | O50: 10.82618 | P50: =Q50/E50/1.13 -> 2.6042631 | Q50: 21.1 | R50: =SUM(L50:P50) -> 16.60246 | S50: 群联/条子 | T50: 单Type C
D51: 46126 | E51: 6.837 | F51: A.F.M.2503232 | G51: SKU69 | N51: =25.7/E51/1.13 -> 3.326512 | O51: 10.88 | P51: =21.1/E51/1.13 -> 2.7311052 | R51: =SUM(L51:P51) -> 16.937617 | T51: PCB上涨中，实单前确认
D52: 46081 | E52: 6.8802 | F52: A.F.M.2400454-OOC | G52: SKU30 | H52: Type c | I52: N95(15W) | J52: 0+0 | K52: - | L52: 缺货 | M52: - | N52: =25.7/E52/1.13 -> 3.3056252 | O52: 11.29851 | P52: =Q52/E52/1.13 -> 2.7139569 | Q52: 21.1 | R52: =SUM(L52:P52) -> 17.318092 | S52: 条子 | T52: 单Type C及一个type c接口；16TQC33MYFB
D53: 46081 | E53: 6.8802 | F53: A.F.M.2400543-MP | G53: SKU31 | H53: Non Type c | I53: N97(12W) | J53: 0+0 | K53: - | L53: 缺货 | M53: - | N53: =25.7/E53/1.13 -> 3.3056252 | O53: 10.810835 | P53: =Q53/E53/1.13 -> 2.7139569 | Q53: 21.1 | R53: =SUM(L53:P53) -> 16.830417 | S53: 条子
D54: 20240508 | E54: 7.17 | F54: A.F.M.2400668-MP | G54: SKU32 | H54: Type c | I54: N100(6W) | J54: 0+0 | K54: - | L54: 缺货 | M54: - | N54: =25.7/E54/1.13 -> 3.1720171 | O54: 11.365767 | P54: =Q54/E54/1.13 -> 2.6042631 | Q54: 21.1 | R54: =SUM(L54:P54) -> 17.142047 | S54: 条子 | T54: 单Type C
D55: 20240508 | E55: 7.17 | F55: A.F.M.2400677-MP | G55: SKU33 | H55: Type c | I55: N100(6W) | J55: 0+0 | K55: - | L55: 缺货 | M55: - | N55: =25.7/E55/1.13 -> 3.1720171 | O55: 12.385055 | P55: =Q55/E55/1.13 -> 2.6042631 | Q55: 21.1 | R55: =SUM(L55:P55) -> 18.161335 | S55: 条子 | T55: 单Type C；含有加密IC TPM
D56: 20240612 | E56: 7.17 | F56: A.F.M.2400872-MP | G56: SKU34 | H56: Non Type c | I56: N100(6W) | J56: 0+0 | K56: - | L56: 缺货 | M56: - | N56: =25.7/E56/1.13 -> 3.1720171 | O56: 9.0525529 | P56: =Q56/E56/1.13 -> 2.6042631 | Q56: 21.1 | R56: =SUM(L56:P56) -> 14.828833 | S56: 条子 | T56: 含有ALC269Q
D57: 20241012 | E57: 7.17 | F57: A.F.M.2501978 | G57: SKU35 | H57: Non Type c(2个TYPE接口) | I57: N97(12W) | J57: 0+0 | K57: - | L57: 缺货 | M57: - | N57: =25.7/E57/1.13 -> 3.1720171 | O57: 10.539174 | P57: =Q57/E57/1.13 -> 2.6042631 | Q57: 21.1 | R57: =SUM(L57:P57) -> 16.315454 | S57: 条子 | T57: 2个Type C接口；含MP86941
D58: 20241012 | E58: 6.9264 | F58: A.F.M.2502465 | G58: SKU36 | H58: Non Type c(2个TYPE接口) | I58: N97(12W) | J58: 0+0 | K58: - | L58: 缺货 | M58: - | N58: =25.7/E58/1.13 -> 3.2835763 | O58: 10.494565 | P58: 21.9 | Q58: 21.1 | R58: =SUM(L58:P58) -> 35.678142 | S58: 条子 | T58: 2个Type C接口；含MP86941
D59: 20240710 | E59: 7.17 | F59: A.F.M.2400957-MP | G59: SKU37 | H59: Type c | I59: N100(6W) | J59: 0+0 | K59: - | L59: 缺货 | M59: - | N59: =25.7/E59/1.13 -> 3.1720171 | O59: 10.544232 | P59: =Q59/E59/1.13 -> 2.6042631 | Q59: 21.1 | R59: =SUM(L59:P59) -> 16.320512 | S59: 条子 | T59: 单Type C
D60: 20240710 | E60: 7.17 | F60: A.F.M.2400958-MP | G60: SKU38 | H60: Type c | I60: N95(15W) | J60: 0+0 | K60: - | L60: 缺货 | M60: - | N60: =25.7/E60/1.13 -> 3.1720171 | O60: 12.44092 | P60: =Q60/E60/1.13 -> 2.6042631 | Q60: 21.1 | R60: =SUM(L60:P60) -> 18.2172 | S60: 条子 | T60: 单Type C;含有加密IC TPM
D61: 20240725 | E61: 7.17 | F61: A.F.M.2400998-MP | G61: SKU39 | H61: Type c | I61: N100(6W) | J61: 0+0 | K61: - | L61: 缺货 | M61: - | N61: =25.7/E61/1.13 -> 3.1720171 | O61: 10.703595 | P61: =Q61/E61/1.13 -> 2.6042631 | Q61: 21.1 | R61: =SUM(L61:P61) -> 16.479875 | S61: 条子 | T61: 单Type C IC及一个Type c 接口；
D62: 20240809 | E62: 7.17 | F62: A.F.M.2401071-MP | G62: SKU40 | H62: Type c(一个Type c 接口) | I62: N100(6W) | J62: 0+0 | K62: - | L62: 缺货 | M62: - | N62: =25.7/E62/1.13 -> 3.1720171 | O62: 10.065561 | P62: =Q62/E62/1.13 -> 2.6042631 | Q62: 21.1 | R62: =SUM(L62:P62) -> 15.841841 | S62: 条子 | T62: 单Type C IC及一个Type c 接口；
D63: 20240809 | E63: 7.17 | F63: A.F.M.2401090-MP | G63: SKU41 | H63: Non Type c(一个Type c 接口) | I63: N95(15W) | J63: 0+0 | K63: - | L63: 缺货 | M63: - | N63: =25.7/E63/1.13 -> 3.1720171 | O63: 10.459877 | P63: =Q63/E63/1.13 -> 2.6042631 | Q63: 21.1 | R63: =SUM(L63:P63) -> 16.236157 | S63: 条子 | T63: 无Type IC及Type C 一个Type c 接口；
D64: 20240809 | E64: 7.17 | F64: A.F.M.2401099-MP | G64: SKU42 | H64: Non Type c(一个Type c 接口) | I64: N100(6W) | J64: 0+0 | K64: - | L64: 缺货 | M64: - | N64: =25.7/E64/1.13 -> 3.1720171 | O64: 9.6983001 | P64: =Q64/E64/1.13 -> 2.6042631 | Q64: 21.1 | R64: =SUM(L64:P64) -> 15.47458 | S64: 条子 | T64: 无Type IC及Type C 一个Type c 接口；
D65: 20240809 | E65: 7.17 | F65: A.F.M.2401212-OOC | G65: SKU43 | H65: Type c(一个Type c 接口) | I65: N355 | J65: 0+0 | K65: - | L65: - | M65: - | N65: =25.7/E65/1.13 -> 3.1720171 | O65: 10.641331 | P65: =Q65/E65/1.13 -> 2.6042631 | Q65: 21.1 | R65: =SUM(L65:P65) -> 16.417612 | S65: 条子 | T65: CPU目前无价格；单Type C IC及一个Type c 接口；
D66: 20240809 | E66: 7.17 | F66: A.F.M.2401213-OOC | G66: SKU44 | H66: Type c(一个Type c 接口) | I66: N150(Q56Z) | J66: 0+0 | K66: - | L66: 缺货 | M66: - | N66: =25.7/E66/1.13 -> 3.1720171 | O66: 10.118722 | P66: =Q66/E66/1.13 -> 2.6042631 | Q66: 21.1 | R66: =SUM(L66:P66) -> 15.895002 | S66: 条子 | T66: 单Type C IC及一个Type c 接口；
D67: 20250219 | E67: 7.17 | F67: A.F.M.2401242-MP | G67: SKU45 | H67: Type c(一个Type c 接口) | I67: N100(6W) | J67: 0+128G | K67: - | L67: 缺货 | M67: - | N67: =25.7/E67/1.13 -> 3.1720171 | O67: 10.270698 | P67: =Q67/E67/1.13 -> 2.6042631 | Q67: 21.1 | R67: =SUM(L67:P67) -> 16.046978 | S67: 群联/条子 | T67: 单Type C IC及一个Type c 接口；
D68: 20250423 | E68: 7.17 | F68: A.F.M.2401501-MP | G68: SKU46 | H68: Type c(两个Type c 接口) | I68: N100(6W) | J68: 0+0 | K68: - | L68: 缺货 | M68: - | N68: =25.7/E68/1.13 -> 3.1720171 | O68: 10.033735 | P68: =Q68/E68/1.13 -> 2.6042631 | Q68: 21.1 | R68: =SUM(L68:P68) -> 15.810015 | S68: 条子 | T68: 单Type C IC及两个Type c 接口；MP86941*2pcs;IT5570E
D69: 20241012 | E69: 7.17 | F69: A.F.M.2401569-MP | G69: SKU47 | H69: Type c(两个Type c 接口) | I69: N100(6W) | J69: 0+0 | K69: - | L69: 缺货 | M69: - | N69: =25.7/E69/1.13 -> 3.1720171 | O69: 11.014055 | P69: =Q69/E69/1.13 -> 2.6042631 | Q69: 21.1 | R69: =SUM(L69:P69) -> 16.790335 | S69: 条子 | T69: 单Type C IC及两个Type c 接口；含ANX7447QN；MP2964GQKT；MP2964GQKT
D70: 202401017 | E70: 7.17 | F70: A.F.M.2401782-MP | G70: SKU48 | H70: Type c(两个Type c 接口) | I70: N200(6W) | J70: 0+0 | K70: - | L70: 缺货 | M70: - | N70: =25.7/E70/1.13 -> 3.1720171 | O70: 12.646576 | P70: =Q70/E70/1.13 -> 2.6042631 | Q70: 21.1 | R70: =SUM(L70:P70) -> 18.422856 | S70: 条子 | T70: 单Type C IC及两个Type c 接口；含有加密IC TPM;MP86941
D71: 20241115 | E71: 7.17 | F71: A.F.M.2402047-MP | G71: SKU52 | H71: Type c(两个Type c 接口) | I71: N100(6W) | J71: 0+0 | K71: - | L71: 缺货 | M71: - | N71: =25.7/E71/1.13 -> 3.1720171 | O71: 10.373249 | P71: =Q71/E71/1.13 -> 2.6042631 | Q71: 21.1 | R71: =SUM(L71:P71) -> 16.14953 | S71: 条子 | T71: 单Type C IC及两个Type c 接口；MP2964GQKT-0083;MP86941*2pcs；SN6140.板子用OSP工艺
D72: 20250812 | E72: 7.17 | F72: A.F.M.2500704-MP | G72: SKU54 | H72: Type c(一个Type c 接口) | I72: N150(6W) | J72: 0+0 | L72: 缺货 | N72: =25.7/E72/1.13 -> 3.1720171 | O72: 10.975199 | P72: =Q72/E72/1.13 -> 2.6042631 | Q72: 21.1 | R72: =SUM(L72:P72) -> 16.751479 | S72: 条子 | T72: 单Type C IC及一个Type c 接口；ALC269Q;MP86941*2pcs；IT5570E;板子用OSP工艺
D73: 20250508 | E73: 7.17 | F73: A.F.M.2500787-MP | G73: SKU55 | H73: 双Type c(两个Type c 接口) | I73: N150(6W) | J73: 0+0 | L73: 缺货 | N73: =25.7/E73/1.13 -> 3.1720171 | O73: 10.905425 | P73: =Q73/E73/1.13 -> 2.6042631 | Q73: 21.1 | R73: =SUM(L73:P73) -> 16.681705 | S73: 条子 | T73: 双Type C IC及两个Type c 接口;ALC269Q;MP86941*3pcs;IT5570E;MP2964GQKT-0084
D74: 20250508 | E74: 7.17 | F74: A.F.M.2500869-MP_for CKD | G74: SKU56(CKD) | H74: 双Type c(两个Type c 接口) | I74: N100(6W) | J74: 0+0 | L74: 缺货 | N74: =25.7/E74/1.13 -> 3.1720171 | O74: 10.292925 | P74: =Q74/E74/1.13 -> 2.6042631 | Q74: 21.1 | R74: =SUM(L74:P74) -> 16.069205 | S74: 条子 | T74: 双Type C IC及两个Type c 接口;ALC269Q;MP86941*2pcs;IT5570E;MP2964GQKT-0084
D75: 20250508 | E75: 7.17 | F75: A.F.M.2500870 | G75: SKU57(CKD) | H75: 双Type c(两个Type c 接口) | I75: N150(6W) | J75: 0+0 | L75: 缺货 | N75: =25.7/E75/1.13 -> 3.1720171 | O75: 10.836103 | P75: =Q75/E75/1.13 -> 2.6042631 | Q75: 21.1 | R75: =SUM(L75:P75) -> 16.612383 | S75: 条子 | T75: 双Type C IC及两个Type c 接口;ALC269Q;MP86941*3pcs;IT5570E;MP2964GQKT-0084
D76: 20250704 | E76: 7.17 | F76: A.F.M.2501223-MP | G76: SKU63 | H76: 双Type c(两个Type c 接口) | I76: N150(6W) | J76: 0+0 | K76: - | L76: - | M76: - | N76: 12.5 | O76: 10.836103 | P76: =Q76/E76/1.13 -> 2.6042631 | Q76: 21.1 | R76: =SUM(L76:P76) -> 25.940366 | S76: 条子 | T76: 双Type C IC及两个Type c 接口;SN6140;MP86941*3pcs;MP2964GQKT;
D77: 46052 | E77: 6.9591 | F77: A.F.M.2502025 | G77: SKU64 | H77: 双Type c(两个Type c 接口) | I77: N150(6W) | J77: 0+0 | K77: - | L77: - | M77: =32.2/E77/1.13 -> 4.0947213 | N77: =25.7/E77/1.13 -> 3.2681472 | O77: 12.21 | P77: =Q76/E77/1.13 -> 2.683187 | R77: =SUM(L77:P77) -> 22.256055 | T77: 双Type C IC及两个Type c 接口;SN6140;MP86941*3pcs;MP2964GQKT;
D78: 20250423 | E78: 7.17 | F78: A.F.D.2300314-EVT | G78: A.F.D.2300314 USB DB 爆款不带RJ45小板 | N78: 0.43334524 | O78: 1.0432459 | P78: 0.2 | R78: =SUM(L78:P78) -> 1.6765912 | U78: .
F79: A.P.10000993 | G79: A.P.10000993 USB DB | N79: 0.3797316 | O79: 1.5973382 | P79: 0.2 | R79: =SUM(L79:P79) -> 2.1770698 | U79: .
B80: DNN20A(8L+HDI1+OSP) | D80: 20240410 | E80: 7.17 | F80: A.F.M.2302353-MP | G80: SKU5 | H80: Type c | I80: N100(6W) | J80: 8G+0 | K80: AX101.D2WG | L80: 缺货 | M80: 3.1 | N80: 3.2378995 | O80: 13.812204 | P80: =Q80/E80/1.13 -> 2.9412128 | Q80: 23.83 | R80: =SUM(L80:P80) -> 23.091316 | S80: LPDDR5-496球8G | T80: DDR使用Spectek暂无价格；双Type c;
D81: 20240422 | E81: 7.17 | F81: A.F.M.2400596-MP | G81: SKU6 | H81: Type c | I81: N100(6W) | J81: 12G+0 | K81: AX101.D2WG | L81: 缺货 | M81: 3.1 | N81: 3.2334272 | O81: 13.779676 | P81: =Q81/E81/1.13 -> 2.9412128 | Q81: 23.83 | R81: =SUM(L81:P81) -> 23.054316 | S81: LPDDR5X-496球12G | T81: DDR使用Spectek；双Type c;
D82: 20250401 | E82: 7.17 | F82: A.F.M.2500483-OOC | G82: SKU7 | H82: 双Type c及两个Typec接口 | I82: N150(6W) | J82: 16G+0 | K82: AX101.D2WG | L82: 缺货 | M82: 3.1 | N82: 3.2334272 | O82: 12.830529 | P82: =Q82/E82/1.13 -> 2.9412128 | Q82: 23.83 | R82: =SUM(L82:P82) -> 22.105169 | S82: LPDDR5X-496球16G | T82: 双Type c及两个接口；MP86941*3pcs;IT5570E
D83: 20250407 | E83: 7.17 | F83: A.F.M.2500676-OOC | G83: SKU8 | H83: 双Type c及两个Typec接口 | I83: N150(6W) | J83: 16G+0 | K83: AX101.D2WG | L83: 缺货 | M83: 3.1 | N83: 3.2334272 | O83: 12.938376 | P83: =Q83/E83/1.13 -> 2.9412128 | Q83: 23.83 | R83: =SUM(L83:P83) -> 22.213016 | S83: LPDDR5X-496球16G | T83: 双Type c及两个接口；MP86941*3pcs；IT5570E；MP2964GQKT;ALC269Q
D84: 20250427 | E84: 7.17 | F84: A.F.M.2500693-OOC | G84: SKU9 | H84: 双Type c及两个Typec接口 | I84: N150(6W) | J84: 16G+0 | K84: AX101.D2WG | L84: 缺货 | M84: 3.1 | N84: 3.2334272 | O84: 12.735712 | P84: =Q84/E84/1.13 -> 2.9412128 | Q84: 23.83 | R84: =SUM(L84:P84) -> 22.010352 | S84: LPDDR5X-496球16G | T84: 双Type c及两个接口；MP86941*3pcs；IT5570E；MP2964GQKT;ALC269Q
B85: DNN11(8L+HDI+OSP) | D85: 20240116 | E85: 7.17 | F85: A.F.M.2301315-MP | G85: SKU5 | H85: Type c | I85: N100(6W) | J85: 8G+0 | K85: 9560.D2WG | L85: 缺货 | M85: 2.3 | N85: 2.9904129 | O85: =55.2/E85/1.13 -> 6.8130485 | P85: =Q85/E85/1.13 -> 0.38490632 | Q85: =22.36/E85 -> 3.1185495 | R85: =SUM(L85:P85) -> 12.488368 | S85: LPDDR5-496球8G | T85: DDR使用spectek暂无价格；单Type c; | U85: .
D86: 20240116 | E86: 7.17 | F86: A.F.M.2301316-MP | G86: SKU6 | H86: Type c | I86: N200(6W) | J86: 12G+64G | K86: AX101.D2WG | L86: 缺货 | M86: 3.1 | N86: 2.9904129 | O86: =55.2/E86/1.13 -> 6.8130485 | P86: =Q86/E86/1.13 -> 0.38490632 | Q86: =22.36/E86 -> 3.1185495 | R86: =SUM(L86:P86) -> 13.288368 | S86: 时创意/LPDDR5-496球12G | T86: DDR使用Spectek；单Type c;；EMMC停产中待验新料暂无价格 | U86: .
D87: 20240116 | E87: 7.17 | F87: A.F.M.2301317-MP | G87: SKU7 | H87: Type c | I87: N300(7W) | J87: 16G+128G | K87: AX201.D2WG | L87: 缺货 | M87: 6 | N87: 2.9904129 | O87: 16.116611 | P87: =Q87/E87/1.13 -> 2.7252194 | Q87: 22.08 | R87: =SUM(L87:P87) -> 27.832243 | S87: 时创意/LPDDR5-496球16G | T87: DDR使用Spectek；单Type c;含有加密IC TPM;含有HUSB238；；EMMC停产中待验新料暂无价格 | U87: .
D88: 20250423 | E88: 7.17 | F88: A.F.M.2400190-MP | G88: SKU8 | H88: Type c(两个接口) | I88: N200(6W) | J88: 8G+0 | K88: AX211.D2WG | L88: 缺货 | M88: 8 | N88: 2.9696461 | O88: 9.923997 | P88: =Q88/E88/1.13 -> 2.7252194 | Q88: 22.08 | R88: =SUM(L88:P88) -> 23.618863 | S88: LPDDR5-496球8G | T88: DDR使用Spectek暂无价格；单Typec C IC及两个接口; | U88: .
D89: 20250423 | E89: 7.17 | F89: A.F.M.2400478-MP | G89: SKU10 | H89: Type c(两个接口) | I89: N200(6W) | J89: 8G+0 | K89: AX211.D2WG | L89: 缺货 | M89: 8 | N89: 2.9696461 | O89: 9.8705838 | P89: =Q89/E89/1.13 -> 2.7252194 | Q89: 22.08 | R89: =SUM(L89:P89) -> 23.565449 | S89: LPDDR5-496球8G | T89: DDR使用Spectek暂无价格；单Typec C IC及两个接口;
D90: 20240819 | E90: 7.17 | F90: A.F.M.2401062-MP | G90: SKU11 | H90: Non Type c(两个接口) | I90: N100(6W) | J90: 4G+0 | K90: 61821CE | L90: 缺货 | M90: 1.6379015 | N90: 2.9904129 | O90: 9.2385934 | P90: =Q90/E90/1.13 -> 2.7252194 | Q90: 22.08 | R90: =SUM(L90:P90) -> 16.592127 | S90: LPDDR5-496球4G | T90: DDR使用镁光替换Spectek；无Typec C IC及两个接口;
D91: 20240819 | E91: 7.17 | F91: A.F.M.2401063-MP | G91: SKU12 | H91: Non Type c(一个接口) | I91: N100(6W) | J91: 4G+0 | K91: 61821CE | L91: 缺货 | M91: 1.6379015 | N91: 2.9904129 | O91: 8.7172009 | P91: =Q91/E91/1.13 -> 2.7252194 | Q91: 22.08 | R91: =SUM(L91:P91) -> 16.070735 | S91: LPDDR5-496球4G | T91: DDR使用镁光替换Spectek；无Typec C IC及一个接口;
D92: 20240819 | E92: 7.17 | F92: A.F.M.2401064-MP | G92: SKU13 | H92: Type c(两个接口) | I92: N100(6W) | J92: 12G+128G | K92: AX101.D2WG | L92: 缺货 | M92: 3.1 | N92: 2.9904129 | O92: 10.144633 | P92: =Q92/E92/1.13 -> 2.7252194 | Q92: 22.08 | R92: =SUM(L92:P92) -> 18.960265 | S92: 时创意/LPDDR5-496球12G | T92: DDR使用海力士；单Typec C IC及两个接口;；EMMC停产中待验新料暂无价格
D93: 20240913 | E93: 7.17 | F93: A.F.M.2401455-MP | G93: SKU14 | H93: Type c(两个接口) | I93: N200(6W) | J93: 12G+128G | K93: AX101.D2WG | L93: 缺货 | M93: 3.1 | N93: 3.0072366 | O93: 10.14024 | P93: =Q93/E93/1.13 -> 2.7252194 | Q93: 22.08 | R93: =SUM(L93:P93) -> 18.972696 | S93: 时创意/LPDDR5-496球12G | T93: DDR使用三星(库存)；单Typec C IC及两个接口;；EMMC停产中待验新料暂无价格
B94: DNN11S(8L+OSP+通孔) | D94: 20250703 | E94: 7.17 | F94: A.F.M.2401059-MP | G94: SKU9 | H94: Non Type c(一个接口) | I94: N100(6W) | J94: 0+64G | K94: 61821CE | L94: 39 | M94: =13.4/E94/1.13 -> 1.6538922 | N94: =25.5/E94/1.13 -> 3.1473322 | O94: =25.54/E94/1.13 -> 3.1522692 | P94: =20.1/E94/1.13 -> 2.4808383 | R94: =SUM(L94:P94) -> 49.434332 | S94: 时创意/条子 | T94: 无Type C IC及1个接口；SN6140;MP86941*2PCS;IT5570E;MP2964GQKT
D95: 20240906 | E95: 6.8309 | F95: A.F.M.2401084-MP | G95: SKU10 | H95: Type c(两个Type c个接口) | I95: N100(6W) | J95: 0+0 | K95: AX211.D2WG | L95: 缺货 | M95: 7.5 | N95: =25.5/E95/1.13 -> 3.3035722 | O95: 14.23 | P95: =20.1/E95/1.13 -> 2.6039922 | R95: =SUM(L95:P95) -> 27.637564 | S95: 条子 | T95: 单Type C IC及2个接口；
D96: 46135 | E96: 6.8226 | F96: A.F.M.2501814 | G96: SKU21 | H96: 单TYPE-C IC+单TYPE-C座 | K96: AX101.D2WG.NV | M96: 3.1 | N96: =25.5/E96/1.13 -> 3.3075912 | O96: 11.15 | P96: =20.1/E96/1.13 -> 2.6071601 | R96: =SUM(L96:P96) -> 20.164751 | S96: 条子
D97: 46253 | E97: 6.75 | F97: A.F.M.2400885 | K97: - | L97: 现询 | M97: - | N97: =51.02/E97/1.13*1.05 -> 7.0234022 | O97: 14.1 | P97: =20.1/E97/1.13 -> 2.6352016 | R97: =SUM(L97:P97) -> 23.758604
D98: 20240727 | E98: 6.901 | F98: A.F.M.2401129-MP | G98: SKU11 | H98: Type c(一个Type c个接口) | I98: N100(6W) | J98: 0+0 | K98: 61821CE | L98: 缺货 | M98: 1.6379015 | N98: =25.5/E98/1.13 -> 3.2700147 | O98: 10.948401 | P98: =20.1/E98/1.13 -> 2.577541 | R98: =SUM(L98:P98) -> 18.433858 | S98: LPDDR5X 8GB*2+256UFS*1 | T98: 单Type C IC及1个接口；
D99: 20240826 | E99: 7.17 | F99: A.F.M.2503155 | G99: SKU12 | H99: Type c(一个Type c个接口) | I99: N100(6W) | J99: 0+128G | K99: 9560.D2WG | L99: 缺货 | M99: 2.3 | N99: =25.5/E99/1.13 -> 3.1473322 | O99: 10.816402 | P99: =20.1/E99/1.13 -> 2.4808383 | R99: =SUM(L99:P99) -> 18.744573 | S99: LPDDR4X 8GB*1+256UFS*1 | T99: 单Type C IC及1个接口；；EMMC停产中待验新料暂无价格
D100: 20240826 | E100: 7.17 | F100: A.F.M.2401446-MP | G100: SKU13 | H100: Type c(一个Type c个接口) | I100: N100(6W) | J100: 0+64G | K100: AX101.D2WG | L100: 缺货 | M100: 3.1 | N100: =25.5/E100/1.13 -> 3.1473322 | O100: 11.014167 | P100: =20.1/E100/1.13 -> 2.4808383 | R100: =SUM(L100:P100) -> 19.742338 | S100: 全功能带RJ45, 128Mb ,ROM，EC:CSCS2010RBR6NR,CODEC: ALC897 | T100: 单Type C IC及1个接口；；EMMC停产中待验新料暂无价格
D101: 20240826 | E101: 7.17 | F101: A.F.M.2401447-MP | G101: SKU14 | H101: Type c(一个Type c个接口) | I101: N100(6W) | J101: 0+64G | K101: AX101.D2WG | L101: 缺货 | M101: 3.1 | N101: =25.5/E101/1.13 -> 3.1473322 | O101: 10.967781 | P101: =20.1/E101/1.13 -> 2.4808383 | R101: =SUM(L101:P101) -> 19.695951 | S101: 群联/条子 | T101: 单Type C IC及1个接口；
...

Sheet EVT PVT大核 E BOM
B1: 1月份汇率：7.01 | N1: 现询 | O1: 现询 | V1: pcb为普通材质OSP工艺，如用特殊材质请单独核;CPU;DDR;SSD;EMMC;WIFI请按需求选配 | W1: - | X1: 类型 | Y1: 型号 | Z1: 美金单项单价 | AB1: - | AC1: 类型 | AD1: 型号 | AE1: 美金单项单价
W2: - | X2: TYPC IC | Y2: ANX7447QN | Z2: 0.64 | AB2: - | AC2: 加密IC TPM | AD2: 9672 | AE2: 1.05
W3: - | Y3: CYPD6228 | Z3: 1.7769148 | AB3: - | AC3: 电量计 | AD3: CW2217 | AE3: 0.23
W4: - | Y4: CYPD6227 | Z4: 1.8079 | AB4: - | AC4: 雷电IC | AD4: 8040 | AE4: 2.948
W5: - | Y5: ASL2330AN | Z5: 0.52 | AB5: - | AD5: 9040 | AE5: 3.054
AB6: -
B7: 机型 | C7: 日期 | D7: 原汇率 | E7: 更新汇率 | F7: 料号 | G7: SKU | H7: Type c | I7: 功率 | J7: CPU/DDR一体式 | K7: 配置 | L7: WIFI | M7: CPU | N7: DDR | O7: EMMC | P7: WIFI | Q7: PCB | R7: Others | S7: SMT | T7: TTL | U7: EMMC/DDR | V7: 备注 | AB7: -
B8: DP67C（10L+通孔+OSP) | C8: 20250805 | E8: 7.13 | F8: A.F.M.2501922-EVT | G8: SKU1 | H8: Type c(两个Type c接口)(CYPD6228) | I8: U-15W | L8: 按需选配 | M8: 按需选配 | N8: 按需选配 | P8: 按需选配 | Q8: =26.1/E8/1.13 -> 3.2394593 | R8: =13.9317679638334+0.23 -> 14.161768 | S8: 4 | T8: =SUM(M8:S8) -> 21.401227 | U8: LPDDR5X-315球6G*2 | V8: 全功能(CYPD6228);含CW2217
B9: DNTU146A(8L+通孔+OSP) | C9: 20250825 | D9: 7.17 | E9: A.F.M.2401621-MP | F9: A.F.M.2502045-EVT | G9: SKU1 | H9: 双Type c及含两个Type c接口((ANX7447QN)) | I9: U-15W | L9: WD_RTL8821CE | M9: 按需选配 | P9: 按需选配 | Q9: =32.97/E9/1.13 -> #VALUE! | R9: =10.8998456682524+1.05+0.23 -> 12.179846 | S9: 4 | T9: =SUBTOTAL(9,K9:S9) -> #VALUE! | U9: 条子 | V9: 全功能(ANX7447QN)；含加密IC TPM（9672）含CW2217
C10: 20250825 | D10: 7.17 | E10: A.F.M.2401623-MP | F10: A.F.M.2502046-EVT | G10: SKU2 | H10: 双Type c及含两个Type c接口(ASL2330AN) | I10: H-28W | L10: CDW-61821CE | M10: 按需选配 | P10: 按需选配 | Q10: =32.97/E10/1.13 -> #VALUE! | R10: =12.8249086039597+1.05+0.23 -> 14.104909 | S10: 4 | T10: =SUBTOTAL(9,K10:S10) -> #VALUE! | U10: 条子 | V10: 全功能(ASL2330AN);含加密ic tpm（9672）含CW2217
C11: 20250825 | D11: 7.17 | E11: 7.13 | F11: A.F.M.2502047-EVT | G11: SKU3 | H11: 双Type c及含两个Type c接口((ANX7447QN)) | I11: H-45W | L11: CDW-61822CE | M11: 按需选配 | P11: 按需选配 | Q11: =32.97/E11/1.13 -> 4.0921446 | R11: =13.241571938046+1.05 -> 14.291572 | S11: 4 | T11: =SUBTOTAL(9,K11:S11) -> 22.383717 | U11: 条子 | V11: 全功能(ANX7447QN)；含加密ic tpm（9672）；含CW2217
B12: DNTU146(8L+通孔+OSP) | C12: 20250613 | D12: 7.19 | E12: 7.13 | F12: A.F.M.2501238-EVT | G12: SKU1 | H12: 单Type c及含两个Type c接口(ANX7447QN) | I12: U-15W | K12: 0+0 | L12: 61821CE | M12: 按需选配 | P12: 按需选配 | Q12: =35.53/E12/1.13 -> 4.4098847 | R12: 10.435899 | S12: =22.5/E12 -> 3.1556802 | T12: =SUBTOTAL(9,K12:S12) -> 18.001464 | U12: 条子 | V12: 全功能(ANX7447QN)；
C13: 20250613 | D13: 7.19 | E13: 7.13 | F13: A.F.M.2501239-EVT | G13: SKU2 | H13: 双Type c及含两个Type c接口(ANX7447QN) | I13: H-45W | K13: 0+0 | L13: AX101.D2WG | M13: 按需选配 | P13: 按需选配 | Q13: =35.53/E13/1.13 -> 4.4098847 | R13: 13.971454 | S13: =22.5/E13 -> 3.1556802 | T13: =SUBTOTAL(9,K13:S13) -> 21.537019 | U13: 条子 | V13: 全功能(ANX7447QN)；
C14: 20250613 | D14: 7.19 | E14: 7.13 | F14: A.F.M.2501369-EVT | G14: SKU3 | H14: 双Type c及含两个Type c接口(ANX7447QN) | I14: H-28W | K14: 0+0 | L14: 8852BE | M14: 按需选配 | P14: 按需选配 | Q14: =35.53/E14/1.13 -> 4.4098847 | R14: 13.209955 | S14: =22.5/E14 -> 3.1556802 | T14: =SUBTOTAL(9,K14:S14) -> 20.77552 | U14: 条子 | V14: 全功能(ANX7447QN)；
B15: LN89(8L+OSP+HDI) | C15: 20240511 | D15: 7.22 | E15: 7.19 | F15: A.F.M.2400361-EVT | G15: SKU1-8L | H15: Type c | I15: Q49M/Q49N(研发样品) | K15: 0+0 | L15: - | M15: - | N15: - | O15: - | P15: - | Q15: =39.28/E15/1.13 -> 4.83464 | R15: 23.384548 | S15: 4.3 | T15: =SUM(M15:S15) -> 32.519188 | U15: 条子 | V15: 研发样品CPU无价格；单Type c IC/两个接口;含有华邦512 Mbit flash;含有瑞萨*RAA225019CRGBM#HA0 4pcs/RAA225020RGNP#HA0 1pcs | W15: 。
C16: 20240511 | D16: 7.22 | E16: 7.19 | F16: A.F.M.2400362-EVT | G16: SKU2-8L/10L | H16: Type c | I16: Q49L/Q49M/Q49P (研发样品) | K16: 0+0 | L16: - | M16: - | N16: - | O16: - | P16: - | Q16: 5.3 | R16: 34.6937 | S16: 4.3 | T16: =SUM(M16:S16) -> 44.2937 | U16: 条子 | V16: 研发样品CPU无价格；单Type c IC/两个接口;含有加密IC TPM;含有武汉新芯256Mbit flash;含有瑞萨*RAA225019CRGBM#HA0 4pcs/RAA225020RGNP#HA0 1pcs；含有：卓运CW8602 解BUG IC;含有微芯科技PAC1934T | W16: 。
C17: 20240905 | D17: 7.11 | E17: 7.19 | F17: A.F.M.2400798-DVT | G17: SKU10-8L | H17: Type c(两个Type c接口) | I17: Q49M/Q5HF/Q5HU(研发样品) | K17: 0+0 | L17: - | M17: - | N17: - | O17: - | P17: - | Q17: =39.28/E17/1.13 -> 4.83464 | R17: 22.687832 | S17: 4.3 | T17: =SUM(M17:S17) -> 31.822472 | U17: 条子 | V17: 研发样品CPU无价格；单Type c IC及两个接口;含有华邦256Mbit flash;含有瑞萨*RAA225019CRGBM#HA0 4pcs/RAA225020RGNP#HA0 1pcs； | W17: 。
C18: 20240905 | D18: 7.11 | E18: 7.19 | F18: A.F.M.2400799-DVT | G18: SKU11-8L | H18: Type c(两个Type c接口) | I18: Q49M/Q5HF/Q5HU(研发样品) | K18: 0+0 | L18: - | M18: - | N18: - | O18: - | P18: - | Q18: =39.28/E18/1.13 -> 4.83464 | R18: 26.691496 | S18: 4.3 | T18: =SUM(M18:S18) -> 35.826136 | U18: 条子 | V18: AMOLED;研发样品CPU无价格；单Type c IC及两个接口;含有加密IC TPM;含有华邦256Mbit flash;含有瑞萨*RAA225019CRGBM#HA0 4pcs/RAA225020RGNP#HA0 1pcs； | W18: 。
C19: 20240913 | D19: 7.11 | E19: 7.19 | F19: A.F.M.2400926-PVT | G19: SKU12-8L | H19: Type c(两个Type c接口) | I19: Q49L/Q5HU/Q5JC/Q5JU/Q5H7(研发样品) | K19: 0+0 | L19: - | M19: - | N19: - | O19: - | P19: - | Q19: =39.28/E19/1.13 -> 4.83464 | R19: 22.31946 | S19: 4.3 | T19: =SUM(M19:S19) -> 31.4541 | U19: 条子 | V19: 研发样品CPU无价格；单Type c IC及两个接口;含有华邦256Mbit flash;含有瑞萨*RAA225019CRGBM#HA0 4pcs/RAA225020RGNP#HA0 1pcs；
C20: 20240913 | D20: 7.11 | E20: 7.19 | F20: A.F.M.2400927-PVT | G20: SKU13-8L | H20: Type c(两个Type c接口) | I20: Q49L/Q5HU/Q5JC/Q5JU/Q5H7(研发样品) | K20: 0+0 | L20: - | M20: - | N20: - | O20: - | P20: - | Q20: =39.28/E20/1.13 -> 4.83464 | R20: 22.594335 | S20: 4.3 | T20: =SUM(M20:S20) -> 31.728975 | U20: 条子 | V20: 研发样品CPU无价格；单Type c IC及两个接口;含有华邦256Mbit flash;含有瑞萨*RAA225019CRGBM#HA0 4pcs/RAA225020RGNP#HA0 1pcs；
C21: 20240913 | D21: 7.11 | E21: 7.19 | F21: A.F.M.2401580-PVT | G21: SKU14-8L | H21: Type c(两个Type c接口) | I21: Q49L/Q5HU/Q5JC/Q5JU/Q5H7(研发样品) | K21: 0+0 | L21: - | M21: - | N21: - | O21: - | P21: - | Q21: =39.28/E21/1.13 -> 4.83464 | R21: 26.096544 | S21: 4.3 | T21: =SUM(M21:S21) -> 35.231184 | U21: 条子 | V21: 研发样品CPU无价格；单Type c IC及两个接口;含有加密IC TPM;含有华邦256Mbit flash;含有瑞萨*RAA225019CRGBM#HA0 4pcs/RAA225020RGNP#HA0 1pcs；
C22: 20241104 | D22: 7.11 | E22: 7.19 | F22: A.F.M.2401873-PVT | G22: SKU15-8L | H22: Type c(两个Type c接口) | I22: Q5JC(研发样品)做客供 | K22: 0+0 | L22: - | M22: - | N22: - | O22: - | P22: - | Q22: =39.28/E22/1.13 -> 4.83464 | R22: 22.20604 | S22: 4.3 | T22: =SUM(M22:S22) -> 31.34068 | U22: 条子 | V22: CPU走客供无价格；单Type c IC及两个接口;含有华邦256Mbit flash;含有瑞萨*RAA225019CRGBM#HA0 4pcs/RAA225020RGNP#HA0 1pcs；
C23: 20250305 | D23: 7.25 | E23: 7.17 | F23: A.F.M.2500190-EVT | G23: SKU1 | H23: Type c(两个Type c接口) | I23: Q5JC(研发样品)做客供 | K23: 0+0 | L23: BE200.D2WG | M23: - | N23: - | O23: - | P23: 13 | Q23: 6.2644844 | R23: 38.371275 | S23: 4.3 | T23: =SUM(M23:S23) -> 61.93576 | U23: 条子 | V23: 单Type c IC及两个接口;RAA225019ERGBM#HA0*4PCS';W25R256JWEIQ;BMI323;含雷电ic*2pcs；含加密IC TPM;IT5570VG；
C24: 20250512 | D24: 7.24 | E24: 7.17 | F24: A.F.M.2500694-DVT | G24: SKU2 | H24: Type c(两个Type c接口) | J24: Ultra 7 258V(32GB) | K24: 0+0 | L24: BE200.D2WG | M24: 405 | P24: 13 | Q24: 6.2644844 | R24: 39.606842 | S24: 4.3 | T24: =SUM(M24:S24) -> 468.17133 | U24: 条子 | V24: 单Type c IC及两个接口;RAA225019ERGBM#HA0*4PCS';W25R256JWEIQ;BMI323;含雷电ic*2pcs；含加密IC TPM(英飞凌）;IT5570VG；TPA2016D2RTJR*2pcs;ALC897
C25: 20250512 | D25: 7.24 | E25: 7.17 | F25: A.F.M.2500695-DVT | G25: SKU3 | H25: Type c(两个Type c接口) | J25: Ultra 5 226V(16GB) | K25: 0+0 | L25: BE200.D2WG | M25: 260 | P25: 13 | Q25: 6.2644844 | R25: 38.427765 | S25: 4.3 | T25: =SUM(M25:S25) -> 321.99225 | U25: 条子 | V25: 单Type c IC及两个接口;RAA225019ERGBM#HA0*4PCS';W25R256JWEIQ;BMI323;含雷电ic*2pcs；含加密IC TPM（新唐）;IT5570VG；TPA2016D2RTJR*2pcs;ALC897
C26: 46105 | D26: 6.91
C27: 46105 | D27: 6.91
C28: 20250702 | D28: 7.17 | E28: A.F.M.2401762 | F28: A.F.M.2501519-PVT | G28: SKU4 | H28: Type c(两个Type c接口) | J28: Ultra 5 226V(16GB)(客供） | K28: 0+0 | L28: BE200.D2WG | M28: - | P28: =42.7/D28/1.13 -> 5.2702386 | Q28: 28.5 | R28: 38.164635 | S28: 4.3 | T28: =SUM(M28:S28) -> 76.234874 | U28: 条子 | V28: 单Type c IC及两个接口;ALC897;RAA225019ERGBM#HA0*4pcs；W25R256JWEIQ；含雷电ic*2pcs；BMI323；IT5570VG；含加密IC TPM;TPA2016D2RTJR*2pcs；YZ-2504280001/YZ-2504280002
C29: 20250702 | D29: 7.17 | E29: 7.17 | F29: A.F.M.2501520-PVT | G29: SKU5 | H29: Type c(两个Type c接口) | J29: Ultra 5 228V(32GB)(客供） | K29: 0+0 | L29: BE200.D2WG | M29: - | P29: 13 | Q29: 6.2644844 | R29: 37.49 | S29: 4.3 | T29: =SUM(M29:S29) -> 61.054484 | U29: 条子 | V29: 单Type c IC及两个接口;ALC897;RAA225019ERGBM#HA0*4pcs；W25R256JWEIQ；含雷电ic*2pcs；BMI323；IT5570VG；含加密IC TPM（新唐）;TPA2016D2RTJR*2pcs；YZ-2504280001/YZ-2504280002
C30: 20250820 | E30: 7.17 | F30: A.F.M.2502002-MP | G30: SKU6临时BOM | H30: Type c(两个Type c接口) | J30: Ultra 5 226V(16GB)(客供） | K30: 0+0 | L30: BE200.D2WG | M30: - | P30: 13 | Q30: =49.255/E30/1.13 -> 6.0792881 | R30: =37.7034212008221+0.5 -> 38.203421 | S30: =24.05/E30 -> 3.3542538 | T30: =SUM(M30:S30) -> 60.636963 | U30: 条子 | V30: 单Type c IC及两个接口;ALC897;含雷电ic*2pcs；BMI323；IT5570VG；含加密IC TPM（新唐）;TPA2016D2RTJR*2pcs；YZ-2504280001/YZ-2504280002;CW8601B;P25Q40SH
C31: 20250820 | E31: 7.17 | F31: A.F.M.2502003-MP | G31: SKU7临时BOM | H31: Type c(两个Type c接口) | J31: Ultra 5 228V(32GB)(客供） | K31: 0+0 | L31: BE200.D2WG | M31: - | P31: 13 | Q31: =49.255/E31/1.13 -> 6.0792881 | R31: =37.7034212008221+0.5 -> 38.203421 | S31: =24.05/E31 -> 3.3542538 | T31: =SUM(M31:S31) -> 60.636963 | U31: 条子 | V31: 单Type c IC及两个接口;ALC897;含雷电ic*2pcs；BMI323；IT5570VG；含加密IC TPM（新唐）;TPA2016D2RTJR*2pcs；YZ-2504280001/YZ-2504280002;CW8601B;P25Q40SH
B32: CN30 | G32: SKU1 | H32: Type c | I32: i5-8279U(28W) | K32: 0+0 | L32: 7265.D2WG | M32: 90 | N32: - | O32: - | P32: - | Q32: 5.7558313 | R32: 27.029711 | S32: 5 | T32: =SUM(M32:S32) -> 127.78554 | U32: 条子 | V32: 不含加密IC；WIFI停产无价格 | W32: .
G33: SKU2 | H33: Type c | I33: I5-10210U(15W) | K33: 0+0 | L33: 9461.D2WG | M33: - | N33: - | O33: - | P33: 3.3 | Q33: 5.7558313 | R33: 26.811406 | S33: 5 | T33: =SUM(M33:S33) -> 40.867238 | U33: 条子 | V33: CPU目前无价格； | W33: .
B34: CN58(8L+沉金+通孔) | G34: SKU1 | H34: Type c | I34: I5-8259U(28W) | K34: 0+0 | L34: 7265.D2WG | M34: 70 | N34: - | O34: - | P34: - | Q34: 4.6279862 | R34: 25.057247 | S34: 5 | T34: =SUM(M34:S34) -> 104.68523 | U34: 条子 | V34: 双Type-c;包含加密IC TPM；WIFI停产无价格 | W34: .
G35: SKU5 | H35: Type c | I35: i5-8279U(28W) | K35: 0+0 | L35: 9461.D2WG | M35: 90 | N35: - | O35: - | P35: 3.3 | Q35: 4.6279862 | R35: 23.124237 | S35: 5 | T35: =SUM(M35:S35) -> 126.05222 | U35: 条子 | V35: 双Type-c; | W35: .
G36: SKU6 | H36: Type c | I36: I5-10210U(15W) | K36: 0+0 | L36: 7265.D2WG | M36: - | N36: - | O36: - | P36: - | Q36: 16 | R36: 21.58177 | S36: 5 | T36: =SUM(M36:S36) -> 42.58177 | U36: 条子 | V36: TYPE-C:ANX7447QN-AC-R,电量计:CW2217,视频桥接：IT6113FN | W36: .
G37: SKU6(精简BOM) | H37: Type c | I37: I5-10210U(15W) | K37: 0+0 | L37: 7265.D2WG | M37: - | N37: - | O37: - | P37: - | Q37: 4.6279862 | R37: 19.366777 | S37: 5 | T37: =SUM(M37:S37) -> 28.994763 | U37: 条子 | V37: CPU目前无价格；单Type-c;；WIFI停产无价格 | W37: .
G38: SKU7 | H38: Type c | I38: I5-8259U(28W) | K38: 0+0 | L38: 7265.D2WG | M38: 70 | N38: - | O38: - | P38: - | Q38: 4.6279862 | R38: 22.883146 | S38: 5 | T38: =SUM(M38:S38) -> 102.51113 | U38: 条子 | V38: 双Type-c;WIFI停产无价格 | W38: .
F39: MP | G39: SKU9 | H39: Type c | I39: i5-8279U(28W) | K39: 0+0 | L39: 7265.D2WG | M39: 90 | N39: - | O39: - | P39: - | Q39: 4.6279862 | R39: 21.094631 | S39: 5 | T39: =SUM(M39:S39) -> 120.72262 | U39: 条子 | V39: 双Type-c;WIFI停产无价格 | W39: .
G40: A.P.10001098 BATT-CON_DB | Q40: 0.06475178 | R40: 0.29750697 | S40: 0.2 | T40: =SUM(M40:S40) -> 0.56225875 | W40: .
G41: A.F.D.2200018 RJ45 8111H DB | Q41: 0.93242563 | R41: 6.9136527 | S41: 0.4 | T41: =SUM(M41:S41) -> 8.2460784 | W41: .
B42: DP13A(10L+沉金+OSP) | G42: 临时BOM | H42: Type c(两个接口) | I42: I5-1235U(不带IPU)(15W) | K42: 4G*4+0 | L42: AX201.D2WG | M42: 100 | N42: - | O42: - | P42: 6 | Q42: 3.7567702 | R42: 18.919752 | S42: 5 | T42: =SUM(M42:S42) -> 133.67652 | U42: LPDDR4x-200球4G | V42: DDR使用三星；双Type c IC及两个Type c 接口；含有英特尔雷电IC;
E43: A.F.M.2503122 | G43: 小板临时BOM A.F.D.2400120 | Q43: 0.29576954 | R43: 1.1212979 | S43: 0.2 | T43: =SUM(M43:S43) -> 1.6170674
G44: 小板临时BOMA.F.D.2400121 | Q44: 0.15285568 | R44: 0.43492599 | S44: 0.2 | T44: =SUM(M44:S44) -> 0.78778168
B45: DP62(10L+HDI1+沉金) | C45: 20240305 | D45: 6.91 | E45: A.F.M.2600110 | F45: A.F.M.2400117-EVT | G45: SKU2 | H45: Type c(无接口) | I45: I5-1235U(不带IPU)(15W) | O45: - | P45: 6 | Q45: 5.239441 | R45: 19.221888 | S45: 3 | T45: =SUM(M45:S45) -> 33.461329 | U45: LPDDR5-496球8G | V45: DDR使用Spectek暂无价格；单Tpye c IC及无Type c接口;；含加密IC TPM;含有BMI323； | W45: .
C46: 20240305 | D46: 7.2 | E46: 7.24 | F46: A.F.M.2400118-EVT | G46: SKU3 | H46: Type c(无接口) | I46: I5-1235U(不带IPU)(15W) | K46: 8G*2+0 | L46: AX201.D2WG | M46: 100 | N46: - | O46: - | P46: 6 | Q46: 5.239441 | R46: 17.024706 | S46: 3 | T46: =SUM(M46:S46) -> 131.26415 | U46: LPDDR5-496球8G | V46: DDR使用Spectek暂无价格；单Tpye c IC及无Type c接口;； | W46: .
C47: 20240305 | D47: 7.2 | E47: 7.24 | F47: A.F.M.2400119-EVT | G47: SKU4 | H47: Type c(无接口) | I47: I7-1255U(不带IPU)(15W) | K47: 8G*2+0 | L47: AX201.D2WG | M47: - | N47: - | O47: - | P47: 6 | Q47: 5.239441 | R47: 17.406189 | S47: 3 | T47: =SUM(M47:S47) -> 31.64563 | U47: LPDDR5-496球8G | V47: DDR使用Spectek暂无价格；单Tpye c IC及无Type c接口;； | W47: .
C48: 20240815 | D48: 7.18 | E48: 7.24 | F48: A.F.M.2401076-PVT | G48: SKU5 | H48: Type c(无接口) | I48: I5-1235U(不带IPU)(15W) | K48: 8G*2+0 | L48: AX201.D2WG | M48: 100 | N48: - | O48: - | P48: 6 | Q48: 5.2540355 | R48: 18.080923 | S48: 3 | T48: =SUM(M48:S48) -> 132.33496 | U48: LPDDR5-496球8G | V48: DDR使用Spectek暂无价格；单Tpye c IC及无Type c接口;；
C49: 20250507 | D49: 7.24 | F49: A.F.M.2500758-PVT | G49: SKU6 | H49: Type c(无接口) | I49: I7-1255U(15W) | K49: 8G*2+0 | L49: AX201.D2WG | M49: - | N49: - | O49: - | P49: =31.73/7.13/1.13 -> 3.9382393 | Q49: 5.239441 | R49: =23.5/6.91 -> 3.4008683 | S49: 3 | T49: =SUM(M49:S49) -> 15.578549 | U49: LPDDR5-496球8G | V49: DDR使用Spectek暂无价格；单Tpye c IC及无Type c接口;；ALC269Q;MP86941*3pcs;IT5570;MP2964GQKT;
C50: 20250507 | D50: 7.24 | F50: A.F.M.2500893-PVT | G50: SKU7 | H50: Type c(无接口) | I50: I7-1255U(15W) | K50: 16G*2+0 | L50: AX201.D2WG | M50: - | N50: - | P50: 6 | Q50: 5.239441 | R50: =23.5/6.91 -> 3.4008683 | S50: 3 | T50: =SUM(M50:S50) -> 17.640309 | U50: LPDDR5-496球16G | V50: DDR使用Spectek；单Tpye c IC及无Type c接口;；ALC269Q;MP86941*3pcs;IT5570;MP2964GQKT;
C51: 20240815 | D51: 7.12 | E51: 7.24 | F51: A.F.D.2400192-PVT | G51: A.F.D.2400192 TYPEC DB | P51: =31.73/D51/1.13 -> 3.9437705 | Q51: 0.63931762 | R51: =23.5/6.91 -> 3.4008683 | S51: 0.2 | T51: =SUM(M51:S51) -> 8.1839564
C52: 20240314 | D52: 7.2 | E52: 7.24 | F52: A.F.D.2400050-EVT | G52: A.F.D.2400050 RJ45 DB | P52: =31.73/D52/1.13 -> 3.8999508 | Q52: 0.26579912 | R52: =23.5/6.91 -> 3.4008683 | S52: 0.4 | T52: =SUM(M52:S52) -> 7.9666183 | W52: .
C53: 20240314 | D53: 7.2 | E53: 7.24 | F53: A.F.D.2400051-EVT | G53: A.F.D.2400051 TYPEC DB | Q53: 0.57776993 | R53: 1.9890494 | S53: 0.2 | T53: =SUM(M53:S53) -> 2.7668193 | W53: .
B54: DN21A | G54: SKU1 | H54: Type c | I54: I7-1255U(不带IPU)(15W) | K54: 0+0 | L54: - | M54: - | N54: - | O54: - | P54: - | Q54: 4.0087921 | R54: 17.052114 | S54: 5 | T54: =SUM(M54:S54) -> 26.060906 | U54: 条子 | V54: 双Tpye c; | W54: .
G55: SKU2 | H55: Type c | I55: i7-1355U(15W) | K55: 0+0 | L55: - | M55: 190 | N55: - | O55: - | P55: - | Q55: 4.0087921 | R55: 16.99835 | S55: 5 | T55: =SUM(M55:S55) -> 216.00714 | U55: 条子 | V55: 双Tpye c; | W55: .
G56: A.F.D.2300069 USB DB | Q56: 0.43967397 | R56: 1.1618437 | S56: 0.2 | T56: =SUM(M56:S56) -> 1.8015177 | W56: .
B57: DN21B(8L+沉金+通孔) | C57: 20240513 | D57: 7.24 | E57: 7.17 | F57: A.F.M.2400641-EVT | G57: SKU1 | H57: Type c | I57: i3-1215U(不带IPU)(15W) | K57: 0+0 | L57: - | M57: 65 | N57: - | O57: - | P57: - | Q57: =45.045/E57/1.13 -> 5.5596697 | R57: 15.539757 | S57: 5 | T57: =SUM(M57:S57) -> 91.099427 | U57: 条子 | V57: 单Tpye c;
C58: 20240513 | D58: 7.24 | E58: 7.17 | F58: A.F.M.2400642-EVT | G58: SKU2 | H58: Type c | I58: I5-1235U(不带IPU)(15W) | K58: 0+0 | L58: - | M58: 100 | N58: - | O58: - | P58: - | Q58: =45.045/E58/1.13 -> 5.5596697 | R58: 16.730507 | S58: 5 | T58: =SUM(M58:S58) -> 127.29018 | U58: 条子 | V58: 单Tpye c;含加密IC TPM
C59: 20240513 | D59: 7.24 | E59: A.F.M.2501978 | F59: A.F.M.2400643-EVT | G59: SKU3 | H59: Type c | I59: i3-1215U(不带IPU)(15W) | K59: 0+0 | L59: - | M59: 65 | N59: - | O59: - | P59: - | Q59: =45.045/E59/1.13 -> #VALUE! | R59: 16.587934 | S59: 5 | T59: =SUM(M59:S59) -> #VALUE! | U59: 条子 | V59: 单Tpye c;
C60: 20240513 | D60: 6.9264 | E60: A.F.M.2502465 | F60: A.F.M.2400644-EVT | G60: SKU4 | H60: Type c | I60: I5-1235U(不带IPU)(15W) | K60: 0+0 | L60: - | M60: 100 | N60: - | O60: - | P60: - | Q60: 21.9 | R60: 17.858301 | S60: 5 | T60: =SUM(M60:S60) -> 144.7583 | U60: 条子 | V60: 单Tpye c;含加密IC TPM
C61: 20240924 | D61: 7.11 | E61: 7.17 | F61: A.F.M.2401603-PVT | G61: SKU5(CKD) | H61: Type c(两个Type c接口) | I61: i3-1215U(不带IPU)(15W) | K61: 0+0 | L61: AX201.NGWG | M61: 65 | N61: - | O61: - | P61: 6 | Q61: =45.045/E61/1.13 -> 5.5596697 | R61: 15.510294 | S61: 0.3 | T61: =SUM(M61:S61) -> 92.369964 | U61: 条子 | V61: 单Tpye c IC及两个Type c接口；
C62: 20240924 | D62: 7.11 | E62: 7.17 | F62: A.F.M.2401604-PVT | G62: SKU6(CKD) | H62: Type c(两个Type c接口) | I62: I5-1235U(不带IPU)(15W) | K62: 0+0 | L62: AX201.NGWG | M62: 100 | N62: - | O62: - | P62: 6 | Q62: =45.045/E62/1.13 -> 5.5596697 | R62: 15.510294 | S62: 0.3 | T62: =SUM(M62:S62) -> 127.36996 | U62: 条子 | V62: 单Tpye c IC及两个Type c接口；
C63: 20240924 | D63: 7.11 | E63: 7.17 | F63: A.F.M.2401605-PVT | G63: SKU7(CKD) | H63: Type c(两个Type c接口) | I63: I7-1255U(不带IPU)(15W) | K63: 0+0 | L63: AX201.NGWG | M63: - | N63: - | O63: - | P63: 6 | Q63: =45.045/E63/1.13 -> 5.5596697 | R63: 15.510294 | S63: 0.3 | T63: =SUM(M63:S63) -> 27.369964 | U63: 条子 | V63: 单Tpye c IC及两个Type c接口；
C64: 20240924 | D64: 7.11 | E64: 7.17 | F64: A.F.M.2401606-PVT | G64: SKU8(CKD) | H64: Type c(两个Type c接口) | I64: i3-1315U(不带IPU)(15W) | K64: 0+0 | L64: AX201.NGWG | M64: 70 | N64: - | O64: - | P64: 6 | Q64: =45.045/E64/1.13 -> 5.5596697 | R64: 15.510294 | S64: 0.3 | T64: =SUM(M64:S64) -> 97.369964 | U64: 条子 | V64: 单Tpye c IC及两个Type c接口；
C65: 20240924 | D65: 7.11 | E65: 7.17 | F65: A.F.M.2401607-PVT | G65: SKU9(CKD) | H65: Type c(两个Type c接口) | I65: i5-1335U(不带IPU)(15W) | K65: 0+0 | L65: AX201.NGWG | M65: 145 | N65: - | O65: - | P65: 6 | Q65: =45.045/E65/1.13 -> 5.5596697 | R65: 15.510294 | S65: 0.3 | T65: =SUM(M65:S65) -> 172.36996 | U65: 条子 | V65: 单Tpye c IC及两个Type c接口；
C66: 20240924 | D66: 7.11 | E66: 7.17 | F66: A.F.M.2401608-PVT | G66: SKU10(CKD) | H66: Type c(两个Type c接口) | I66: i7-1355U(15W) | K66: 0+0 | L66: AX201.NGWG | M66: 190 | N66: - | O66: - | P66: 6 | Q66: =45.045/E66/1.13 -> 5.5596697 | R66: 15.510294 | S66: 0.3 | T66: =SUM(M66:S66) -> 217.36996 | U66: 条子 | V66: 单Tpye c IC及两个Type c接口；
C67: 20240924 | D67: 7.11 | E67: 7.17 | F67: A.F.M.2401609-PVT | G67: SKU11 | H67: Type c(两个Type c接口) | I67: i3-1315U(不带IPU)(15W) | K67: 0+0 | L67: - | M67: 70 | N67: - | O67: - | P67: - | Q67: =45.045/E67/1.13 -> 5.5596697 | R67: 15.777764 | S67: 5 | T67: =SUM(M67:S67) -> 96.337434 | U67: 条子 | V67: 单Tpye c IC及两个Type c接口；
C68: 20240924 | D68: 7.11 | E68: 7.17 | F68: A.F.M.2401610-PVT | G68: SKU12 | H68: Type c(两个Type c接口) | I68: i5-1335U(不带IPU)(15W) | K68: 0+0 | L68: - | M68: 145 | N68: - | O68: - | P68: - | Q68: =45.045/E68/1.13 -> 5.5596697 | R68: 15.937532 | S68: 5 | T68: =SUM(M68:S68) -> 171.4972 | U68: 条子 | V68: 单Tpye c IC及两个Type c接口；
C69: 20250814 | D69: 7.11 | E69: 7.17 | F69: A.F.M.2401719-PVT | G69: SKU13(CKD) | H69: Type c(两个Type c接口) | I69: i7-1355U(15W) | K69: 0+0 | L69: AX201.NGWG | M69: 190 | N69: - | O69: - | P69: 6 | Q69: =45.045/E69/1.13 -> 5.5596697 | R69: 15.550218 | S69: 0.3 | T69: =SUM(M69:S69) -> 217.40989 | U69: 条子 | V69: 单Tpye c IC及两个Type c接口；PCB为沉金材质低损耗TG150
C70: 20250424 | D70: 7.31 | E70: 7.24 | G70: 临时bom | H70: Type c(一个Type c接口) | I70: I5-1235U(不带IPU)(15W) | K70: 0+0 | M70: 100 | Q70: 4.1960548 | R70: 14.910949 | S70: 5 | T70: =SUM(M70:S70) -> 124.107 | U70: 条子 | V70: MP86941*3pcs；IT5570E；IT66318FN；MP2964GQKT；含加密IC TPM;
